Workbook

Sheet Call Sheet
A1: CALL SHEET - work top to bottom
A2: Everything you need to dial, in priority order. Rows 1-5 are the real prospects; call those first and get ONE quote in hand before touching the rest - a concrete number transforms every later conversation. Open every call with the question in column L: the larger box needs a 171 x 75 in blank, and a 75 in wide blank is the single most likely disqualifier on this job. Ten seconds, and it saves you twenty minutes. Scripts and a paste-ready RFQ email are on the 'Outreach Scripts' tab. Fill in the YELLOW columns as you go. Contact details verified 26 Aug 2026 - see 'Verification Log' for exactly what was checked against what.
A4: # | B4: Call? | C4: Company | D4: PHONE | E4: Ask for | F4: EMAIL | G4: Website / RFQ form | H4: Contact data checked? | I4: Plant open? | J4: Miles | K4: Hours | L4: The ONE question to open with | M4: Est. MOQ | N4: Est. $/box SKU 1 | O4: Est. $/box SKU 2 | P4: Date called | Q4: Spoke to | R4: Outcome | S4: Quote $ SKU 1 | T4: Quote $ SKU 2 | U4: Freight $/unit | V4: MOQ quoted | W4: Lead time | X4: Notes
A5: 1 | B5: PHONE | C5: Commercial-Wagner, Inc. | D5: (410) 522-0900 | E5: Sales / estimating - then ask for the Northern Virginia rep | F5: -- none published -- | G5: commercialwagner.com | H5: Not yet verified | I5: Not yet verified | J5: 65 | K5: call 8-5 ET | L5: Can you run a 75 in wide blank in one piece, and can you stitch a double-wall RSC at 36 in depth? | M5: 250 - 500 | N5: ='Cost Model'!$I$6/1000*230.0 -> 9.904375 | O5: ='Cost Model'!$I$7/1000*230.0 -> 20.514323
A6: 2 | B6: PHONE + EMAIL | C6: Atlas Container Corp. | D6: (410) 551-6300 | E6: Inside sales. Christine Beeler (cbeeler@atlascontainer.com) is a named rep. | F6: info@atlascontainer.com | G6: atlascontainer.com | H6: Not yet verified | I6: Not yet verified | J6: 62 | K6: call 8-5 ET | L6: Your site says orders as small as 100 - does that hold for a 46 x 39 x 36 double-wall box, and does a 75 in wide blank run on your equipment? | M6: 100 | N6: ='Cost Model'!$I$6/1000*230.0 -> 9.904375 | O6: ='Cost Model'!$I$7/1000*230.0 -> 20.514323
A7: 3 | B7: EMAIL / FORM then PHONE | C7: Green Bay Packaging - Baltimore Division | D7: (410) 785-2233 | E7: Baltimore division inside sales | F7: -- none published -- | G7: gbp.com/locations/baltimore | H7: Not yet verified | I7: Not yet verified | J7: 72 | K7: call 8-5 ET | L7: Can you certify a BCT figure for a 46.5 x 39.5 x 36.5 in box in 48ECT DW, and run ISTA on it in your on-site lab? | M7: 1,000 - 2,500 | N7: ='Cost Model'!$I$6/1000*195.0 -> 8.3971875 | O7: ='Cost Model'!$I$7/1000*195.0 -> 17.392578
A8: 4 | B8: EMAIL then PHONE | C8: Columbia Container Corp. | D8: (410) 467-1400 | E8: Quotes desk | F8: quotes@columbiacontainer.net | G8: columbiacontainer.net | H8: Not yet verified | I8: Not yet verified | J8: 65 | K8: call 8-5 ET | L8: You advertise custom flute and liner combinations - which build would you use to hit 48ECT DW, and what caliper does it come out at? | M8: 250 - 500 | N8: ='Cost Model'!$I$6/1000*240.0 -> 10.335 | O8: ='Cost Model'!$I$7/1000*240.0 -> 21.40625
A9: 5 | B9: PHONE (site was flaky) | C9: Packaging Services Industries, Inc. (PSI) | D9: (301) 223-8726 | E9: Northern Virginia / Manassas territory rep | F9: info@psimd.com | G9: psimd.com | H9: Not yet verified | I9: Not yet verified | J9: 62 | K9: call 8-5 ET | L9: Will you hold a blanket order with monthly releases, and can your engineered-foam side quote dunnage for a 6 in clearance envelope? | M9: 500 - 1,000 | N9: ='Cost Model'!$I$6/1000*210.0 -> 9.043125 | O9: ='Cost Model'!$I$7/1000*210.0 -> 18.730469
A10: 6 | B10: PHONE | C10: Keystone Sheets (Buckeye Corrugated / Corrugated Partners Group) | D10: (717) 287-1764 | E10: Inside sales | F10: -- none published -- | G10: keystonesheets.com | H10: Not yet verified | I10: Not yet verified | J10: 78 | K10: call 8-5 ET | L10: Can you supply 48ECT double wall in 75 in wide sheets, and what is your minimum run? | M10: Skid / bundle minimum | N10: n/a | O10: n/a
A11: 7 | B11: CORPORATE FORM | C11: Smurfit Westrock - Baltimore South Box Plant | D11: -- none published -- | E11: Mid-Atlantic corrugated account team | F11: WEB FORM ONLY | G11: us.smurfitwestrock.com/locations | H11: Not yet verified | I11: Not yet verified | J11: 62 | K11: call 8-5 ET | L11: Is this plant still running, and will you quote 500-5,000/yr at all? | M11: 2,500 - 5,000+ | N11: ='Cost Model'!$I$6/1000*185.0 -> 7.9665625 | O11: ='Cost Model'!$I$7/1000*185.0 -> 16.500651
A12: 8 | B12: PHONE - or just drive over | C12: Craters & Freighters Northern Virginia | D12: (703) 796-0180 | E12: Sterling branch | F12: -- none published -- | G12: cratersandfreightersnorthernvirginia.com | H12: Not yet verified | I12: Not yet verified | J12: 4 | K12: 8:30am-5:00pm ET Mon-Fri | L12: Can you build me one of each as a fit-check prototype this week, and what would that cost? | M12: 1 | N12: n/a | O12: n/a
A13: 9 | B13: PHONE | C13: Atlantic Corrugated Box Company, Inc. | D13: (804) 231-4050 | E13: Inside sales | F13: -- none published -- | G13: acbc-inc.com | H13: Not yet verified | I13: Not yet verified | J13: 110 | K13: call 8-5 ET | L13: Can you run a 75 in wide double-wall blank, and what does freight to Sterling VA 20166 add per box? | M13: 250 - 500 | N13: ='Cost Model'!$I$6/1000*240.0 -> 10.335 | O13: ='Cost Model'!$I$7/1000*240.0 -> 21.40625
A14: 10 | B14: PHONE | C14: Richmond Corrugated Box Co., Inc. | D14: (804) 222-1300 | E14: Inside sales | F14: -- none published -- | G14: richmondcorrugated.com | H14: Not yet verified | I14: Not yet verified | J14: 112 | K14: 8:00am-5:00pm | L14: Do you run double wall, and what is the widest blank your equipment takes? | M14: 250 - 500 | N14: ='Cost Model'!$I$6/1000*240.0 -> 10.335 | O14: ='Cost Model'!$I$7/1000*240.0 -> 21.40625
A15: 11 | B15: CORPORATE FORM | C15: Smurfit Westrock - Richmond Box Plant | D15: -- none published -- | E15: Mid-Atlantic corrugated account team | F15: WEB FORM ONLY | G15: us.smurfitwestrock.com/locations | H15: Not yet verified | I15: Not yet verified | J15: 112 | K15: call 8-5 ET | L15: Same as Baltimore South - will you quote at 500-5,000/yr? | M15: 2,500 - 5,000+ | N15: ='Cost Model'!$I$6/1000*185.0 -> 7.9665625 | O15: ='Cost Model'!$I$7/1000*185.0 -> 16.500651
A17: DO NOT CALL
C18: Packaging Corp. of America (PCA) - Richmond Full-Line Plant | D18: 2000 Richmond Hwy, Richmond, VA 23224 | F18: DO NOT CALL - PCA announced permanent closure of this corrugated plant. Listed so it does not resurface from a stale directory.
C19: Kelly Box & Packaging | D19: Fort Wayne, IN - 570 miles | F19: REMOVED. It was on the earlier list purely as a die-cut specialist with an ISTA lab for the bridge panel. With the bridge out of scope there is no die-cutting on this job, and Green Bay Packaging provides an ISTA lab inside the radius.
C20: Uline / packagingprice.com and other catalogue distributors | D20: No Virginia plant | F20: NOT SUPPLIERS for this job - your sizes are non-stock. They ARE the price benchmark: the Cost Model tab back-calculates $/MSF from their published 48ECT and 275 lb test double-wall prices. Beat those numbers.
C21: SEO reseller / offshore broker sites (CustomBoxesZone, BoxLark, Branded Boxes, OXO, PakFactory) | D21: No plant | F21: EXCLUDED. They dominate search results for 'corrugated boxes Sterling/Ashburn/Dulles VA' but hold no converting asset in Virginia, will not certify 48ECT DW board, and cannot support first-article approval.

Sheet Outreach Scripts
A1: Outreach Scripts - paste-ready
A2: Phone opener, follow-up questions, voicemail, and a complete RFQ email. Fill the [BRACKETED] placeholders. The email body is deliberately a more complete spec than the drawings are - see the note on attachments below.
A4: PHONE - open with this
A5: "Hi - I'm sourcing two heavy-duty double-wall corrugated boxes, and I have one qualifying question before I take up your time. The larger box needs a blank roughly 171 by 75 inches. Can you run a 75-inch-wide blank in one piece?" WHY THIS OPENER: it is the single most likely disqualifier on this job, it takes ten seconds to answer, and it signals immediately that you know what you are buying. If the answer is no, thank them and move on - you have saved twenty minutes. If yes, continue with Q2-Q5 below.
A7: PHONE - then work through these
A8: Q2 BOARD "Can you do 48ECT kraft in heavy-duty double wall at that width, and will you certify actual ECT on a cert of compliance? Do you corrugate in house or buy sheets?" Q3 DIMS "Both boxes call out a not-to-exceed OUTSIDE dimension only half an inch over the INSIDE dimension. With your actual double-wall caliper, can you hold both at once? If not, which would you relax?" <- listen carefully, answers will differ Q4 MOQ "What's your minimum order quantity per SKU, and per release against a blanket order?" (Atlas Container publishes 100 - use that as your benchmark.) Q5 CLOSURE "At 46-1/2 by 39-1/2 by 36-1/2 in double wall, do you recommend taped, glued or stitched? Can you stitch at that depth?" THEN "What's your $/MSF, and can you quote freight to Sterling VA 20166 as a separate line?"
A10: VOICEMAIL - if you get the machine
A11: "Hi, this is [YOUR NAME] from [YOUR COMPANY], phone [YOUR NUMBER]. I'm sourcing two heavy-duty double-wall corrugated boxes - 48ECT, plain RSCs, no printing - at roughly 500 to 5,000 pieces a year each. The larger one needs a 75-inch-wide blank. I'd like to find out whether that runs on your equipment and get a quote. Best number is [YOUR NUMBER], or I can email the full spec over. Thanks very much." Keep it under 25 seconds. Leaving the 75-inch detail in the voicemail means whoever calls back has already checked, which saves you a round trip.
A13: EMAIL - subject line
A14: RFQ - two 48ECT double-wall RSCs, 500-5,000/yr - [YOUR COMPANY]
A16: EMAIL - body, paste as-is
A17: Hello, We are sourcing two corrugated shipping boxes and would like to request a quote. Both are plain RSCs - no inserts, no die-cutting, no printing. SKU 1 Style ................ RSC Board ................ 48ECT kraft, heavy-duty double wall Inside dimensions .... 39 x 20 x 32 in Outside dimensions ... NOT TO EXCEED 39.5 x 20.5 x 32.5 in Approx. blank ........ 119 x 52 in SKU 2 Style ................ RSC Board ................ 48ECT kraft, heavy-duty double wall Inside dimensions .... 46 x 39 x 36 in Outside dimensions ... NOT TO EXCEED 46.5 x 39.5 x 36.5 in Approx. blank ........ 171 x 75 in <-- please confirm you can run a 75 in wide blank in one piece, unspliced Annual volume: please quote price breaks at 500 / 1,000 / 2,500 / 5,000 pcs per year, per SKU. Please include in your response: 1. Unit price at each volume break, and your $/MSF so the two sizes can be compared on the same basis. 2. IMPORTANT - both boxes allow only 0.5 in total between the inside and the not-to-exceed outside dimensions. On an RSC the outside dimension is the inside plus two board thicknesses, so heavy-duty double wall at 0.28-0.31 in caliper would overrun the callout. With YOUR actual caliper, can you hold both constraints at once? If not, what do you propose to relax, and by how much? 3. Board build (liner weights and flute combination), certified ECT, and caliper. 4. Minimum order quantity per SKU, and minimum per release against a blanket order. 5. Recommended closure at the SKU 2 size - taped, glued or stitched - and whether you can stitch at 36 in depth. 6. Setup and any tooling charges, broken out separately from unit price. 7. Freight to Sterling, VA 20166 as a separate line item, plus boxes per pallet, pallet size, and pallets per truck. Both SKUs knock down to oversized flats (SKU 2 is roughly 86 x 75 in flat), so we need to compare on landed cost rather than unit price. 8. Lead time for first article and for repeat production, and how long the quote holds. 9. Certifications held (ISO 9001, FSC or SFI, BRCGS), and whether you have an in-house ISTA lab and can certify a BCT figure for each SKU. 10. We are open to equivalent alternatives. If a different flute combination, ECT or construction meets the same stacking performance for less at our volume, please quote that alongside and show the cost delta. We would also like one physical sample of each SKU before any first production run. Thank you - happy to answer any questions by phone. [YOUR NAME] [TITLE] [YOUR COMPANY] [PHONE] | [EMAIL]
... A22: HOW TO RUN THE OUTREACH
A23: Before you send anything | B23: Fill in the bracketed placeholders, and decide what you will say about volume. Quoting the full 500-5,000 range invites the top of it to be priced. If you have a realistic first-year number, give that as the committed volume and the rest as an option - you will get a keener price on a firm quantity than on a range.
A24: Attach or don't attach the drawings? | B24: If you attach the Rev C sheets, ANNOTATE THEM FIRST. Both sheets are titled BRIDGE and dimension a part you are no longer buying; only notes 2, 2.1 and 2.2 apply. Unannotated, you will get bridge pricing back and a confused estimator. Honestly, for two plain RSCs the email body above is a more complete spec than the drawings are - consider sending text only.
A25: Call or email? | B25: Call the independents (Commercial-Wagner, Atlas, Columbia, Richmond, Atlantic). Small sheet plants respond to a human voice and often quote same-week; an email into a general inbox can sit. Email the larger shops (Green Bay Packaging, PSI, Smurfit Westrock) where a written spec gets routed to an estimator. Where only a web form exists, submit the form AND call.
A26: Sequence them, don't blast them | B26: Call the top three first and get one real quote in hand before contacting the rest. A single concrete number transforms every later conversation, because you can ask the next shop to beat something specific rather than quote into a vacuum.
A27: What a good quote looks like | B27: Unit price AND $/MSF, freight separated, ECT certified on a CoC, MOQ stated plainly, and a direct answer on the dimensional conflict. A quote with a single unit price and no $/MSF, no freight line and no caliper answer is not comparable to anything - go back and ask.
A28: The number to beat | B28: Uline sells a comparable 275 lb test (= 48 ECT) double-wall box at about $370/MSF at 1,000 pcs. That is retail, off the shelf, no minimum. Any converter quoting above that for a custom size at your volume is not trying. See the Cost Model tab.

Sheet Supplier Detail
A1: Supplier Detail - the full research record
A2: The Call Sheet is what you work from; this is the evidence behind it. Every capability claim traces to the 'Sources' tab, and every contact field to 'Verification Log'. Estimated prices are live formulas off the 'Cost Model' tab.
A4: # | B4: Tier | C4: Company | D4: Business model | E4: Street address | F4: City | G4: State | H4: ZIP | I4: Miles from IAD | J4: Drive time | K4: Phone | L4: Phone checked? | M4: Email | N4: Email checked? | O4: Website | P4: Named contacts found | Q4: Handles 75in blank (SKU 2) | R4: Est. MOQ | S4: MOQ reliability | T4: Est. $/MSF | U4: Est. $/box SKU 1 | V4: Est. $/box SKU 2 | W4: Price reliability | X4: Capability facts found | Y4: Why they fit | Z4: Watch-outs
A5: 1 | B5: A - Call first | C5: Commercial-Wagner, Inc. | D5: Independent sheet plant - 17 box-making machines, own truck fleet | E5: 4101 Ashland Ave | F5: Baltimore | G5: MD | H5: 21205 | I5: 65 | J5: 1 hr 15 min | K5: (410) 522-0900 | L5: Not yet verified | M5: none published | N5: Not yet verified | O5: commercialwagner.com | P5: None found | Q5: Likely - only shop advertising it | R5: 250 - 500 | S5: Inferred (plant class) | T5: 200 - 260 | U5: ='Cost Model'!$I$6/1000*230.0 -> 9.904375 | V5: ='Cost Model'!$I$7/1000*230.0 -> 20.514323 | W5: Estimate (modelled) | X5: See Qualification Matrix | Y5: Top pick. With the bridge gone the hardest requirement is SIZE: the SKU 2 blank is roughly 171 x 75 in, and Commercial-Wagner is the only shop here that explicitly advertises EXTRA-LARGE boxes plus taped, glued AND stitched construction. Stitching is the normal closure for a heavy-duty double-wall RSC at 46.5 x 39.5 x 36.5 in. 17 box-making machines means two very different SKUs route efficiently. They run their own fleet into Northern Virginia, which matters more than ever given Spec Flag SF-4 - these ship as oversized flats and freight is a top-3 cost driver. | Z5: No published email - RFQ web portal only, so this one is a phone call. No published certifications. Two sites (production + warehouse/fulfillment) so confirm which ships you.
A6: 2 | B6: A - Call first | C6: Atlas Container Corp. | D6: Independent converter (ESOP-reported), rotary + flatbed die cutting | E6: 8140 Telegraph Rd | F6: Severn | G6: MD | H6: 21144 | I6: 62 | J6: 1 hr 15 min | K6: (410) 551-6300 | L6: Not yet verified | M6: info@atlascontainer.com | N6: Not yet verified | O6: atlascontainer.com | P6: None found | Q6: MUST CONFIRM - potential disqualifier | R6: 100 | S6: PUBLISHED on their site | T6: 200 - 260 | U6: ='Cost Model'!$I$6/1000*230.0 -> 9.904375 | V6: ='Cost Model'!$I$7/1000*230.0 -> 20.514323 | W6: Estimate (modelled) | X6: See Qualification Matrix | Y6: The only supplier here with a PUBLISHED minimum - 'orders as small as 100 Qty' - a genuine advantage at the 500/yr end, and it lets you buy in small frequent releases instead of sitting on a year of inventory. Free custom design and physical samples means a no-cost first article. Founded 1968, easy single-truck run to Dulles. | Z6: Their advertised strengths were die-cutting-centric and that edge no longer applies. The real question is whether their press and folder-gluer take a 75 in wide blank - ask FIRST, it is potentially disqualifying for SKU 2 even though SKU 1 is comfortable anywhere.
A7: 3 | B7: A - Call first | C7: Green Bay Packaging - Baltimore Division | D7: Integrated mill-backed converter with in-house corrugator | E7: 11000 Gilroy Rd | F7: Hunt Valley | G7: MD | H7: 21031 | I7: 72 | J7: 1 hr 20 min | K7: (410) 785-2233 | L7: Not yet verified | M7: none published | N7: Not yet verified | O7: gbp.com/locations/baltimore | P7: None found | Q7: Yes - in-house corrugator | R7: 1,000 - 2,500 | S7: Inferred (mill-backed) | T7: 170 - 220 | U7: ='Cost Model'!$I$6/1000*195.0 -> 8.3971875 | V7: ='Cost Model'!$I$7/1000*195.0 -> 17.392578 | W7: Estimate (modelled) | X7: See Qualification Matrix | Y7: Promoted sharply by the scope change. Without a bridge, this job IS board and stacking strength, and GBP is the only shop in radius that controls both. In-house corrugator (they make the board rather than buy sheets, so a 75 in wide 48ECT double-wall sheet is a scheduling question not a special order), explicit DOUBLE WALL offering, in-house structural design, and an ON-SITE ISTA LABORATORY. BRCGS and SFI certified. For a 46.5 in box that gets stacked on pallets, documented ECT and BCT data is the deliverable that de-risks the programme. Likely the best $/MSF too. | Z7: Expect MOQ pressure and a push toward an annual contract - that is the trade for the best board price and the test lab. Ask whether they will hold finished goods and release monthly. FSC and ISO not listed (they hold SFI + BRCGS).
A8: 4 | B8: A - Call first | C8: Columbia Container Corp. | D8: Independent full-service converter, single Baltimore plant, 40+ yrs | E8: 4311 Erdman Ave | F8: Baltimore | G8: MD | H8: 21213 | I8: 65 | J8: 1 hr 15 min | K8: (410) 467-1400 | L8: Not yet verified | M8: quotes@columbiacontainer.net | N8: Not yet verified | O8: columbiacontainer.net | P8: None found | Q8: MUST CONFIRM | R8: 250 - 500 | S8: Inferred (plant class) | T8: 210 - 270 | U8: ='Cost Model'!$I$6/1000*240.0 -> 10.335 | V8: ='Cost Model'!$I$7/1000*240.0 -> 21.40625 | W8: Estimate (modelled) | X8: See Qualification Matrix | Y8: The best partner for the 'equivalent alternative' path you left open. They advertise custom FLUTE AND LINER COMBINATIONS, which is exactly the lever that decides whether you hit 48ECT cheaply, and - per Spec Flag SF-1 - which caliper you land on decides whether the not-to-exceed outside dimensions are achievable at all. Fastest published turnaround here (most orders in 3-5 business days). Their product list includes UN-rated boxes, and a shop doing UN work has the test discipline to certify ECT on a CoC. | Z8: Single plant = single point of failure; ask about contingency. Confirm max blank width for SKU 2. Certifications not published.
A9: 5 | B9: A - Call first | C9: Packaging Services Industries, Inc. (PSI) | D9: Integrated regional converter - 3 production plants + 1 dedicated corrugation plant | E9: 16461 Elliott Pkwy | F9: Williamsport | G9: MD | H9: 21795 | I9: 62 | J9: 1 hr 10 min | K9: (301) 223-8726 | L9: Not yet verified | M9: info@psimd.com | N9: Not yet verified | O9: psimd.com | P9: None found | Q9: Likely - dedicated corrugation plant | R9: 500 - 1,000 | S9: Inferred (multi-plant) | T9: 180 - 240 | U9: ='Cost Model'!$I$6/1000*210.0 -> 9.043125 | V9: ='Cost Model'!$I$7/1000*210.0 -> 18.730469 | W9: Estimate (modelled) | X9: See Qualification Matrix | Y9: Best combination of scale and proximity: 282,000 sq ft HQ, four plants including a dedicated corrugation plant, roughly 40 million sq ft of board per month, and they actively market into Manassas/NoVA. Two specific reasons they matter: they can hold a blanket order and release against it (smoothing 500-5,000/yr without inventory risk), and their engineered-foam capability covers the dunnage question in Spec Flag SF-2 - the boxes have a 6 in clearance envelope all round and nothing fills it. | Z9: Big-shop minimums are less flexible than Atlas on a 500-piece first run - get the MOQ explicitly. psimd.com returned HTTP 500 during research, so lead with the phone.
A10: 6 | B10: B - Board supply | C10: Keystone Sheets (Buckeye Corrugated / Corrugated Partners Group) | D10: SHEET FEEDER - sells corrugated sheets, not finished boxes | E10: 1465 Nitterhouse Dr | F10: Chambersburg | G10: PA | H10: 17201 | I10: 78 | J10: 1 hr 30 min | K10: (717) 287-1764 | L10: Not yet verified | M10: none published | N10: Not yet verified | O10: keystonesheets.com | P10: None found | Q10: Yes - 132 in corrugator | R10: Skid / bundle minimum | S10: Inferred (sheet feeder) | T10: Board only / n/a | W10: n/a - board only | X10: See Qualification Matrix | Y10: Strategic leverage, not a direct supplier - DO NOT expect a box price from them. Runs a 132 in BHS corrugator, reportedly the widest in the country capable of triple wall. Your SKU 2 blank needs a 75 in wide sheet in 48ECT double wall, wide enough that some sheet plants will call it a special order and price it accordingly. Naming Keystone as an approved board source in your RFQ removes that excuse. They are also your route to triple wall if Spec Flag SF-3 bites. | Z10: THEY DO NOT MAKE BOXES - you still need a converter to score, slot and stitch. Founded late 2023 so no long track record as this entity. ECT ranges and certifications not published.
A11: 7 | B11: B - Price benchmark | C11: Smurfit Westrock - Baltimore South Box Plant | D11: Integrated full-line box plant (global #1 by scale) | E11: 725 Pittman Rd | F11: Baltimore | G11: MD | H11: 21226 | I11: 62 | J11: 1 hr 15 min | K11: none published | L11: Not yet verified | M11: none published | N11: Not yet verified | O11: us.smurfitwestrock.com/locations | P11: None found | Q11: Yes | R11: 2,500 - 5,000+ | S11: Inferred (integrated) | T11: 160 - 210 | U11: ='Cost Model'!$I$6/1000*185.0 -> 7.9665625 | V11: ='Cost Model'!$I$7/1000*185.0 -> 16.500651 | W11: Estimate (modelled) | X11: See Qualification Matrix | Y11: Quote them as your price floor reference. Full-line integrated plant with deep heavy-duty double-wall experience and real package-testing resources. At the 5,000/yr end they become genuinely competitive, and their number keeps the independents honest even if you never place the order. | Z11: VERIFY THE PLANT IS OPEN BEFORE INVESTING TIME - see the Verification Log tab. Least flexible option at 500/yr; expect long lead times and little interest in a small first run.
A12: 8 | B12: C - Prototype only | C12: Craters & Freighters Northern Virginia | D12: Local custom container fabricator + crating (not a corrugated plant) | E12: 113 Executive Dr, Ste. 131 | F12: Sterling | G12: VA | H12: 20166 | I12: 4 | J12: 10 min | K12: (703) 796-0180 | L12: Not yet verified | M12: none published | N12: Not yet verified | O12: cratersandfreightersnorthernvirginia.com | P12: None found | Q12: Yes - hand built | R12: 1 | S12: PUBLISHED (one-off model) | T12: Board only / n/a | W12: Not comparable - hand built | X12: See Qualification Matrix | Y12: The only genuine fabricator essentially AT Dulles - about 4 miles from IAD. Builds to a minimum 350 lb double-wall standard, sized per item, with strapping and palletizing. Use for exactly one thing: a same-day physical prototype so you can resolve Spec Flag SF-1 with a real box in your hands before any converter quotes hard numbers. Call them IN PARALLEL with the others, not after. | Z12: NOT a production source - per-unit cost is roughly an order of magnitude above a converter. 350 lb DW is a basis-weight spec, not an ECT spec, so it does not by itself satisfy 48ECT.
A13: 9 | B13: D - Price check | C13: Atlantic Corrugated Box Company, Inc. | D13: Independent sheet plant (est. 1985) - packaging + displays | E13: 1701 Ruffin Rd | F13: Richmond | G13: VA | H13: 23234 | I13: 110 | J13: 2 hr 0 min | K13: (804) 231-4050 | L13: Not yet verified | M13: none published | N13: Not yet verified | O13: acbc-inc.com | P13: None found | Q13: MUST CONFIRM | R13: 250 - 500 | S13: Inferred (plant class) | T13: 210 - 270 | U13: ='Cost Model'!$I$6/1000*240.0 -> 10.335 | V13: ='Cost Model'!$I$7/1000*240.0 -> 21.40625 | W13: Estimate (modelled) | X13: See Qualification Matrix | Y13: Strongest of the Richmond cluster and Virginia-based, which matters if in-state sourcing carries weight. Sheet plant with design services, serving medical, food and beverage and tobacco - regulated industries that demand consistent certified board. Adds real price competition against the Baltimore group. | Z13: About 110 miles, past your stated radius - and freight is a larger share of landed cost on oversized flats than on a normal box, so the distance penalty is real, not nominal. Get freight quoted separately or the comparison is meaningless.
A14: 10 | B14: D - Price check | C14: Richmond Corrugated Box Co., Inc. | D14: Independent converter, family-run since 1971 | E14: 5301 Corrugated Rd | F14: Sandston | G14: VA | H14: 23150 | I14: 112 | J14: 2 hr 0 min | K14: (804) 222-1300 | L14: Not yet verified | M14: none published | N14: Not yet verified | O14: richmondcorrugated.com | P14: None found | Q14: MUST CONFIRM | R14: 250 - 500 | S14: Guess (no data) | T14: 200 - 280 | U14: ='Cost Model'!$I$6/1000*240.0 -> 10.335 | V14: ='Cost Model'!$I$7/1000*240.0 -> 21.40625 | W14: Low confidence | X14: See Qualification Matrix | Y14: Long-established Virginia independent (54+ yrs). Small family converters are often the most accommodating on awkward low-volume work and can surprise you on price because they are not optimising a corrugator schedule around you. Worth one call as a price and flexibility check. | Z14: Least documented supplier here - almost no published capability data, so both MOQ and price are genuinely guesses. Verify double-wall capability and max blank width on the first call before spending more time.
A15: 11 | B15: D - Price check | C15: Smurfit Westrock - Richmond Box Plant | D15: Integrated full-line box plant | E15: 5710 S Laburnum Ave | F15: Richmond | G15: VA | H15: 23231 | I15: 112 | J15: 2 hr 0 min | K15: none published | L15: Not yet verified | M15: none published | N15: Not yet verified | O15: us.smurfitwestrock.com/locations | P15: None found | Q15: Yes | R15: 2,500 - 5,000+ | S15: Inferred (integrated) | T15: 160 - 210 | U15: ='Cost Model'!$I$6/1000*185.0 -> 7.9665625 | V15: ='Cost Model'!$I$7/1000*185.0 -> 16.500651 | W15: Estimate (modelled) | X15: See Qualification Matrix | Y15: Second integrated benchmark and the in-Virginia alternative to their Baltimore plant. Useful if Baltimore South turns out to be closed. | Z15: Same caveats as Baltimore South: low interest at your volume, slow setup, consolidation risk.

Sheet Cost Model
A1: Cost Model - where the price estimates come from
A2: Corrugated is priced per MSF (thousand square feet of board), so unit price tracks blank area almost linearly. This tab computes your blank areas, back-calculates real $/MSF from PUBLISHED prices for 48ECT (and 275 lb test, its burst-basis equivalent) double wall, then applies a converter-direct discount. Blue cells are inputs; everything else is a live formula. Treat outputs as +/- 30% until a supplier quotes.
A4: 1. RSC blank geometry - the driver of everything below
A5: SKU | B5: Inside L (in) | C5: Inside W (in) | D5: Inside D (in) | E5: Glue tab (in) | F5: Blank length (in) | G5: Blank width (in) | H5: Blank area (sq in) | I5: Board sq ft per box | J5: Knocked-down flat footprint (in)
A6: SKU 1 (39 x 20 x 32 ID) | B6: 39 | C6: 20 | D6: 32 | E6: 1.25 | F6: =2*(B6+C6)+E6 -> 119.25 | G6: =D6+C6 -> 52 | H6: =F6*G6 -> 6201 | I6: =H6/144 -> 43.0625 | J6: =TEXT(B6+C6+E6,"0.0")&" x "&TEXT(D6+C6,"0.0") -> 60.2 x 52.0
A7: SKU 2 (46 x 39 x 36 ID) | B7: 46 | C7: 39 | D7: 36 | E7: 1.25 | F7: =2*(B7+C7)+E7 -> 171.25 | G7: =D7+C7 -> 75 | H7: =F7*G7 -> 12843.75 | I7: =H7/144 -> 89.192708 | J7: =TEXT(B7+C7+E7,"0.0")&" x "&TEXT(D7+C7,"0.0") -> 86.2 x 75.0
A8: Blank length = 2 x (L + W) + glue tab. Blank width = depth + width (top and bottom flaps together equal one box width). The knocked-down flat footprint is what actually gets palletised - see Spec Flag SF-4: both SKUs overhang a standard 48 x 40 in pallet.
A10: 2. Calibration - $/MSF back-calculated from REAL published prices (48ECT DW, or 275 lb test DW which is its equivalent)
A11: Source (published price) | B11: Size L x W x D (in) | C11: L | D11: W | E11: D | F11: Qty break | G11: Published $/box | H11: Blank sq ft (calc) | I11: Implied $/MSF (calc) | J11: Note
A12: packagingprice.com, 48ECT DW C-flute kraft | B12: 20 x 20 x 12 | C12: 20 | D12: 20 | E12: 12 | F12: bundle of 10 | G12: 6.57 | H12: =(2*(C12+D12)+1.25)*(E12+D12)/144 -> 18.055556 | I12: =G12/H12*1000 -> 363.87692 | J12: Stated 48 ECT double wall - exactly your spec. Small-bundle retail.
A13: packagingprice.com, 48ECT DW C-flute kraft | B13: 24 x 16 x 16 | C13: 24 | D13: 16 | E13: 16 | F13: bundle of 10 | G13: 6.57 | H13: =(2*(C13+D13)+1.25)*(E13+D13)/144 -> 18.055556 | I13: =G13/H13*1000 -> 363.87692 | J13: Same board area as the row above and the same price - confirms the blank-area method.
A14: packagingprice.com, 48ECT DW C-flute kraft | B14: 20 x 12 x 12 | C14: 20 | D14: 12 | E14: 12 | F14: bundle of 15 | G14: 4.01 | H14: =(2*(C14+D14)+1.25)*(E14+D14)/144 -> 10.875 | I14: =G14/H14*1000 -> 368.73563 | J14: Third independent check landing on the same $/MSF.
A15: Uline S-19776, 275 lb test DW | B15: 40 x 30 x 30 | C15: 40 | D15: 30 | E15: 30 | F15: 5 | G15: 26.15 | H15: =(2*(C15+D15)+1.25)*(E15+D15)/144 -> 58.854167 | I15: =G15/H15*1000 -> 444.31858 | J15: 275 lb burst DW = 48 ECT DW on the standard equivalence tables. Nearest published size to your SKUs.
A16: Uline S-19776, 275 lb test DW | B16: 40 x 30 x 30 | C16: 40 | D16: 30 | E16: 30 | F16: 500 | G16: 22.5 | H16: =(2*(C16+D16)+1.25)*(E16+D16)/144 -> 58.854167 | I16: =G16/H16*1000 -> 382.30088 | J16: Same box at 500 pcs - shows how little catalogue pricing moves with volume.
A17: Uline S-19776, 275 lb test DW | B17: 40 x 30 x 30 | C17: 40 | D17: 30 | E17: 30 | F17: 1,000+ | G17: 21.79 | H17: =(2*(C17+D17)+1.25)*(E17+D17)/144 -> 58.854167 | I17: =G17/H17*1000 -> 370.23717 | J17: Uline's best price. This is your RETAIL CEILING - any converter quote above it is not competitive.
A18: Mean implied $/MSF across all published benchmarks (the retail level): | I18: =AVERAGE(I12:I17) -> 382.22435
A19: Every benchmark lands in a tight band, which is the useful result: retail 48ECT double wall prices out around $360-450/MSF. Buying custom sizes direct from a converter at 500-5,000/yr should come in well under that - a distributor's margin on corrugated is commonly 40-100% over converter-direct.
A21: 3. Indicative unit price for YOUR two SKUs
A22: Scenario | B22: $/MSF | C22: SKU 1 $/box | D22: SKU 2 $/box | E22: Combined $ per set | F22: vs retail ceiling | G22: Who this looks like
A23: Retail ceiling (catalogue, do not pay this) | B23: 410 | C23: =$I$6/1000*B23 -> 17.655625 | D23: =$I$7/1000*B23 -> 36.56901 | E23: =C23+D23 -> 54.224635 | F23: =B23/$B$23-1 -> 0 | G23: Uline / packagingprice.com level - the number to beat.
A24: Distributor / broker | B24: 320 | C24: =$I$6/1000*B24 -> 13.78 | D24: =$I$7/1000*B24 -> 28.541667 | E24: =C24+D24 -> 42.321667 | F24: =B24/$B$23-1 -> -0.2195122 | G24: A packaging distributor reselling a converter's box. Still too high at your volume.
A25: Converter direct - conservative | B25: 260 | C25: =$I$6/1000*B25 -> 11.19625 | D25: =$I$7/1000*B25 -> 23.190104 | E25: =C25+D25 -> 34.386354 | F25: =B25/$B$23-1 -> -0.36585366 | G25: A small independent sheet plant at the 500/yr end, non-stock size, no commitment.
A26: Converter direct - expected (USE THIS) | B26: 220 | C26: =$I$6/1000*B26 -> 9.47375 | D26: =$I$7/1000*B26 -> 19.622396 | E26: =C26+D26 -> 29.096146 | F26: =B26/$B$23-1 -> -0.46341463 | G26: Most likely landing zone: an independent at 1,000-2,500/yr on a blanket order. Basis for the green price cells.
A27: Converter direct - aggressive | B27: 180 | C27: =$I$6/1000*B27 -> 7.75125 | D27: =$I$7/1000*B27 -> 16.054688 | E27: =C27+D27 -> 23.805937 | F27: =B27/$B$23-1 -> -0.56097561 | G27: Mill-backed (GBP) or integrated (Smurfit Westrock) at 5,000/yr on contract.
A29: 4. Indicative annual spend at the expected converter-direct rate (row 26)
A30: Annual volume per SKU | B30: SKU 1 annual $ | C30: SKU 2 annual $ | D30: Combined annual $ | E30: Board sq ft per yr | F30: Note
A31: 500 | B31: =A31*$C$26 -> 4736.875 | C31: =A31*$D$26 -> 9811.1979 | D31: =B31+C31 -> 14548.073 | E31: =A31*($I$6+$I$7) -> 66127.604 | F31: Bottom of your range. Setup weighs heavily per unit; Atlas Container's published 100-piece minimum matters most here.
A32: 1000 | B32: =A32*$C$26 -> 9473.75 | C32: =A32*$D$26 -> 19622.396 | D32: =B32+C32 -> 29096.146 | E32: =A32*($I$6+$I$7) -> 132255.21 | F32: Setup starts to amortise. Independents competitive.
A33: 2500 | B33: =A33*$C$26 -> 23684.375 | C33: =A33*$D$26 -> 49055.99 | D33: =B33+C33 -> 72740.365 | E33: =A33*($I$6+$I$7) -> 330638.02 | F33: Sweet spot for the independents - and where a blanket order with monthly releases pays off.
A34: 5000 | B34: =A34*$C$26 -> 47368.75 | C34: =A34*$D$26 -> 98111.979 | D34: =B34+C34 -> 145480.73 | E34: =A34*($I$6+$I$7) -> 661276.04 | F34: Mill-backed and integrated plants become genuinely competitive; revisit GBP and Smurfit Westrock.
A36: EXCLUDED FROM THESE NUMBERS, and each is material: (1) FREIGHT - both SKUs ship as oversized flats that overhang a 48 x 40 in pallet, so freight is a top-3 cost driver, not a rounding error. Always get it quoted as a separate line. (2) SETUP - a plain unprinted RSC usually needs no die, but expect a setup charge per run; ask for it broken out. (3) BOARD PRICE MOVES - PCA announced a $70/ton containerboard increase effective 1 March 2026 with mixed reception, and paper can shift 10-20% in a quarter. Ask how long each quote holds and whether there is an index clause.

Sheet Qualification Matrix
A1: Qualification Matrix
A2: Legend: C = confirmed on a public source | L = likely / industry-typical for this class of plant but NOT stated | A = must ASK on the call | N = no / not applicable | n/a = not relevant. Nothing marked L or A is a capability until a supplier confirms it. Column G is the one that ends conversations - ask it first.
A4: Company | B4: City, State | C4: In-house corrugator (vs. buys sheets) | D4: Double wall / heavy duty confirmed | E4: 48ECT specifically confirmed | F4: Triple wall available (fallback) | G4: Takes 75in wide blank (SKU 2) | H4: Extra-large box experience | I4: Stitched closure available | J4: MOQ 500 or below | K4: Structural design + physical samples | L4: In-house ISTA / package test lab | M4: Certifies ECT / BCT on a CoC | N4: FSC or SFI chain of custody | O4: ISO 9001 / BRCGS / other QMS | P4: Own delivery fleet into NoVA | Q4: Holds stock / blanket releases | R4: Overall confidence | S4: Priority
A5: Commercial-Wagner, Inc. | B5: Baltimore, MD | C5: A | D5: L | E5: A | F5: L | G5: L | H5: C | I5: C | J5: L | K5: A | L5: A | M5: A | N5: A | O5: A | P5: C | Q5: C | R5: Medium | S5: 1 - Call first
A6: Atlas Container Corp. | B6: Severn, MD | C6: A | D6: A | E6: A | F6: A | G6: A | H6: L | I6: L | J6: C | K6: C | L6: A | M6: A | N6: A | O6: A | P6: A | Q6: L | R6: Medium | S6: 2 - Call first
A7: Green Bay Packaging - Baltimore Division | B7: Hunt Valley, MD | C7: C | D7: C | E7: A | F7: L | G7: C | H7: L | I7: L | J7: N | K7: C | L7: C | M7: C | N7: L | O7: C | P7: L | Q7: A | R7: High | S7: 3 - Best board + test data
A8: Columbia Container Corp. | B8: Baltimore, MD | C8: A | D8: C | E8: A | F8: A | G8: A | H8: L | I8: L | J8: L | K8: C | L8: A | M8: L | N8: A | O8: A | P8: A | Q8: A | R8: Medium | S8: 4 - Call first
A9: Packaging Services Industries, Inc. (PSI) | B9: Williamsport, MD | C9: C | D9: L | E9: A | F9: A | G9: L | H9: L | I9: L | J9: A | K9: C | L9: A | M9: A | N9: A | O9: A | P9: C | Q9: L | R9: Medium | S9: 5 - Call first
A10: Keystone Sheets (Buckeye Corrugated / Corrugated Partners Group) | B10: Chambersburg, PA | C10: C | D10: C | E10: A | F10: C | G10: C | H10: n/a | I10: n/a | J10: n/a | K10: n/a | L10: A | M10: A | N10: A | O10: A | P10: N | Q10: A | R10: Medium | S10: 6 - Board source only
A11: Smurfit Westrock - Baltimore South Box Plant | B11: Baltimore, MD | C11: C | D11: C | E11: A | F11: C | G11: C | H11: C | I11: C | J11: N | K11: C | L11: C | M11: C | N11: C | O11: C | P11: C | Q11: C | R11: Low - verify open | S11: 7 - Price floor
A12: Craters & Freighters Northern Virginia | B12: Sterling, VA | C12: N | D12: C | E12: N | F12: N | G12: C | H12: C | I12: N | J12: C | K12: A | L12: N | M12: N | N12: A | O12: A | P12: C | Q12: N | R12: Medium | S12: 8 - Prototypes only
A13: Atlantic Corrugated Box Company, Inc. | B13: Richmond, VA | C13: A | D13: A | E13: A | F13: A | G13: A | H13: A | I13: A | J13: L | K13: C | L13: A | M13: A | N13: A | O13: A | P13: A | Q13: A | R13: Low | S13: 9 - Price check
A14: Richmond Corrugated Box Co., Inc. | B14: Sandston, VA | C14: A | D14: A | E14: A | F14: A | G14: A | H14: A | I14: A | J14: A | K14: A | L14: A | M14: A | N14: A | O14: A | P14: A | Q14: A | R14: Low | S14: 10 - Price check
A15: Smurfit Westrock - Richmond Box Plant | B15: Richmond, VA | C15: C | D15: C | E15: A | F15: C | G15: C | H15: C | I15: C | J15: N | K15: C | L15: C | M15: C | N15: C | O15: C | P15: C | Q15: C | R15: Low - verify open | S15: 11 - Price check
A17: Note how much red there is. Mid-Atlantic sheet plants almost never publish ECT grades, blank widths, MOQs or certifications - that is normal for the industry rather than a signal about these particular shops, but it does mean the phone call, not this spreadsheet, is where suppliers get qualified.

Sheet Spec Flags
A1: Spec Flags - issues that will affect quoting
A2: Boxes only. Raise SF-1 with every supplier (it is question 3 in the RFQ email) - it may decide the award, and it is far cheaper to resolve before tooling than after.
A4: Flag | B4: Severity | C4: Issue | D4: What the drawings say | E4: Recommended action
A5: SF-1 | B5: HIGH | C5: The not-to-exceed outside dimensions conflict with the stated inside dimensions in double wall | D5: Both boxes allow exactly 0.5 in total between inside and outside (39 -> 39.5, 20 -> 20.5, 32 -> 32.5; and 46 -> 46.5, 39 -> 39.5, 36 -> 36.5). On an RSC the outside dimension is the inside plus TWO board thicknesses. Heavy-duty 48ECT double wall typically runs 0.28-0.31 in caliper, so outside = inside + roughly 0.56-0.62 in. That overruns every not-to-exceed callout by about 0.06-0.12 in. A 0.5 in allowance implies 0.25 in board, which is light double wall, not heavy duty. | E5: THE MOST IMPORTANT ITEM HERE. Decide which constraint governs. If the max OD is hard - Rev C says it was added for pallet fit - either drop the inside dimensions about 0.1 in each or accept a lighter caliper. If the ID is hard because of the payload, raise the OD callout to inside + 0.65 in. Ask every supplier and COMPARE THEIR CALIPERS; the answers will differ and that difference is a real selection criterion.
A6: SF-2 | B6: MEDIUM | C6: Nothing locates the payload inside a 6 in clearance envelope | D6: SKU 1: payload 33 x 14 x 26 in inside a 39 x 20 x 32 in box. SKU 2: payload 40 x 33 x 30 in inside 46 x 39 x 36 in. Both leave a deliberate, consistent 6 in of clearance on every axis. The bridge was the only part in the drawing set that occupied any of it. | E6: Either there is a dunnage or cushioning part not on the drawings that needs specifying and sourcing, or the 6 in envelope is no longer needed and both boxes should shrink. The second option is worth real money: price tracks blank area almost linearly, so a smaller box is cheaper twice over - less board AND less freight. Resolve before committing to 5,000 of anything. PSI has in-house engineered foam if dunnage is required.
A7: SF-3 | B7: MEDIUM | C7: Stacking strength, not edge crush, is the real requirement - and it is unspecified | D7: The drawings specify 48ECT but say nothing about stack height, pallet pattern, warehouse humidity or storage duration. ECT is a board property; what governs whether a 46.5 x 39.5 x 36.5 in box survives is BCT (box compression), which falls sharply with box size, humidity and time under load. A large box at 48ECT is a very different risk from a small one at the same grade. | E7: Give suppliers the stack height, pallet pattern and storage environment, and ask them to certify a BCT figure (RFQ item 9). This is the flag most likely to justify Green Bay Packaging's ISTA lab, or a move to triple wall via Keystone Sheets. Getting it wrong shows up as crushed boxes in a warehouse six months after award, not at first article.
A8: SF-4 | B8: MEDIUM | C8: Both boxes ship as oversized flats that overhang a standard pallet - freight is a top-3 cost driver | D8: Knocked down flat, SKU 1 is roughly 60 x 52 in and SKU 2 roughly 86 x 75 in (calculated on the Cost Model tab). A standard GMA pallet is 48 x 40 in. SKU 2's flat overhangs it on both axes by a wide margin, so it ships on an oversized skid or floor-loaded, and a truck holds far fewer than board area alone suggests. | E8: This is why Commercial-Wagner's own fleet into Northern Virginia put them at #1, and why the 110-mile Richmond options carry a real rather than nominal penalty. Get freight quoted as a separate line (RFQ item 7), ask for boxes per pallet and pallets per truck, and re-rank on LANDED cost. On low-density freight a cheaper box from further away frequently loses.
A9: SF-5 | B9: LOW | C9: '48ECT' plus 'heavy-duty double wall' is an ambiguous pairing worth pinning down | D9: 48ECT is a legitimate double-wall edge-crush grade, but 'heavy duty' is a marketing term, not a spec. Different shops hit 48ECT with different liner and medium combinations at different cost and different caliper - which feeds straight back into SF-1. Useful reference: 275 lb burst test double wall is the burst-basis equivalent of 48 ECT, which is why Uline's 275 lb boxes are valid price benchmarks on the Cost Model tab. | E9: Require each supplier to state the actual board build (liner weights and flute combination), certified ECT and caliper. Since you are open to equivalents, ask each to also quote their nearest standard grade - standardising on something a plant already runs is usually the largest single cost lever available.
A10: SF-6 | B10: LOW | C10: The drawing set does not contain a box drawing | D10: Both sheets are titled BRIDGE and dimension only the bridge panel. The box appears solely as text in notes 2, 2.1 and 2.2. There is no flap detail, no closure method, no print or part-marking spec, and no tolerance block. | E10: An RSC can be quoted from ID/OD plus board grade, so this is not a blocker - the RFQ email on the 'Outreach Scripts' tab is a more complete spec than the drawings are. But before first article you need a written spec covering closure method, any part marking, and a dimensional tolerance; without a tolerance you have no basis to reject a shipment. And if you attach the drawings, ANNOTATE the bridge views as out of scope or you will get bridge pricing back.

Sheet Verification Log
A1: Verification Log - what was checked, and how hard
A2: Each supplier's contact record was researched against the company's own website plus independent directories, then handed to a SECOND independent checker instructed to try to REFUTE it - to search the phone number itself, confirm the email appears on a real source rather than being pattern-guessed, and hunt for closure news. UNVERIFIABLE below is an honest answer, not a failure: it means dial with mild suspicion. Verified 26 Aug 2026.
A4: Company | B4: Phone on file | C4: Phone source grade | D4: Challenge verdict | E4: Email on file | F4: Email source grade | G4: Email challenge | H4: Plant operating? | I4: Discrepancies and notes
A5: Commercial-Wagner, Inc. | B5: (410) 522-0900 | C5: Not yet verified | D5: Not yet run | E5: none published | F5: Not yet verified | G5: Not yet run | H5: Not yet verified | I5: No discrepancies found.
A6: Atlas Container Corp. | B6: (410) 551-6300 | C6: Not yet verified | D6: Not yet run | E6: info@atlascontainer.com | F6: Not yet verified | G6: Not yet run | H6: Not yet verified | I6: No discrepancies found.
A7: Green Bay Packaging - Baltimore Division | B7: (410) 785-2233 | C7: Not yet verified | D7: Not yet run | E7: none published | F7: Not yet verified | G7: Not yet run | H7: Not yet verified | I7: No discrepancies found.
A8: Columbia Container Corp. | B8: (410) 467-1400 | C8: Not yet verified | D8: Not yet run | E8: quotes@columbiacontainer.net | F8: Not yet verified | G8: Not yet run | H8: Not yet verified | I8: No discrepancies found.
A9: Packaging Services Industries, Inc. (PSI) | B9: (301) 223-8726 | C9: Not yet verified | D9: Not yet run | E9: info@psimd.com | F9: Not yet verified | G9: Not yet run | H9: Not yet verified | I9: No discrepancies found.
A10: Keystone Sheets (Buckeye Corrugated / Corrugated Partners Group) | B10: (717) 287-1764 | C10: Not yet verified | D10: Not yet run | E10: none published | F10: Not yet verified | G10: Not yet run | H10: Not yet verified | I10: No discrepancies found.
A11: Smurfit Westrock - Baltimore South Box Plant | B11: none published | C11: Not yet verified | D11: Not yet run | E11: none published | F11: Not yet verified | G11: Not yet run | H11: Not yet verified | I11: No discrepancies found.
A12: Craters & Freighters Northern Virginia | B12: (703) 796-0180 | C12: Not yet verified | D12: Not yet run | E12: none published | F12: Not yet verified | G12: Not yet run | H12: Not yet verified | I12: No discrepancies found.
A13: Atlantic Corrugated Box Company, Inc. | B13: (804) 231-4050 | C13: Not yet verified | D13: Not yet run | E13: none published | F13: Not yet verified | G13: Not yet run | H13: Not yet verified | I13: No discrepancies found.
A14: Richmond Corrugated Box Co., Inc. | B14: (804) 222-1300 | C14: Not yet verified | D14: Not yet run | E14: none published | F14: Not yet verified | G14: Not yet run | H14: Not yet verified | I14: No discrepancies found.
A15: Smurfit Westrock - Richmond Box Plant | B15: none published | C15: Not yet verified | D15: Not yet run | E15: none published | F15: Not yet verified | G15: Not yet run | H15: Not yet verified | I15: No discrepancies found.

Sheet Sources
A1: Sources and method
A2: Capability, MOQ and price provenance. Contact-detail provenance is on the 'Verification Log' tab. All of this is public marketing, directory or catalogue data - none of it is a supplier commitment.
A4: Supplier / topic | B4: Source | C4: What was taken from it
A5: MOQ data - reliability | B5: Supplier websites + industry norms | C5: Only TWO MOQs here are published by the supplier: Atlas Container's 'orders as small as 100 Qty' and Craters & Freighters' one-off model. Every other MOQ is INFERRED from plant class (small independent sheet plant 250-500; multi-plant regional 500-1,000; mill-backed 1,000-2,500; integrated 2,500+), and Richmond Corrugated is a straight guess because no capability data exists publicly. Mid-Atlantic sheet plants essentially never publish minimums. Treat every non-green MOQ as a hypothesis to test on the call.
A6: Price data - method | B6: Cost Model tab; Uline; packagingprice.com | C6: No supplier here publishes prices, so prices are MODELLED, not found. Method: compute RSC blank area from the given inside dimensions; back-calculate $/MSF from real published prices for 48ECT double wall (packagingprice.com, three sizes, all landing within $5/MSF of each other - which validates the method) and 275 lb test double wall (Uline S-19776, five quantity breaks, $26.15 down to $21.79); then discount for converter-direct purchasing. 275 lb burst DW is the equivalent of 48 ECT DW on the standard tables, which is what makes the Uline series a valid comparator. Outputs are +/- 30%.
A7: Price data - market context | B7: CorrugatedNews containerboard guide; Green Markets Box Report; corrugatedboxsuppliers.com cost guide | C7: PCA announced a $70/ton containerboard increase effective 1 March 2026, with mixed reception and flat demand. Box shipments closed 2025 down 1.5-2.0% year on year, ~1.6% growth forecast 2026-27. Corrugated pricing can move 10-20% in a quarter. A soft demand market is a good time to be buying - and a reason to ask how long each quote holds.
A8: Commercial-Wagner | B8: commercialwagner.com; Thomasnet; directory listings | C8: 17 box-making machines, rotary and flatbed die cutting, EXTRA-LARGE boxes, taped/glued/stitched construction, hand assembly and fulfillment, own fleet serving Northern Virginia, two sites. The extra-large and stitched claims are why they rank first.
A9: Atlas Container | B9: atlascontainer.com and /central-pa-packaging-solutions | C9: Founded 1968, rotary + flatbed die cutting, 'orders as small as 100 Qty' - the only published MOQ on this list - free custom designs and samples, named regional rep, service region.
A10: Green Bay Packaging - Baltimore | B10: gbp.com/locations/baltimore | C10: IN-HOUSE CORRUGATOR, B/C/E flute plus explicit double wall for heavy products and long-distance shipping, in-house graphic and structural design, ON-SITE ISTA LAB, BRCGS and SFI certifications, MD/DE/PA/NJ/VA/WV.
A11: Columbia Container | B11: columbiacontainer.net | C11: 40+ years, DE/MD/PA/VA/DC region, 3-5 business day turnaround claim, custom flute and liner combinations, die cut / Gaylord / UN-rated / anti-static product list.
A12: Packaging Services Industries (PSI) | B12: psimd.com; Buzzfile; Facebook business listing | C12: 282,000 sq ft HQ, three production facilities plus one dedicated corrugation plant, ~40 million sq ft board/month, engineered foam and displays, Manassas VA marketing page. psimd.com returned HTTP 500 during research - lead with the phone.
A13: Keystone Sheets | B13: keystonesheets.com; bcipkg.com; cpgteam.com | C13: 132 in BHS corrugator described as the widest in the country capable of triple wall, single/double/triple wall SHEETS only, next-day delivery, founded late 2023, parent Corrugated Partners Group / Buckeye Corrugated with 16 plants. Relevant for 75 in wide double-wall sheet supply and as the triple-wall fallback for SF-3.
A14: Smurfit Westrock | B14: westrock.com/locations; us.smurfitwestrock.com/locations; Packaging Dive and Manufacturing Dive closure reporting | C14: Baltimore South (725 Pittman Rd, 21226) and Richmond (5710 S Laburnum Ave, 23231) box plant addresses. Operating status was independently re-checked - see the Verification Log tab for the verdict.
A15: Craters & Freighters Northern Virginia | B15: cratersandfreightersnorthernvirginia.com | C15: 113 Executive Dr Ste 131, Sterling VA 20166; minimum 350 lb double-wall corrugated fiberboard standard; custom-sized containers; strapping, banding, palletizing.
... A20: Limitation - the honest answer on 'near Dulles' | B20: - | C20: There is no corrugated converting plant in Loudoun County. The closest genuine fabricator to IAD is Craters & Freighters in Sterling at about 4 miles, and it is a one-off crating shop, not a production converter. If 'near Dulles' is a hard requirement rather than a preference, 60 miles to Severn, Baltimore or Williamsport is as close as real production capacity gets - and given SF-4, proximity is worth paying for on this job.
