Workbook

Sheet Dashboard
B2: Cardiac MVR Suture Skills Kit — Sourcing Dashboard
B3: Three parts, quantity 50. Four quotes, two vendors. Fictiv's SLS re-quote cut its price 21.5% and closed most of the gap, but Xometry still holds the lowest parts cost. Every figure is PARTS ONLY — Xometry has never quoted shipping or tax. Live formulas; all detail sheets sit behind this one.
B6: AT A GLANCE
B7: LOWEST PARTS COST | D7: GAP TO FICTIV | F7: SAVED BY MJF → SLS | H7: UNEXPLAINED ON FICTIV TOTAL
B8: ='Process Comparison @ 50'!C14 -> 54540 | D8: ='Process Comparison @ 50'!C16 -> 12824 | F8: ='Process Comparison @ 50'!C15 -> 18463 | H8: 7252.29
B9: Xometry, SLS | D9: 19.0% — was $31,287 on MJF | F9: Fictiv cut 21.5% on process alone | H9: Quote total $74,616.29 vs parts $67,364
B11: TOTAL PARTS COST — 50 KITS
B12: Option | C12: Process | D12: Lead time | E12: Total @ 50 | F12: Per kit | G12: vs cheapest
B13: Split award (best per part) | C13: MJF + SLS | D13: mixed | E13: ='Process Comparison @ 50'!C20 -> 54246.5 | F13: ='Process Comparison @ 50'!C20/QtyKits -> 1084.93 | G13: =E13-MIN($E$13:$E$17) -> 0
B14: Xometry | C14: SLS | D14: 35 business days | E14: ='Process Comparison @ 50'!C14 -> 54540 | F14: ='Process Comparison @ 50'!C14/QtyKits -> 1090.8 | G14: =E14-MIN($E$13:$E$17) -> 293.5
B15: Fictiv — best mix | C15: MJF + SLS | D15: 26 production days | E15: ='Process Comparison @ 50'!C21 -> 66453 | F15: ='Process Comparison @ 50'!C21/QtyKits -> 1329.06 | G15: =E15-MIN($E$13:$E$17) -> 12206.5
B16: Fictiv — all SLS (newest) | C16: SLS | D16: 26 production days | E16: ='Process Comparison @ 50'!C13 -> 67364 | F16: ='Process Comparison @ 50'!C13/QtyKits -> 1347.28 | G16: =E16-MIN($E$13:$E$17) -> 13117.5
B17: Fictiv — MJF (superseded) | C17: MJF | D17: 32 production days | E17: ='Process Comparison @ 50'!C12 -> 85827 | F17: ='Process Comparison @ 50'!C12/QtyKits -> 1716.54 | G17: =E17-MIN($E$13:$E$17) -> 31580.5
B19: The split award saves only ~$294 (0.5%) over single-sourcing Xometry — not worth two suppliers on price alone. Fictiv's own best mix (MJF for the valve, SLS for the other two) is $911 under its all-SLS quote: worth asking for as one order.
B22: WHERE THE MONEY IS — UNIT PRICE AT QTY 50
B23: Part | C23: Fictiv MJF | D23: Fictiv SLS | E23: MJF → SLS | F23: Xometry SLS | G23: Cheapest | H23: Why
B24: ='Process Comparison @ 50'!B6 -> 667357 Valve receptacle | C24: ='Process Comparison @ 50'!C6 -> 53.71 | D24: ='Process Comparison @ 50'!D6 -> 71.93 | E24: ='Process Comparison @ 50'!E6 -> 0.33922919 | F24: ='Process Comparison @ 50'!F6 -> 59.58 | G24: ='Process Comparison @ 50'!G6 -> Fictiv MJF | H24: Packs ~117 per MJF build — no envelope penalty, so MJF wins it.
B25: ='Process Comparison @ 50'!B7 -> 667355 Chest | C25: ='Process Comparison @ 50'!C7 -> 616.18 | D25: ='Process Comparison @ 50'!D7 -> 541.58 | E25: ='Process Comparison @ 50'!E7 -> -0.12106852 | F25: ='Process Comparison @ 50'!F7 -> 378.56 | G25: ='Process Comparison @ 50'!G7 -> Xometry | H25: Large hollow shell: ~2 per MJF build vs ~12 on large-format SLS.
B26: ='Process Comparison @ 50'!B8 -> 667354 Base | C26: ='Process Comparison @ 50'!C8 -> 1046.65 | D26: ='Process Comparison @ 50'!D8 -> 733.77 | E26: ='Process Comparison @ 50'!E8 -> -0.2989347 | F26: ='Process Comparison @ 50'!F8 -> 652.66 | G26: ='Process Comparison @ 50'!G8 -> Xometry | H26: Largest part, biggest MJF envelope penalty — biggest SLS gain.
B27: KIT (one of each) | C27: ='Process Comparison @ 50'!C9 -> 1716.54 | D27: ='Process Comparison @ 50'!D9 -> 1347.28 | E27: ='Process Comparison @ 50'!E9 -> -0.21511879 | F27: ='Process Comparison @ 50'!F9 -> 1090.8 | G27: =IF(MIN(C27,D27,F27)=C27,"Fictiv MJF",IF(MIN(C27,D27,F27)=D27,"Fictiv SLS","Xometry")) -> Xometry
B29: ARE THEY QUOTING THE SAME THING?
B30: Criterion | C30: Fictiv — SLS | E30: Xometry — SLS | G30: Status
B31: Process | C31: Selective Laser Sintering | E31: Selective Laser Sintering | G31: Match
B32: Material | C32: Nylon (powder) | E32: Nylon 12 | G32: Match
B33: Colour | C33: Black / White / Black | E33: Black-dyed / Natural / Black-dyed | G33: Match
B34: Inspection | C34: 8-pt, 14-pt, 13-pt dimensional | E34: Dimensional report + 5 first articles | G34: Close, not identical
B35: Lead time | C35: 26 production days | E35: 35 business days, after FAI acceptance | G35: Fictiv faster
B36: Chest drawing revision | C36: rev_c | E36: REV B | G36: Different geometry
B37: Quote age | C37: Current | E37: 10 months; price honour lapsed Dec 2025 | G37: Xometry stale
B38: Shipping & tax | C38: Inside the $74,616.29 total | E38: Calculated at checkout — never quoted | G38: Not comparable
B40: BEFORE YOU AWARD
B41: Priority | C41: Action | E41: Why it matters
B42: 1 | C42: Ask Fictiv to itemise the $7,252.29 | E42: Quote total $74,616.29 vs line items $67,364.00 — 10.8% of the quote, and more than half the remaining gap.
B43: 2 | C43: Ask Xometry to re-quote on current pricing | E43: The $54,540 that wins this comparison was quoted Nov 2025; its 30-day price honour lapsed in Dec.
B44: 3 | C44: Settle the chest drawing revision | E44: Fictiv quoted rev_c, Xometry REV B — different geometry on a part carrying $27,079 of the order.
B45: 4 | C45: Level the inspection scope on both sides | E45: Xometry ships 5 first articles; Fictiv names point-counts only. Price the same plan both ways.
B46: 5 | C46: Ask Fictiv for the MJF + SLS mix as one order | E46: MJF for the valve, SLS for the other two: $66,453, i.e. $911 under its all-SLS quote.
B49: Basis: parts-only cost at quantity 50, from four quote documents. Every extended price reproduces from its own unit price x quantity, and each quote's printed total reproduces from the model. Build-packing figures behind the 'Why' column are modelled from part envelopes against published machine build volumes — neither vendor names its equipment. No personal data is carried into this workbook.

Sheet Inputs & Assumptions
B2: Quote Comparison — Cardiac MVR Suture Skills Kit (3 parts)
B3: Three quote documents, two vendors. Figures transcribed verbatim from the PDFs; every extended price on each quote reproduces exactly from its own unit price x quantity. YELLOW = as-quoted input, GREEN = calculated. No personal data extracted; the Fictiv quote reference is redacted because it embeds a surname.
B5: 1) THE THREE QUOTE DOCUMENTS
C6: Fictiv A0 (superseded) | D6: Fictiv A1 — MQ (current) | E6: Xometry | F6: Fictiv A2 — SLS (newest)
B7: Quote reference | C7: [redacted] | D7: [redacted] | E7: Q47-2889-3704 | F7: [redacted] | G7: Fictiv refs omitted: they embed a personal name.
B8: Quote date | C8: 2026-08-25 | D8: 2026-08-28 | E8: 2025-11-24 | F8: 2026-09-25 | G8: Fictiv A1 supersedes A0 three days later. Xometry is ~9 months old.
B9: Valid until | C9: 2026-09-24 | D9: 2026-09-27 | E9: 2025-12-24 | F9: — | G9: Xometry's 30-day price honour lapsed long ago — treat as indicative.
B10: Quantities quoted | C10: 1 | D10: 1 / 20 / 50 | E10: 50 | F10: 50 | G10: *** A1 now quotes 50, so a TRUE like-for-like is finally possible. ***
B11: Process | C11: MJF | D11: MJF | E11: SLS | F11: SLS | G11: Both PA12 powder-bed, both vapor smoothed.
B12: Material | C12: PA 12 | D12: PA 12 | E12: Nylon 12 | F12: Nylon (powder) | G12: Chemically equivalent.
B13: Country | C13: USA | D13: USA | E13: USA | F13: USA | G13: Both domestic — no tariff exposure either side.
B14: Formal inspection | C14: Not quoted | D14: Not quoted | E14: Included | F14: 8/14/13-pt | G14: Xometry carries dimensional report + 5 FAI. Fictiv does not.
B16: 2) AS-QUOTED UNIT PRICES ($ per single part)
B17: Part | C17: Volume (in³) | D17: Fictiv A0 @ qty 1 | E17: Fictiv A1 @ qty 1 | F17: Fictiv A1 @ qty 20 | G17: Fictiv A1 @ qty 50 | H17: Xometry @ qty 50 | I17: Fictiv SLS @ qty 50
B18: 667357 Valve receptacle | C18: 2.56 | D18: 168.68 | E18: 159.8 | F18: 58.54 | G18: 53.71 | H18: 59.58 | I18: 71.93
B19: 667355 Chest | C19: 11.952 | D19: 1039.11 | E19: 984.42 | F19: 648.38 | G19: 616.18 | H19: 378.56 | I19: 541.58
B20: 667354 Base | C20: 25.007 | D20: 1709.77 | E20: 1619.78 | F20: 1101.19 | G20: 1046.65 | H20: 652.66 | I20: 733.77
B21: KIT (one of each part) | C21: =SUM(C18:C20) -> 39.519 | D21: =SUM(D18:D20) -> 2917.56 | E21: =SUM(E18:E20) -> 2764 | F21: =SUM(F18:F20) -> 1808.11 | G21: =SUM(G18:G20) -> 1716.54 | H21: =SUM(H18:H20) -> 1090.8 | I21: =SUM(I18:I20) -> 1347.28
B23: 3) LEAD TIME AS QUOTED (production / business days)
D24: Fictiv A1 @ qty 1 | E24: Fictiv A1 @ qty 20 | F24: Fictiv A1 @ qty 50 | G24: Xometry @ qty 50
B25: Stated lead time (days) | D25: 6 | E25: 20 | F25: 32 | G25: 35
B26: Fictiv quotes PRODUCTION days and its lead time lengthens with quantity (6 -> 32). Xometry quotes 35 BUSINESS days AND its clock starts only after first-article acceptance, so its true elapsed time is longer than 35. At qty 50 the two are broadly comparable — Fictiv's speed advantage exists at qty 1, not at volume.
B29: 4) DRIVER
B30: Kit quantity to compare at | C30: 50 | E30: EDIT ME. 50 is the only quantity both vendors have quoted. At 1 or 20 only Fictiv has a price.
B32: QUOTE 4 (Fictiv, SLS): printed QUOTE TOTAL is $74,616.29 but the three line items sum to $67,364.00. The $7,252.29 difference is not itemised on the page supplied and is EXCLUDED from every parts-only comparison in this workbook. Confirm with Fictiv what it covers before comparing totals.

Sheet Head-to-Head @ 50
B2: Like-for-Like: Both Vendors at Quantity 50
B3: This is now a true comparison — both vendors have quoted the same quantity of the same three parts. It replaces the qty-1-vs-qty-50 mismatch that made the first comparison unusable.
B5: Part | C5: Fictiv A1 $/unit @ 50 | D5: Xometry $/unit @ 50 | E5: Δ (F − X) | F5: % gap | G5: Cheaper | H5: Fictiv $ per in³ | I5: Xometry $ per in³
B6: ='Inputs & Assumptions'!B18 -> 667357 Valve receptacle | C6: ='Inputs & Assumptions'!G18 -> 53.71 | D6: ='Inputs & Assumptions'!H18 -> 59.58 | E6: =C6-D6 -> -5.87 | F6: =IF(MAX(C6,D6)=0,0,ABS(C6-D6)/MAX(C6,D6)) -> 0.098522994 | G6: =IF(C6<D6,"FICTIV","XOMETRY") -> FICTIV | H6: =IF('Inputs & Assumptions'!C18=0,0,C6/'Inputs & Assumptions'!C18) -> 20.980469 | I6: =IF('Inputs & Assumptions'!C18=0,0,D6/'Inputs & Assumptions'!C18) -> 23.273438
B7: ='Inputs & Assumptions'!B19 -> 667355 Chest | C7: ='Inputs & Assumptions'!G19 -> 616.18 | D7: ='Inputs & Assumptions'!H19 -> 378.56 | E7: =C7-D7 -> 237.62 | F7: =IF(MAX(C7,D7)=0,0,ABS(C7-D7)/MAX(C7,D7)) -> 0.38563407 | G7: =IF(C7<D7,"FICTIV","XOMETRY") -> XOMETRY | H7: =IF('Inputs & Assumptions'!C19=0,0,C7/'Inputs & Assumptions'!C19) -> 51.554552 | I7: =IF('Inputs & Assumptions'!C19=0,0,D7/'Inputs & Assumptions'!C19) -> 31.67336
B8: ='Inputs & Assumptions'!B20 -> 667354 Base | C8: ='Inputs & Assumptions'!G20 -> 1046.65 | D8: ='Inputs & Assumptions'!H20 -> 652.66 | E8: =C8-D8 -> 393.99 | F8: =IF(MAX(C8,D8)=0,0,ABS(C8-D8)/MAX(C8,D8)) -> 0.37642956 | G8: =IF(C8<D8,"FICTIV","XOMETRY") -> XOMETRY | H8: =IF('Inputs & Assumptions'!C20=0,0,C8/'Inputs & Assumptions'!C20) -> 41.854281 | I8: =IF('Inputs & Assumptions'!C20=0,0,D8/'Inputs & Assumptions'!C20) -> 26.099092
B9: FULL KIT (1 of each) | C9: =SUM(C6:C8) -> 1716.54 | D9: =SUM(D6:D8) -> 1090.8 | E9: =C9-D9 -> 625.74 | F9: =IF(MAX(C9,D9)=0,0,ABS(C9-D9)/MAX(C9,D9)) -> 0.36453564 | G9: =IF(C9<D9,"FICTIV","XOMETRY") -> XOMETRY | H9: =IF(VolKit=0,0,C9/VolKit) -> 43.435816 | I9: =IF(VolKit=0,0,D9/VolKit) -> 27.601913
B11: TOTAL COST OF 50 KITS
B12: Fictiv A1 — all three parts | C12: =C9*QtyKits -> 85827
B13: Xometry — all three parts | C13: =D9*QtyKits -> 54540
B14: Difference (Fictiv − Xometry) | C14: =C12-C13 -> 31287
B15: Xometry cheaper by | C15: =IF(C12=0,0,(C12-C13)/C12) -> 0.36453564
B17: WHAT CHANGED VERSUS THE FIRST COMPARISON
B18: Apparent gap when comparing qty 1 to qty 50 | C18: =IF(KitA0=0,0,1-KitX50/KitA0) -> 0.62612594 | D18: The misleading number. Fictiv had no volume price.
B19: Real gap now, both at qty 50 | C19: =IF(C9=0,0,1-D9/C9) -> 0.36453564 | D19: Roughly HALF the apparent gap. Still Xometry's win.
B20: Volume break Fictiv actually delivered | C20: =IF(KitA1q1=0,0,1-KitA1q50/KitA1q1) -> 0.37896527 | D20: Off its own current qty-1 price.
B21: Volume break Fictiv needed to reach parity | C21: =IF(KitA1q1=0,0,1-KitX50/KitA1q1) -> 0.60535456 | D21: It fell short — but by far less than first feared.
B23: HEADLINE: Xometry still wins the kit at qty 50, but by 36% rather than the 63% the first comparison suggested. Fictiv is now CHEAPER on 667357 (valve receptacle) — the first part where it beats Xometry. The remaining gap is concentrated entirely in the two large parts (chest and base), where Fictiv is ~38% more expensive.

Sheet Process Comparison @ 50
B2: Three Options at Quantity 50 — MJF vs SLS vs Xometry
B3: Fictiv re-quoted the same three parts on SLS. The process switch cut its price 21.5% and closed most of the gap to Xometry. Parts only — Fictiv's quote total carries $7,252.29 that Xometry has not quoted.
B5: Part | C5: Fictiv MJF | D5: Fictiv SLS | E5: MJF→SLS | F5: Xometry SLS | G5: Cheapest | H5: Why
B6: ='Inputs & Assumptions'!B18 -> 667357 Valve receptacle | C6: ='Inputs & Assumptions'!G18 -> 53.71 | D6: ='Inputs & Assumptions'!I18 -> 71.93 | E6: =IF(C6=0,0,D6/C6-1) -> 0.33922919 | F6: ='Inputs & Assumptions'!H18 -> 59.58 | G6: =IF(MIN(C6,D6,F6)=C6,"Fictiv MJF",IF(MIN(C6,D6,F6)=D6,"Fictiv SLS","Xometry")) -> Fictiv MJF | H6: Small part packs ~117 per MJF build — no envelope penalty, so MJF wins it.
B7: ='Inputs & Assumptions'!B19 -> 667355 Chest | C7: ='Inputs & Assumptions'!G19 -> 616.18 | D7: ='Inputs & Assumptions'!I19 -> 541.58 | E7: =IF(C7=0,0,D7/C7-1) -> -0.12106852 | F7: ='Inputs & Assumptions'!H19 -> 378.56 | G7: =IF(MIN(C7,D7,F7)=C7,"Fictiv MJF",IF(MIN(C7,D7,F7)=D7,"Fictiv SLS","Xometry")) -> Xometry | H7: Large hollow shell: only ~2 per MJF build vs ~12 on large-format SLS.
B8: ='Inputs & Assumptions'!B20 -> 667354 Base | C8: ='Inputs & Assumptions'!G20 -> 1046.65 | D8: ='Inputs & Assumptions'!I20 -> 733.77 | E8: =IF(C8=0,0,D8/C8-1) -> -0.2989347 | F8: ='Inputs & Assumptions'!H20 -> 652.66 | G8: =IF(MIN(C8,D8,F8)=C8,"Fictiv MJF",IF(MIN(C8,D8,F8)=D8,"Fictiv SLS","Xometry")) -> Xometry | H8: Largest part — biggest envelope penalty on MJF, so the biggest SLS gain.
B9: KIT (one of each) | C9: =SUM(C6:C8) -> 1716.54 | D9: =SUM(D6:D8) -> 1347.28 | E9: =IF(C9=0,0,D9/C9-1) -> -0.21511879 | F9: =SUM(F6:F8) -> 1090.8 | G9: =IF(MIN(C9,D9,F9)=C9,"Fictiv MJF",IF(MIN(C9,D9,F9)=D9,"Fictiv SLS","Xometry")) -> Xometry
B11: TOTAL AT 50 KITS (parts only)
B12: Fictiv — MJF (superseded) | C12: =C9*QtyKits -> 85827
B13: Fictiv — SLS (newest) | C13: =D9*QtyKits -> 67364
B14: Xometry — SLS | C14: =F9*QtyKits -> 54540
B15: Saved by switching MJF→SLS | C15: =C12-C13 -> 18463 | D15: What the process change alone bought.
B16: Remaining gap to Xometry | C16: =C13-C14 -> 12824 | D16: Was $31,287 on MJF.
B17: Remaining gap (%) | C17: =IF(C13=0,0,(C13-C14)/C13) -> 0.19036874 | D17: Was 36.5% on MJF.
B19: BEST ACHIEVABLE MIXES
B20: Split award — cheapest vendor per part | C20: =(MIN(C6,D6,F6)+MIN(C7,D7,F7)+MIN(C8,D8,F8))*QtyKits -> 54246.5 | D20: 667357 from Fictiv MJF, the two large parts from Xometry. Saves only ~$294 (0.5%) over all-Xometry.
B21: Best all-Fictiv mix (MJF + SLS) | C21: =(MIN(C6,D6)+MIN(C7,D7)+MIN(C8,D8))*QtyKits -> 66453 | D21: Valve on MJF, chest and base on SLS. $911 under Fictiv's all-SLS quote — ask for it as one order.
B22: All-Xometry | C22: =F9*QtyKits -> 54540 | D22: The benchmark this comparison is measured against.
B24: MECHANISM: powder-bed cost tracks parts-per-build. The two large parts are ~10-litre bounding boxes only 2-4% filled; MJF's 41 L chamber takes ~2 of them per build against ~9-12 on a large-format SLS machine (154 L). That is why SLS helped the big parts and HURT the small one (+33.9%). Machine classes are inferred from the quoted processes — neither vendor names its equipment.

Sheet Volume Curve
B2: How Fictiv's Price Moves With Quantity
B3: Fictiv quoted three quantities, so its volume curve is visible. Xometry quoted only 50, shown as a flat reference line. The shape of Fictiv's curve is the key question: is there more discount left at higher volume?
K4: Chart data (drives the chart; Xometry shown flat as a reference line — it quoted qty 50 only)
B5: 1) KIT PRICE BY QUANTITY | K5: Order quantity | L5: Fictiv A1 $/kit | M5: Xometry $/kit (ref)
C6: @ qty 1 | D6: @ qty 20 | E6: @ qty 50 | K6: 1 | L6: =KitA1q1 -> 2764 | M6: =KitX50 -> 1090.8
B7: Fictiv A1 — $/kit | C7: =KitA1q1 -> 2764 | D7: =KitA1q20 -> 1808.11 | E7: =KitA1q50 -> 1716.54 | K7: 20 | L7: =KitA1q20 -> 1808.11 | M7: =KitX50 -> 1090.8
B8: Xometry — $/kit | C8: n/a | D8: n/a | E8: =KitX50 -> 1090.8 | K8: 50 | L8: =KitA1q50 -> 1716.54 | M8: =KitX50 -> 1090.8
B9: Fictiv premium over Xometry | C9: n/a | D9: n/a | E9: =IF(KitX50=0,0,KitA1q50/KitX50-1) -> 0.57365237
B11: 2) MARGINAL DISCOUNT — where the volume break actually happens
B12: Part | C12: qty 1 → 20 | D12: qty 20 → 50 | E12: qty 1 → 50
B13: ='Inputs & Assumptions'!B18 -> 667357 Valve receptacle | C13: =IF('Inputs & Assumptions'!E18=0,0,'Inputs & Assumptions'!F18/'Inputs & Assumptions'!E18-1) -> -0.63366708 | D13: =IF('Inputs & Assumptions'!F18=0,0,'Inputs & Assumptions'!G18/'Inputs & Assumptions'!F18-1) -> -0.082507687 | E13: =IF('Inputs & Assumptions'!E18=0,0,'Inputs & Assumptions'!G18/'Inputs & Assumptions'!E18-1) -> -0.66389237
B14: ='Inputs & Assumptions'!B19 -> 667355 Chest | C14: =IF('Inputs & Assumptions'!E19=0,0,'Inputs & Assumptions'!F19/'Inputs & Assumptions'!E19-1) -> -0.34135836 | D14: =IF('Inputs & Assumptions'!F19=0,0,'Inputs & Assumptions'!G19/'Inputs & Assumptions'!F19-1) -> -0.049662235 | E14: =IF('Inputs & Assumptions'!E19=0,0,'Inputs & Assumptions'!G19/'Inputs & Assumptions'!E19-1) -> -0.37406798
B15: ='Inputs & Assumptions'!B20 -> 667354 Base | C15: =IF('Inputs & Assumptions'!E20=0,0,'Inputs & Assumptions'!F20/'Inputs & Assumptions'!E20-1) -> -0.32016076 | D15: =IF('Inputs & Assumptions'!F20=0,0,'Inputs & Assumptions'!G20/'Inputs & Assumptions'!F20-1) -> -0.049528238 | E15: =IF('Inputs & Assumptions'!E20=0,0,'Inputs & Assumptions'!G20/'Inputs & Assumptions'!E20-1) -> -0.353832
B16: KIT | C16: =IF(KitA1q1=0,0,KitA1q20/KitA1q1-1) -> -0.34583575 | D16: =IF(KitA1q20=0,0,KitA1q50/KitA1q20-1) -> -0.050644043 | E16: =IF(KitA1q1=0,0,KitA1q50/KitA1q1-1) -> -0.37896527
B18: READ THIS: almost the entire volume break is spent by qty 20. Going from 20 to 50 buys only ~5% more. Fictiv's curve has effectively flattened, so it is unlikely to close a 36% gap through volume alone — reaching Xometry's price would need a step change in quoting, not a bigger order.
B21: 3) WHAT FICTIV WOULD STILL HAVE TO DO
B22: Fictiv kit @ 50 today | C22: =KitA1q50 -> 1716.54
B23: Xometry kit @ 50 | C23: =KitX50 -> 1090.8
B24: Further discount Fictiv needs from here | C24: =IF(KitA1q50=0,0,1-KitX50/KitA1q50) -> 0.36453564
B25: Extra $ per kit Fictiv must find | C25: =KitA1q50-KitX50 -> 625.74
B26: Extra $ across 50 kits | C26: =(KitA1q50-KitX50)*QtyKits -> 31287

Sheet Split Award
B2: Split Award — Cheapest Vendor Per Part
B3: Because Fictiv now wins one of the three parts, single-sourcing is no longer automatically optimal on price. This sheet awards each part to whichever vendor is cheaper at qty 50.
B5: Part | C5: Fictiv @ 50 | D5: Xometry @ 50 | E5: Award to | F5: Unit price | G5: Extended (50)
B6: ='Head-to-Head @ 50'!B6 -> 667357 Valve receptacle | C6: ='Head-to-Head @ 50'!C6 -> 53.71 | D6: ='Head-to-Head @ 50'!D6 -> 59.58 | E6: =IF(C6<D6,"FICTIV","XOMETRY") -> FICTIV | F6: =MIN(C6,D6) -> 53.71 | G6: =F6*QtyKits -> 2685.5
B7: ='Head-to-Head @ 50'!B7 -> 667355 Chest | C7: ='Head-to-Head @ 50'!C7 -> 616.18 | D7: ='Head-to-Head @ 50'!D7 -> 378.56 | E7: =IF(C7<D7,"FICTIV","XOMETRY") -> XOMETRY | F7: =MIN(C7,D7) -> 378.56 | G7: =F7*QtyKits -> 18928
B8: ='Head-to-Head @ 50'!B8 -> 667354 Base | C8: ='Head-to-Head @ 50'!C8 -> 1046.65 | D8: ='Head-to-Head @ 50'!D8 -> 652.66 | E8: =IF(C8<D8,"FICTIV","XOMETRY") -> XOMETRY | F8: =MIN(C8,D8) -> 652.66 | G8: =F8*QtyKits -> 32633
B9: SPLIT-AWARD TOTAL | F9: =SUM(F6:F8) -> 1084.93 | G9: =SUM(G6:G8) -> 54246.5
B11: IS THE SPLIT WORTH IT?
B12: All-Xometry (single source) | C12: =KitX50*QtyKits -> 54540
B13: All-Fictiv (single source) | C13: =KitA1q50*QtyKits -> 85827
B14: Split award (cheapest per part) | C14: =G9 -> 54246.5
B15: Split saving vs all-Xometry | C15: =C12-C14 -> 293.5 | D15: The entire prize from splitting.
B16: Split saving vs all-Xometry (%) | C16: =IF(C12=0,0,(C12-C14)/C12) -> 0.0053813715 | D16: Immaterial on price alone.
B17: Split saving vs all-Fictiv | C17: =C13-C14 -> 31580.5 | D17: Large — but that is just Xometry winning two parts.
B19: VERDICT: splitting saves roughly $294 across 50 kits — about half a percent. That does not pay for running two suppliers, two inspection regimes and two sets of first articles for one small part. Award the split only if dual-sourcing is wanted for supply resilience; on price alone it is noise. The one genuinely useful signal is that Fictiv is now competitive on small parts, so it is worth quoting Fictiv on future small-part work.

Sheet Revision A0 to A1
B2: What Changed Between Fictiv's Two Quotes
B3: Fictiv re-issued three days after its first quote. Comparing like quantity (qty 1) isolates the repricing from the new volume tiers.
B5: Part | C5: A0 @ qty 1 | D5: A1 @ qty 1 | E5: Δ $ | F5: Δ %
B6: ='Inputs & Assumptions'!B18 -> 667357 Valve receptacle | C6: ='Inputs & Assumptions'!D18 -> 168.68 | D6: ='Inputs & Assumptions'!E18 -> 159.8 | E6: =D6-C6 -> -8.88 | F6: =IF(C6=0,0,D6/C6-1) -> -0.05264406
B7: ='Inputs & Assumptions'!B19 -> 667355 Chest | C7: ='Inputs & Assumptions'!D19 -> 1039.11 | D7: ='Inputs & Assumptions'!E19 -> 984.42 | E7: =D7-C7 -> -54.69 | F7: =IF(C7=0,0,D7/C7-1) -> -0.052631579
B8: ='Inputs & Assumptions'!B20 -> 667354 Base | C8: ='Inputs & Assumptions'!D20 -> 1709.77 | D8: ='Inputs & Assumptions'!E20 -> 1619.78 | E8: =D8-C8 -> -89.99 | F8: =IF(C8=0,0,D8/C8-1) -> -0.05263281
B9: KIT | C9: =SUM(C6:C8) -> 2917.56 | D9: =SUM(D6:D8) -> 2764 | E9: =D9-C9 -> -153.56 | F9: =IF(C9=0,0,D9/C9-1) -> -0.052633022
B11: READING THE REVISION
B12: Every part fell by the same ~5.26% | C12: A uniform across-the-board reduction, not a part-by-part re-engineering. This is a commercial gesture — a list-price adjustment — rather than a manufacturing improvement, so it carries no quality or process implication.
B13: The real change is the new volume tiers | C13: A0 offered qty 1 only. A1 adds 20 and 50. That, not the 5.26%, is what makes this quote comparable to Xometry.
B14: A0 is superseded | C14: Use A1 for every decision. A0 is retained here only to show the movement and to explain why the first comparison read a 63% gap.

Sheet Scope & Risk
B2: What The Price Comparison Still Does Not Capture
B3: The qty-50 comparison is now sound on price. These are the remaining differences in what each vendor is actually selling.
B5: BOTTOM LINE
B6: At qty 50: | C6: Xometry $1,090.80/kit vs Fictiv $1,716.54/kit — Xometry is 36.4% cheaper, $31,287 across 50 kits.
B7: Not the 63% first thought: | C7: That figure compared Fictiv at qty 1 with Xometry at qty 50. The real gap is roughly half of it.
B8: Fictiv wins one part: | C8: 667357 valve receptacle — $53.71 vs $59.58. Its volume curve is steepest on small parts.
B9: The gap is all in the big parts: | C9: Chest and base, where Fictiv is ~38% dearer. That is where any negotiation must land.
B10: Fictiv's discount is spent: | C10: 94% of its volume break is used up by qty 20. More volume will not close 36%.
B11: Before awarding: | C11: Refresh Xometry's 9-month-old pricing, align inspection scope and the 667355 drawing revision, and confirm colour.
B13: Difference | C13: What it means now that both are quoted at 50 | D13: Bias
B14: Inspection scope | C14: Xometry's unit price includes custom inspection, a formal dimensional report and 5 first articles. Fictiv's A1 quote still carries no inspection line. Adding equivalent inspection to Fictiv would widen the gap further, so the 36.4% is if anything understated. | D14: Favours Fictiv
B15: Xometry quote age | C15: Xometry's pricing is ~9 months old and its 30-day price honour lapsed in Dec 2025. Fictiv's is three days old. Xometry's real price today is unknown and is the single biggest open question in this comparison. | D15: Favours Xometry
B16: Drawing revision on 667355 (Chest) | C16: Fictiv quoted rev_c on both A0 and A1; Xometry quoted REV B. The vendors priced DIFFERENT geometry on the largest cost line after the base. This line is not strictly comparable until Xometry re-quotes rev C. | D16: Unknown
B17: Tolerance commitment | C17: Fictiv's A1 DFM feedback states tolerances will be dictated by printer capability ONLY and may be tighter or looser than indicated. Xometry states ±0.015" typical and will inspect to process standard in exception to the drawing. NEITHER vendor is committing to the drawing. | D17: Neutral
B18: Lead time at volume | C18: Fictiv's advantage disappears with quantity: 6 days at qty 1 but 32 at qty 50, against Xometry's 35 business days. At the quantity that matters they are broadly equal — and Xometry's clock only starts after FAI acceptance. | D18: Slightly Fictiv
B19: Colour specification | C19: Xometry specifies Black-Dyed on 667357 and 667354, natural on 667355. Fictiv's quote specifies no colour. If colour is required, Fictiv's price rises and the gap widens. | D19: Favours Fictiv
B20: Ink stamping / partner-matching | C20: Xometry's notes require month/year ink stamping and sourcing to a named prior partner for consistency. Neither is in Fictiv's scope — more cost inside Xometry's number with no Fictiv equivalent. | D20: Favours Fictiv
B21: Process: MJF vs SLS | C21: Both PA12 powder-bed, both vapor smoothed, broadly interchangeable. MJF gives finer feature resolution; SLS slightly better isotropic strength. Not identical parts, but not a defect either way. | D21: Neutral
B22: Shipping, tax | C22: Unpriced on both (TBD / calculated at checkout). Both US-domestic, so no tariff exposure. Neither total is a landed cost. | D22: Neutral
B24: 'Bias' names which vendor the difference favours once corrected — i.e. the direction the 36.4% gap would move if that difference were equalised. Most point toward Fictiv, so the true gap is somewhat narrower than 36.4% — but not enough to overturn the result.
