Workbook

Sheet Sources
A1: Quote Sources — Where the numbers come from
A3: Five quotes in the Fictiv series are compared head-to-head. All extended subtotals are normalized to Quote 2 quantities so the quotes are directly comparable. Quote 5 (Sep 3, 2026) is quoted in two volume tiers; its Tier 1 unit price (qty 2 per part, 26 business days) is the one carried into the comparison, to stay like-for-like with the Q2 quantity basis — the Tier 2 volume pricing and the landed-cost build-up live on the "Quote 5 Detail" tab. Xometry pricing appears at the right-most columns as a reference benchmark only.
A7: Quote | B7: Source / File | C7: Date | D7: Pricing Basis
A8: Quote 1 — Fictiv (AI, original) | B8: Image provided by user: Fictiv-vs-Xometry comparison table | C8: Pre-Apr 2026 | D8: Fictiv platform automated (AI-based) per-part quote. Per-piece pricing. The original AI quote that triggered Xometry benchmarking.
A9: Quote 2 — Fictiv (AI re-quote) | B9: PDF: felts_032526_US_A5.pdf | C9: April 23, 2026 | D9: Fictiv platform automated per-part quote (re-issue). Three production-day tiers; comparison uses the 20-day tier.
A10: Quote 3 — Fictiv (MP holistic, had error) | B10: PDF: Supine_Fictiv_Quote_2.pdf | C10: May 1, 2026 | D10: Fictiv MP holistic re-quote of full BOM after pushback. Contained a systematic +10.34% markup on 12 of 15 parts — Fictiv later acknowledged this as a quoting-team mistake.
A11: Quote 4 — Fictiv (MP corrected) ★ | B11: PDF: felts_032526_US_A5__1_.pdf | C11: May 11, 2026 | D11: Fictiv MP corrected quote. Sam Felts (Fictiv) email: 'small mistake on our side in the previous version… aligns correctly with Q2.' Net effect: Q2 prices preserved on 12 parts, Q3 discounts retained on the 3 MP-discounted parts (670832, 670833, 670845).
A12: Quote 5 — MJF China production (current) ◆ | B12: Images provided by user: 3-page quote, 15 line items + quote-level feedback | C12: September 3, 2026 | D12: Two-tier 3DP quote. Multi Jet Fusion (MJF) / Nylon 12 / Black / Vapor Smoothed / Per 2D drawing and DFM. Tier 1 = qty 2 per part @ 26 business days; Tier 2 = qty 30 per part @ 45 business days. China production, DAP shipping, 7.5% sales tax on parts. Quote-level feedback: LT excludes holiday such as 9.25-9.27; 10.1-10.7; 3DP parts exclude inspection report. NOTE: no vendor name appears on the pages provided — confirm it is Fictiv before citing it as such.
A13: Reference — Xometry | B13: Image provided by user: shown alongside Q1 Fictiv | C13: Same era as Q1 Fictiv | D13: Xometry per-piece pricing. Benchmark only. NOT part of the four-way Fictiv comparison.
A15: Quantities used for normalization (Q2 basis):
A16: PN | B16: Description | C16: Qty (Q2 basis)
A17: 670834 | B17: Rim Head | C17: 2
A18: 670836 | B18: Head Cap | C18: 2
A19: 670837 | B19: Foot Cap | C19: 2
A20: 670845 | B20: Hanging Plate | C20: 2
A21: 670842 | B21: Revasc Heart Plate | C21: 2
A22: 670820 | B22: Upper Right Support | C22: 4
A23: 670821 | B23: Upper Left Support | C23: 4
A24: 670823 | B24: Lower Left Support | C24: 4
A25: 670822 | B25: Lower Right Support | C25: 4
A26: 670832 | B26: Rim Right | C26: 2
A27: 670835 | B27: Rim Foot | C27: 2
A28: 670846 | B28: MVR Lung Plate | C28: 2
... A31: 670833 | B31: Rim Left | C31: 2
B32: Total parts | C32: =SUM(C17:C31) -> 40

Sheet Five-Quote Comparison
A1: Five-Quote Comparison — Q1 (AI orig) | Q2 (AI re-quote) | Q3 (MP w/ error) | Q4 (MP corrected) ★ | Q5 (MJF China, Sep 3) ◆
A2: All extended subtotals normalized to Quote 2 quantities. Q5 uses its Tier 1 unit price (qty 2 / 26 business days) for like-for-like comparison. Xometry shown at right as reference only.
A4: Part | D4: Qty | E4: Unit Price by Quote ($) | J4: Extended Subtotal @ Q2 Qty ($) | O4: Quote-to-Quote Δ (%) | S4: Reference: Xometry
A5: # | B5: Part No. | C5: Description | D5: Qty | E5: Q1 (AI orig) | F5: Q2 (Apr 23) | G5: Q3 (May 1) | H5: Q4 (May 11) ★ | I5: Q5 (Sep 3) ◆ | J5: Q1 Ext | K5: Q2 Ext | L5: Q3 Ext | M5: Q4 Ext ★ | N5: Q5 Ext ◆ | O5: Δ Q2→Q3 | P5: Δ Q3→Q4 ★ | Q5: Δ Q2→Q4 (net) | R5: Δ Q4→Q5 ◆ | S5: Xom. Unit | T5: Xom. Ext
A6: 1 | B6: 670834 | C6: Rim Head | D6: 2 | E6: 184.09 | F6: 97.15 | G6: 107.2 | H6: 97.15 | I6: ='Quote 5 Detail'!E24 -> 235.3 | J6: =$D6*E6 -> 368.18 | K6: =$D6*F6 -> 194.3 | L6: =$D6*G6 -> 214.4 | M6: =$D6*H6 -> 194.3 | N6: =$D6*I6 -> 470.6 | O6: =(G6-F6)/F6 -> 0.10344828 | P6: =(H6-G6)/G6 -> -0.09375 | Q6: =(H6-F6)/F6 -> 0 | R6: =(I6-H6)/H6 -> 1.4220278 | S6: 65.46 | T6: =$D6*S6 -> 130.92
A7: 2 | B7: 670836 | C7: Head Cap | D7: 2 | E7: 1412.2 | F7: 336.4 | G7: 371.2 | H7: 336.4 | I7: ='Quote 5 Detail'!E21 -> 1352.94 | J7: =$D7*E7 -> 2824.4 | K7: =$D7*F7 -> 672.8 | L7: =$D7*G7 -> 742.4 | M7: =$D7*H7 -> 672.8 | N7: =$D7*I7 -> 2705.88 | O7: =(G7-F7)/F7 -> 0.10344828 | P7: =(H7-G7)/G7 -> -0.09375 | Q7: =(H7-F7)/F7 -> 0 | R7: =(I7-H7)/H7 -> 3.0218193 | S7: 434.58 | T7: =$D7*S7 -> 869.16
A8: 3 | B8: 670837 | C8: Foot Cap | D8: 2 | E8: 5126.86 | F8: 661.2 | G8: 729.6 | H8: 661.2 | I8: ='Quote 5 Detail'!E20 -> 2176.48 | J8: =$D8*E8 -> 10253.72 | K8: =$D8*F8 -> 1322.4 | L8: =$D8*G8 -> 1459.2 | M8: =$D8*H8 -> 1322.4 | N8: =$D8*I8 -> 4352.96 | O8: =(G8-F8)/F8 -> 0.10344828 | P8: =(H8-G8)/G8 -> -0.09375 | Q8: =(H8-F8)/F8 -> 0 | R8: =(I8-H8)/H8 -> 2.291712 | S8: 1055.25 | T8: =$D8*S8 -> 2110.5
A9: 4 | B9: 670845 | C9: Hanging Plate | D9: 2 | E9: 67.4 | F9: 100.05 | G9: 80 | H9: 80 | I9: ='Quote 5 Detail'!E25 -> 164.7 | J9: =$D9*E9 -> 134.8 | K9: =$D9*F9 -> 200.1 | L9: =$D9*G9 -> 160 | M9: =$D9*H9 -> 160 | N9: =$D9*I9 -> 329.4 | O9: =(G9-F9)/F9 -> -0.2003998 | P9: =(H9-G9)/G9 -> 0 | Q9: =(H9-F9)/F9 -> -0.2003998 | R9: =(I9-H9)/H9 -> 1.05875 | S9: 35.19 | T9: =$D9*S9 -> 70.38
A10: 5 | B10: 670842 | C10: Revasc Heart Plate | D10: 2 | E10: 1148.34 | F10: 284.2 | G10: 313.6 | H10: 284.2 | I10: ='Quote 5 Detail'!E26 -> 1294.12 | J10: =$D10*E10 -> 2296.68 | K10: =$D10*F10 -> 568.4 | L10: =$D10*G10 -> 627.2 | M10: =$D10*H10 -> 568.4 | N10: =$D10*I10 -> 2588.24 | O10: =(G10-F10)/F10 -> 0.10344828 | P10: =(H10-G10)/G10 -> -0.09375 | Q10: =(H10-F10)/F10 -> 0 | R10: =(I10-H10)/H10 -> 3.5535538 | S10: 348.22 | T10: =$D10*S10 -> 696.44
A11: 6 | B11: 670820 | C11: Upper Right Support | D11: 4 | E11: 283.83 | F11: 150.8 | G11: 166.4 | H11: 150.8 | I11: ='Quote 5 Detail'!E22 -> 305.88 | J11: =$D11*E11 -> 1135.32 | K11: =$D11*F11 -> 603.2 | L11: =$D11*G11 -> 665.6 | M11: =$D11*H11 -> 603.2 | N11: =$D11*I11 -> 1223.52 | O11: =(G11-F11)/F11 -> 0.10344828 | P11: =(H11-G11)/G11 -> -0.09375 | Q11: =(H11-F11)/F11 -> 0 | R11: =(I11-H11)/H11 -> 1.028382 | S11: 96.91 | T11: =$D11*S11 -> 387.64
A12: 7 | B12: 670821 | C12: Upper Left Support | D12: 4 | E12: 283.79 | F12: 150.8 | G12: 166.4 | H12: 150.8 | I12: ='Quote 5 Detail'!E27 -> 305.88 | J12: =$D12*E12 -> 1135.16 | K12: =$D12*F12 -> 603.2 | L12: =$D12*G12 -> 665.6 | M12: =$D12*H12 -> 603.2 | N12: =$D12*I12 -> 1223.52 | O12: =(G12-F12)/F12 -> 0.10344828 | P12: =(H12-G12)/G12 -> -0.09375 | Q12: =(H12-F12)/F12 -> 0 | R12: =(I12-H12)/H12 -> 1.028382 | S12: 96.92 | T12: =$D12*S12 -> 387.68
A13: 8 | B13: 670823 | C13: Lower Left Support | D13: 4 | E13: 323.16 | F13: 256.65 | G13: 283.2 | H13: 256.65 | I13: ='Quote 5 Detail'!E23 -> 329.42 | J13: =$D13*E13 -> 1292.64 | K13: =$D13*F13 -> 1026.6 | L13: =$D13*G13 -> 1132.8 | M13: =$D13*H13 -> 1026.6 | N13: =$D13*I13 -> 1317.68 | O13: =(G13-F13)/F13 -> 0.10344828 | P13: =(H13-G13)/G13 -> -0.09375 | Q13: =(H13-F13)/F13 -> 0 | R13: =(I13-H13)/H13 -> 0.28353789 | S13: 107.4 | T13: =$D13*S13 -> 429.6
A14: 9 | B14: 670822 | C14: Lower Right Support | D14: 4 | E14: 321.38 | F14: 256.65 | G14: 283.2 | H14: 256.65 | I14: ='Quote 5 Detail'!E28 -> 352.94 | J14: =$D14*E14 -> 1285.52 | K14: =$D14*F14 -> 1026.6 | L14: =$D14*G14 -> 1132.8 | M14: =$D14*H14 -> 1026.6 | N14: =$D14*I14 -> 1411.76 | O14: =(G14-F14)/F14 -> 0.10344828 | P14: =(H14-G14)/G14 -> -0.09375 | Q14: =(H14-F14)/F14 -> 0 | R14: =(I14-H14)/H14 -> 0.37518021 | S14: 107.08 | T14: =$D14*S14 -> 428.32
A15: 10 | B15: 670832 | C15: Rim Right | D15: 2 | E15: 365.95 | F15: 691.65 | G15: 524.7 | H15: 524.7 | I15: ='Quote 5 Detail'!E19 -> 932.36 | J15: =$D15*E15 -> 731.9 | K15: =$D15*F15 -> 1383.3 | L15: =$D15*G15 -> 1049.4 | M15: =$D15*H15 -> 1049.4 | N15: =$D15*I15 -> 1864.72 | O15: =(G15-F15)/F15 -> -0.24137931 | P15: =(H15-G15)/G15 -> 0 | Q15: =(H15-F15)/F15 -> -0.24137931 | R15: =(I15-H15)/H15 -> 0.7769392 | S15: 284.5 | T15: =$D15*S15 -> 569
A16: 11 | B16: 670835 | C16: Rim Foot | D16: 2 | E16: 205.52 | F16: 107.3 | G16: 118.4 | H16: 107.3 | I16: ='Quote 5 Detail'!E29 -> 223.52 | J16: =$D16*E16 -> 411.04 | K16: =$D16*F16 -> 214.6 | L16: =$D16*G16 -> 236.8 | M16: =$D16*H16 -> 214.6 | N16: =$D16*I16 -> 447.04 | O16: =(G16-F16)/F16 -> 0.10344828 | P16: =(H16-G16)/G16 -> -0.09375 | Q16: =(H16-F16)/F16 -> 0 | R16: =(I16-H16)/H16 -> 1.0831314 | S16: 66.5 | T16: =$D16*S16 -> 133
A17: 12 | B17: 670846 | C17: MVR Lung Plate | D17: 2 | E17: 1380.42 | F17: 348 | G17: 384 | H17: 348 | I17: ='Quote 5 Detail'!E31 -> 1741.18 | J17: =$D17*E17 -> 2760.84 | K17: =$D17*F17 -> 696 | L17: =$D17*G17 -> 768 | M17: =$D17*H17 -> 696 | N17: =$D17*I17 -> 3482.36 | O17: =(G17-F17)/F17 -> 0.10344828 | P17: =(H17-G17)/G17 -> -0.09375 | Q17: =(H17-F17)/F17 -> 0 | R17: =(I17-H17)/H17 -> 4.0033908 | S17: 442.78 | T17: =$D17*S17 -> 885.56
A18: 13 | B18: 670839 | C18: Handle 1 | D18: 4 | E18: 353.52 | F18: 187.05 | G18: 206.4 | H18: 187.05 | I18: ='Quote 5 Detail'!E32 -> 441.18 | J18: =$D18*E18 -> 1414.08 | K18: =$D18*F18 -> 748.2 | L18: =$D18*G18 -> 825.6 | M18: =$D18*H18 -> 748.2 | N18: =$D18*I18 -> 1764.72 | O18: =(G18-F18)/F18 -> 0.10344828 | P18: =(H18-G18)/G18 -> -0.09375 | Q18: =(H18-F18)/F18 -> 0 | R18: =(I18-H18)/H18 -> 1.3586207 | S18: 165.91 | T18: =$D18*S18 -> 663.64
A19: 14 | B19: 670841 | C19: Heart Base Riser | D19: 2 | E19: 421.06 | F19: 230.55 | G19: 254.4 | H19: 230.55 | I19: ='Quote 5 Detail'!E30 -> 1176.48 | J19: =$D19*E19 -> 842.12 | K19: =$D19*F19 -> 461.1 | L19: =$D19*G19 -> 508.8 | M19: =$D19*H19 -> 461.1 | N19: =$D19*I19 -> 2352.96 | O19: =(G19-F19)/F19 -> 0.10344828 | P19: =(H19-G19)/G19 -> -0.09375 | Q19: =(H19-F19)/F19 -> 0 | R19: =(I19-H19)/H19 -> 4.1029278 | S19: 292.3 | T19: =$D19*S19 -> 584.6
A20: 15 | B20: 670833 | C20: Rim Left | D20: 2 | E20: 315.91 | F20: 690.2 | G20: 523.6 | H20: 523.6 | I20: ='Quote 5 Detail'!E33 -> 932.36 | J20: =$D20*E20 -> 631.82 | K20: =$D20*F20 -> 1380.4 | L20: =$D20*G20 -> 1047.2 | M20: =$D20*H20 -> 1047.2 | N20: =$D20*I20 -> 1864.72 | O20: =(G20-F20)/F20 -> -0.24137931 | P20: =(H20-G20)/G20 -> 0 | Q20: =(H20-F20)/F20 -> -0.24137931 | R20: =(I20-H20)/H20 -> 0.78067227 | S20: 284.5 | T20: =$D20*S20 -> 569
C21: TOTAL (parts only, @ Q2 qty) | J21: =SUM(J6:J20) -> 27518.22 | K21: =SUM(K6:K20) -> 11101.2 | L21: =SUM(L6:L20) -> 11235.8 | M21: =SUM(M6:M20) -> 10394 | N21: =SUM(N6:N20) -> 27400.08 | O21: =(L21-K21)/K21 -> 0.012124815 | P21: =(M21-L21)/L21 -> -0.074921234 | Q21: =(M21-K21)/K21 -> -0.063704825 | R21: =(N21-M21)/M21 -> 1.6361439 | T21: =SUM(T6:T20) -> 8915.44
A23: ★ = Q4 (corrected MP quote). ◆ = Q5, the current quote (Sep 3, 2026).
A24: • Δ Q2→Q3: the +10.34% systematic markup that Fictiv later acknowledged as a mistake.
A25: • Δ Q3→Q4: the correction step — Q4 rolls back 12 parts to Q2 prices; keeps 3 parts at Q3 discount.
A26: • Δ Q2→Q4: the net MP value-add after correction. Equals exactly the genuine MP-discount savings on 670832, 670833, 670845.
A27: • Δ Q4→Q5: the move in the current quote. Q5 is a two-tier quote; this column compares its Tier 1 (qty 2 / 26-day) unit price against Q4.
A28: • Q5 unit prices are pulled from the "Quote 5 Detail" tab (cells E19:E33) so there is a single place to correct them.
A29: • Q4 PDF lists Head Cap (670836) at qty 4; normalized to qty 2 here to match Q2 basis (established convention).
A30: • Neither the Fictiv quotes nor Q5 include FAI / inspection — Q5 states explicitly that 3DP parts exclude the inspection report.
A31: • CAVEAT: Q5 is explicitly MJF / Nylon 12 / vapor-smoothed. The V3 workbook never recorded the process for Q1–Q4, so confirm they were quoted to the same finish spec before treating Δ Q4→Q5 as a pure price move.

Sheet Quote 5 Detail
A1: Quote 5 — As-Quoted Detail (quote date: September 3, 2026)
A2: Transcribed from the 3-page quote images supplied by the user on Sep 3, 2026. Both stated totals reconcile exactly from these line items (see the Tier structure check column), which is the transcription's proof of accuracy. Yellow cells are the as-quoted inputs — edit those; every other cell is a formula.
A4: Quote inputs & assumptions — edit the yellow cells only
A5: Quote date | B5: 46268 | C5: Vendor name does not appear on the pages provided — confirm before citing as Fictiv.
A6: Process / finish (as quoted) | B6: Multi Jet Fusion (MJF) / Nylon 12 / Black / Vapor Smoothed / Per 2D drawing and DFM
A7: Sales tax on parts | B7: 0.075
A8: Back-solve divisor (assumed margin gross-up) | B8: 0.85 | C8: B8 = 0.85 is an inference, not a quoted figure: 13 of 15 Tier-1 prices land on a round-dollar base when divided by it.
A9: Quote-level feedback | B9: LT excludes holiday such as 9.25-9.27; 10.1-10.7; 3DP parts exclude inspection report
A11: Tier structure & reconciliation against the as-quoted totals
A12: Tier | B12: Qty / part | C12: Lead time (bus. days) | D12: Parts subtotal ($) | E12: Sales tax ($) | F12: Freight, DAP ($) | G12: Landed total ($) | H12: As-quoted total ($) | I12: Check
A13: Tier 1 — prototype | B13: 2 | C13: 26 | D13: =SUM(F19:F33) -> 23929.48 | E13: =D13*$B$7 -> 1794.711 | F13: 1048.32 | G13: =D13+E13+F13 -> 26772.511 | H13: 26772.51 | I13: =IF(ABS(G13-H13)<0.02,"OK","MISMATCH") -> OK
A14: Tier 2 — production | B14: 30 | C14: 45 | D14: =SUM(H19:H33) -> 161523.6 | E14: =D14*$B$7 -> 12114.27 | F14: 8555.32 | G14: =D14+E14+F14 -> 182193.19 | H14: 182193.19 | I14: =IF(ABS(G14-H14)<0.02,"OK","MISMATCH") -> OK
A16: As-quoted line items — all 15 parts, both tiers, with price-structure back-solve
A17: Part | E17: Tier 1 — qty 2 @ 26 business days | G17: Tier 2 — qty 30 @ 45 business days | I17: Ratio | J17: Price-structure back-solve | L17: DFM
A18: # | B18: Part No. | C18: Description | D18: Quoted file | E18: Unit ($) | F18: Ext ($) | G18: Unit ($) | H18: Ext ($) | I18: T2 ÷ T1 | J18: Base @ divisor ($) | K18: Round-$ base? | L18: Remarks / DFM feedback
A19: 1 | B19: 670832 | C19: Rim Right | D19: 670832_revb_-_supine_chestribcagerim_right.step | E19: 932.36 | F19: =E19*$B$13 -> 1864.72 | G19: 419.56 | H19: =G19*$B$14 -> 12586.8 | I19: =G19/E19 -> 0.44999785 | J19: =E19*$B$8 -> 792.506 | K19: =IF(ABS(J19-ROUND(J19,0))<0.02,"Yes — $"&TEXT(ROUND(J19,0),"#,##0"),"NO — breaks pattern") -> NO — breaks pattern | L19: 1. Brass inserts will be used equivalent instead. 2. Printing tolerance will be +/-0.80mm.
A20: 2 | B20: 670837 | C20: Foot Cap | D20: 670837_reva_-_supine_chestfoot_capcap.step | E20: 2176.48 | F20: =E20*$B$13 -> 4352.96 | G20: 979.42 | H20: =G20*$B$14 -> 29382.6 | I20: =G20/E20 -> 0.45000184 | J20: =E20*$B$8 -> 1850.008 | K20: =IF(ABS(J20-ROUND(J20,0))<0.02,"Yes — $"&TEXT(ROUND(J20,0),"#,##0"),"NO — breaks pattern") -> Yes — $1,850 | L20: 1. Brass inserts will be used equivalent instead. 2. Printing tolerance will be +/-0.80mm.
A21: 3 | B21: 670836 | C21: Head Cap | D21: 670836_reva_-_supine_chesthead_capcap.step | E21: 1352.94 | F21: =E21*$B$13 -> 2705.88 | G21: 608.83 | H21: =G21*$B$14 -> 18264.9 | I21: =G21/E21 -> 0.45000517 | J21: =E21*$B$8 -> 1149.999 | K21: =IF(ABS(J21-ROUND(J21,0))<0.02,"Yes — $"&TEXT(ROUND(J21,0),"#,##0"),"NO — breaks pattern") -> Yes — $1,150 | L21: 1. Brass inserts will be used equivalent instead. 2. Printing tolerance will be +/-0.80mm.
A22: 4 | B22: 670820 | C22: Upper Right Support | D22: 670820_reva_-_supine_chestribcageupper_right_support.step | E22: 305.88 | F22: =E22*$B$13 -> 611.76 | G22: 137.65 | H22: =G22*$B$14 -> 4129.5 | I22: =G22/E22 -> 0.45001308 | J22: =E22*$B$8 -> 259.998 | K22: =IF(ABS(J22-ROUND(J22,0))<0.02,"Yes — $"&TEXT(ROUND(J22,0),"#,##0"),"NO — breaks pattern") -> Yes — $260 | L22: 1. Brass inserts will be used equivalent instead. 2. Printing tolerance will be +/-0.80mm.
A23: 5 | B23: 670823 | C23: Lower Left Support | D23: 670823_revb_-_supine_chestribcagelower_left_support.step | E23: 329.42 | F23: =E23*$B$13 -> 658.84 | G23: 148.23 | H23: =G23*$B$14 -> 4446.9 | I23: =G23/E23 -> 0.44997268 | J23: =E23*$B$8 -> 280.007 | K23: =IF(ABS(J23-ROUND(J23,0))<0.02,"Yes — $"&TEXT(ROUND(J23,0),"#,##0"),"NO — breaks pattern") -> Yes — $280 | L23: 1. Brass inserts will be used equivalent instead. 2. Printing tolerance will be +/-0.80mm.
A24: 6 | B24: 670834 | C24: Rim Head | D24: 670834_reva_-_supine_chestribcagerim_head.step | E24: 235.3 | F24: =E24*$B$13 -> 470.6 | G24: 105.88 | H24: =G24*$B$14 -> 3176.4 | I24: =G24/E24 -> 0.44997875 | J24: =E24*$B$8 -> 200.005 | K24: =IF(ABS(J24-ROUND(J24,0))<0.02,"Yes — $"&TEXT(ROUND(J24,0),"#,##0"),"NO — breaks pattern") -> Yes — $200 | L24: Printing tolerance will be +/-0.80mm.
A25: 7 | B25: 670845 | C25: Hanging Plate | D25: 670845_revb_-_supine_chestrevaschanging_plate.step | E25: 164.7 | F25: =E25*$B$13 -> 329.4 | G25: 74.12 | H25: =G25*$B$14 -> 2223.6 | I25: =G25/E25 -> 0.45003036 | J25: =E25*$B$8 -> 139.995 | K25: =IF(ABS(J25-ROUND(J25,0))<0.02,"Yes — $"&TEXT(ROUND(J25,0),"#,##0"),"NO — breaks pattern") -> Yes — $140 | L25: 1. Brass inserts will be used equivalent instead. 2. Printing tolerance will be +/-0.80mm.
A26: 8 | B26: 670842 | C26: Revasc Heart Plate | D26: 670842_reva_-_supine_chestrevasc_heart_plate.stl | E26: 1294.12 | F26: =E26*$B$13 -> 2588.24 | G26: 582.35 | H26: =G26*$B$14 -> 17470.5 | I26: =G26/E26 -> 0.44999691 | J26: =E26*$B$8 -> 1100.002 | K26: =IF(ABS(J26-ROUND(J26,0))<0.02,"Yes — $"&TEXT(ROUND(J26,0),"#,##0"),"NO — breaks pattern") -> Yes — $1,100 | L26: 1. Brass inserts will be used equivalent instead. 2. Printing tolerance will be +/-0.80mm.
A27: 9 | B27: 670821 | C27: Upper Left Support | D27: 670821_reva_-_supine_chestribcageupper_left_support.step | E27: 305.88 | F27: =E27*$B$13 -> 611.76 | G27: 137.65 | H27: =G27*$B$14 -> 4129.5 | I27: =G27/E27 -> 0.45001308 | J27: =E27*$B$8 -> 259.998 | K27: =IF(ABS(J27-ROUND(J27,0))<0.02,"Yes — $"&TEXT(ROUND(J27,0),"#,##0"),"NO — breaks pattern") -> Yes — $260 | L27: 1. Brass inserts will be used equivalent instead. 2. Printing tolerance will be +/-0.80mm.
A28: 10 | B28: 670822 | C28: Lower Right Support | D28: 670822_revb_-_supine_chestribcagelower_right_support.step | E28: 352.94 | F28: =E28*$B$13 -> 705.88 | G28: 158.83 | H28: =G28*$B$14 -> 4764.9 | I28: =G28/E28 -> 0.45001983 | J28: =E28*$B$8 -> 299.999 | K28: =IF(ABS(J28-ROUND(J28,0))<0.02,"Yes — $"&TEXT(ROUND(J28,0),"#,##0"),"NO — breaks pattern") -> Yes — $300 | L28: 1. Brass inserts will be used equivalent instead. 2. Printing tolerance will be +/-0.80mm.
A29: 11 | B29: 670835 | C29: Rim Foot | D29: 670835_reva_-_supine_chestribcagerim_foot.step | E29: 223.52 | F29: =E29*$B$13 -> 447.04 | G29: 100.58 | H29: =G29*$B$14 -> 3017.4 | I29: =G29/E29 -> 0.4499821 | J29: =E29*$B$8 -> 189.992 | K29: =IF(ABS(J29-ROUND(J29,0))<0.02,"Yes — $"&TEXT(ROUND(J29,0),"#,##0"),"NO — breaks pattern") -> Yes — $190 | L29: Printing tolerance will be +/-0.80mm.
A30: 12 | B30: 670841 | C30: Heart Base Riser | D30: 670841_reva_-_supine_chestheart_baseriser.step | E30: 1176.48 | F30: =E30*$B$13 -> 2352.96 | G30: 529.42 | H30: =G30*$B$14 -> 15882.6 | I30: =G30/E30 -> 0.4500034 | J30: =E30*$B$8 -> 1000.008 | K30: =IF(ABS(J30-ROUND(J30,0))<0.02,"Yes — $"&TEXT(ROUND(J30,0),"#,##0"),"NO — breaks pattern") -> Yes — $1,000 | L30: 1. Brass inserts will be used equivalent instead. 2. Printing tolerance will be +/-0.80mm.
... A33: 15 | B33: 670833 | C33: Rim Left | D33: 670833_revb_-_supine_chestribcagerim_left.stl | E33: 932.36 | F33: =E33*$B$13 -> 1864.72 | G33: 419.56 | H33: =G33*$B$14 -> 12586.8 | I33: =G33/E33 -> 0.44999785 | J33: =E33*$B$8 -> 792.506 | K33: =IF(ABS(J33-ROUND(J33,0))<0.02,"Yes — $"&TEXT(ROUND(J33,0),"#,##0"),"NO — breaks pattern") -> NO — breaks pattern | L33: 1. Brass inserts will be used equivalent instead. 2. Printing tolerance will be +/-0.80mm.
C34: TOTAL — as quoted | F34: =SUM(F19:F33) -> 23929.48 | H34: =SUM(H19:H33) -> 161523.6
A36: Landed cost per part — sales tax + DAP freight allocated pro-rata by part value
A37: # | B37: Part No. | C37: Description | D37: T1 Ext ($) | E37: T1 freight alloc. ($) | F37: T1 landed ext ($) | G37: T1 landed / unit ($) | H37: T2 Ext ($) | I37: T2 freight alloc. ($) | J37: T2 landed ext ($) | K37: T2 landed / unit ($) | L37: T2 landed unit as % of T1
A38: =A19 -> 1 | B38: =B19 -> 670832 | C38: =C19 -> Rim Right | D38: =F19 -> 1864.72 | E38: =$F$13*D38/$D$13 -> 81.691005 | F38: =D38*(1+$B$7)+E38 -> 2086.265 | G38: =F38/$B$13 -> 1043.1325 | H38: =H19 -> 12586.8 | I38: =$F$14*H38/$D$14 -> 666.6772 | J38: =H38*(1+$B$7)+I38 -> 14197.487 | K38: =J38/$B$14 -> 473.24957 | L38: =K38/G38 -> 0.45368117
A39: =A20 -> 2 | B39: =B20 -> 670837 | C39: =C20 -> Foot Cap | D39: =F20 -> 4352.96 | E39: =$F$13*D39/$D$13 -> 190.69763 | F39: =D39*(1+$B$7)+E39 -> 4870.1296 | G39: =F39/$B$13 -> 2435.0648 | H39: =H20 -> 29382.6 | I39: =$F$14*H39/$D$14 -> 1556.2899 | J39: =H39*(1+$B$7)+I39 -> 33142.585 | K39: =J39/$B$14 -> 1104.7528 | L39: =K39/G39 -> 0.45368518
A40: =A21 -> 3 | B40: =B21 -> 670836 | C40: =C21 -> Head Cap | D40: =F21 -> 2705.88 | E40: =$F$13*D40/$D$13 -> 118.54115 | F40: =D40*(1+$B$7)+E40 -> 3027.3622 | G40: =F40/$B$13 -> 1513.6811 | H40: =H21 -> 18264.9 | I40: =$F$14*H40/$D$14 -> 967.42559 | J40: =H40*(1+$B$7)+I40 -> 20602.193 | K40: =J40/$B$14 -> 686.73977 | L40: =K40/G40 -> 0.45368855
A41: =A22 -> 4 | B41: =B22 -> 670820 | C41: =C22 -> Upper Right Support | D41: =F22 -> 611.76 | E41: =$F$13*D41/$D$13 -> 26.800425 | F41: =D41*(1+$B$7)+E41 -> 684.44243 | G41: =F41/$B$13 -> 342.22121 | H41: =H22 -> 4129.5 | I41: =$F$14*H41/$D$14 -> 218.72466 | J41: =H41*(1+$B$7)+I41 -> 4657.9372 | K41: =J41/$B$14 -> 155.26457 | L41: =K41/G41 -> 0.45369652
A42: =A23 -> 5 | B42: =B23 -> 670823 | C42: =C23 -> Lower Left Support | D42: =F23 -> 658.84 | E42: =$F$13*D42/$D$13 -> 28.86294 | F42: =D42*(1+$B$7)+E42 -> 737.11594 | G42: =F42/$B$13 -> 368.55797 | H42: =H23 -> 4446.9 | I42: =$F$14*H42/$D$14 -> 235.53618 | J42: =H42*(1+$B$7)+I42 -> 5015.9537 | K42: =J42/$B$14 -> 167.19846 | L42: =K42/G42 -> 0.45365579
A43: =A24 -> 6 | B43: =B24 -> 670834 | C43: =C24 -> Rim Head | D43: =F24 -> 470.6 | E43: =$F$13*D43/$D$13 -> 20.616386 | F43: =D43*(1+$B$7)+E43 -> 526.51139 | G43: =F43/$B$13 -> 263.25569 | H43: =H24 -> 3176.4 | I43: =$F$14*H43/$D$14 -> 168.2424 | J43: =H43*(1+$B$7)+I43 -> 3582.8724 | K43: =J43/$B$14 -> 119.42908 | L43: =K43/G43 -> 0.45366191
A44: =A25 -> 7 | B44: =B25 -> 670845 | C44: =C25 -> Hanging Plate | D44: =F25 -> 329.4 | E44: =$F$13*D44/$D$13 -> 14.430594 | F44: =D44*(1+$B$7)+E44 -> 368.53559 | G44: =F44/$B$13 -> 184.2678 | H44: =H25 -> 2223.6 | I44: =$F$14*H44/$D$14 -> 117.77604 | J44: =H44*(1+$B$7)+I44 -> 2508.146 | K44: =J44/$B$14 -> 83.604868 | L44: =K44/G44 -> 0.45371394
A45: =A26 -> 8 | B45: =B26 -> 670842 | C45: =C26 -> Revasc Heart Plate | D45: =F26 -> 2588.24 | E45: =$F$13*D45/$D$13 -> 113.38749 | F45: =D45*(1+$B$7)+E45 -> 2895.7455 | G45: =F45/$B$13 -> 1447.8727 | H45: =H26 -> 17470.5 | I45: =$F$14*H45/$D$14 -> 925.3491 | J45: =H45*(1+$B$7)+I45 -> 19706.137 | K45: =J45/$B$14 -> 656.87122 | L45: =K45/G45 -> 0.45368022
A46: =A27 -> 9 | B46: =B27 -> 670821 | C46: =C27 -> Upper Left Support | D46: =F27 -> 611.76 | E46: =$F$13*D46/$D$13 -> 26.800425 | F46: =D46*(1+$B$7)+E46 -> 684.44243 | G46: =F46/$B$13 -> 342.22121 | H46: =H27 -> 4129.5 | I46: =$F$14*H46/$D$14 -> 218.72466 | J46: =H46*(1+$B$7)+I46 -> 4657.9372 | K46: =J46/$B$14 -> 155.26457 | L46: =K46/G46 -> 0.45369652
A47: =A28 -> 10 | B47: =B28 -> 670822 | C47: =C28 -> Lower Right Support | D47: =F28 -> 705.88 | E47: =$F$13*D47/$D$13 -> 30.923703 | F47: =D47*(1+$B$7)+E47 -> 789.7447 | G47: =F47/$B$13 -> 394.87235 | H47: =H28 -> 4764.9 | I47: =$F$14*H47/$D$14 -> 252.37949 | J47: =H47*(1+$B$7)+I47 -> 5374.647 | K47: =J47/$B$14 -> 179.1549 | L47: =K47/G47 -> 0.45370333
A48: =A29 -> 11 | B48: =B29 -> 670835 | C48: =C29 -> Rim Foot | D48: =F29 -> 447.04 | E48: =$F$13*D48/$D$13 -> 19.584252 | F48: =D48*(1+$B$7)+E48 -> 500.15225 | G48: =F48/$B$13 -> 250.07613 | H48: =H29 -> 3017.4 | I48: =$F$14*H48/$D$14 -> 159.82075 | J48: =H48*(1+$B$7)+I48 -> 3403.5257 | K48: =J48/$B$14 -> 113.45086 | L48: =K48/G48 -> 0.45366529
A49: =A30 -> 12 | B49: =B30 -> 670841 | C49: =C30 -> Heart Base Riser | D49: =F30 -> 2352.96 | E49: =$F$13*D49/$D$13 -> 103.08018 | F49: =D49*(1+$B$7)+E49 -> 2632.5122 | G49: =F49/$B$13 -> 1316.2561 | H49: =H30 -> 15882.6 | I49: =$F$14*H49/$D$14 -> 841.24379 | J49: =H49*(1+$B$7)+I49 -> 17915.039 | K49: =J49/$B$14 -> 597.16796 | L49: =K49/G49 -> 0.45368676
... A52: =A33 -> 15 | B52: =B33 -> 670833 | C52: =C33 -> Rim Left | D52: =F33 -> 1864.72 | E52: =$F$13*D52/$D$13 -> 81.691005 | F52: =D52*(1+$B$7)+E52 -> 2086.265 | G52: =F52/$B$13 -> 1043.1325 | H52: =H33 -> 12586.8 | I52: =$F$14*H52/$D$14 -> 666.6772 | J52: =H52*(1+$B$7)+I52 -> 14197.487 | K52: =J52/$B$14 -> 473.24957 | L52: =K52/G52 -> 0.45368117
C53: TOTAL landed | D53: =SUM(D38:D52) -> 23929.48 | E53: =SUM(E38:E52) -> 1048.32 | F53: =SUM(F38:F52) -> 26772.511 | G53: =F53/($B$13*15) -> 892.41703 | H53: =SUM(H38:H52) -> 161523.6 | I53: =SUM(I38:I52) -> 8555.32 | J53: =SUM(J38:J52) -> 182193.19 | K53: =J53/($B$14*15) -> 404.87376
A54: G53 / K53 are the blended landed cost per piece across all 15 parts (landed total ÷ pieces), not a sum — the per-part figures above them are the ones to quote.
A56: Audit findings
A57: Volume-tier ratio — lowest across the 15 parts | D57: =MIN(I19:I33) -> 0.44997268 | E57: Tier 2 unit price as a share of Tier 1.
A58: Volume-tier ratio — highest across the 15 parts | D58: =MAX(I19:I33) -> 0.45003036
A59: Spread (highest − lowest) | D59: =D58-D57 -> 5.7678973e-05 | E59: A spread this close to zero means one flat multiplier was applied to every part, not part-by-part volume economics.
A60: Implied volume discount, Tier 1 → Tier 2 | D60: =1-AVERAGE(I19:I33) -> 0.55000122 | E60: A flat cut applied uniformly — so it is a pricing policy, not a reflection of how these parts nest or batch.
A61: Parts whose Tier-1 price back-solves to a round-dollar base | D61: =SUMPRODUCT(--(ABS(J19:J33-ROUND(J19:J33,0))<0.02)) -> 13 | E61: At the B8 divisor. The two exceptions are 670832 / 670833 — the mirrored rim pair.
A62: Implied gross margin at that back-solved base | D62: =1-$B$8 -> 0.15 | E62: If the round-dollar bases are the underlying cost, this is the margin sitting on top.
A63: Tier 1 — blended landed cost per piece | D63: =G53 -> 892.41703 | E63: Landed total ÷ 30 pieces (15 parts × qty 2).
A64: Tier 2 — blended landed cost per piece | D64: =K53 -> 404.87376 | E64: Landed total ÷ 450 pieces (15 parts × qty 30).
A65: Freight as % of parts subtotal — Tier 1 | D65: =F13/D13 -> 0.043808725
A66: Freight as % of parts subtotal — Tier 2 | D66: =F14/D14 -> 0.052966378 | E66: Freight scales close to linearly with part value, so there is little freight leverage in ordering more.
A68: Source: 3-page quote images supplied by the user, Sep 3, 2026. Vendor not named on those pages.
A69: Transcription proof: the 15 line items sum to the quote’s own stated part-price totals ($23,929.48 Tier 1 / $161,523.60 Tier 2), and parts × 1.075 + freight reproduces the stated grand totals ($26,772.51 / $182,193.19) to the cent.
A70: Assumption — tax base: the 7.5% is applied to the part price only, not to freight. This is what makes both stated grand totals reconcile exactly, so it is confirmed by the quote’s own arithmetic rather than assumed.
A71: Assumption — freight allocation: DAP freight is spread across parts in proportion to part value. The quote gives one freight figure per tier, not per part, so any split is a modelling choice; by weight or volume would shift it.
A72: Assumption — back-solve divisor (B8 = 0.85): inferred from the data, not quoted. Change B8 to test other margin assumptions; column K re-tests every part against it.
A73: Lead times exclude the 9.25–9.27 and 10.1–10.7 holiday periods — both fall inside a 26- or 45-business-day window starting Sep 3, so the calendar dates land later than the day counts suggest.

Sheet Summary
A1: Summary & Insights — Fictiv 3DP Quote Journey (V4, through Sep 3, 2026)
A3: Headline totals (part production, @ Q2 quantities)
A4: Quote 1 — Fictiv (AI, original) | B4: ='Five-Quote Comparison'!J21 -> 27518.22
A5: Quote 2 — Fictiv (AI re-quote, Apr 23) | B5: ='Five-Quote Comparison'!K21 -> 11101.2
A6: Quote 3 — Fictiv (MP w/ error, May 1) | B6: ='Five-Quote Comparison'!L21 -> 11235.8
A7: Quote 4 — Fictiv (MP corrected, May 11) ★ | B7: ='Five-Quote Comparison'!M21 -> 10394
A8: Quote 5 — MJF China production (Sep 3) ◆ — Tier 1 unit price, like-for-like | B8: ='Five-Quote Comparison'!N21 -> 27400.08
A10: The corrected-quote story (Q1 → Q4), unchanged from V3
A11: Δ Q1 → Q4 ($) — full journey | B11: ='Five-Quote Comparison'!M21-'Five-Quote Comparison'!J21 -> -17124.22
A12: Δ Q1 → Q4 (%) — full journey | B12: =('Five-Quote Comparison'!M21-'Five-Quote Comparison'!J21)/'Five-Quote Comparison'!J21 -> -0.62228662
A13: Δ Q2 → Q4 ($) — MP net value | B13: ='Five-Quote Comparison'!M21-'Five-Quote Comparison'!K21 -> -707.2
A14: Δ Q2 → Q4 (%) — MP net value | B14: ='Five-Quote Comparison'!Q21 -> -0.063704825
A15: Δ Q3 → Q4 ($) — correction | B15: ='Five-Quote Comparison'!M21-'Five-Quote Comparison'!L21 -> -841.8
A16: Δ Q3 → Q4 (%) — correction | B16: ='Five-Quote Comparison'!P21 -> -0.074921234
A18: The new quote (Q5, Sep 3, 2026) against the journey so far
A19: Δ Q4 → Q5 ($) — the current move | B19: ='Five-Quote Comparison'!N21-'Five-Quote Comparison'!M21 -> 17006.08
A20: Δ Q4 → Q5 (%) — the current move | B20: ='Five-Quote Comparison'!R21 -> 1.6361439
A21: Δ Q1 → Q5 ($) — Q5 vs the original AI quote | B21: ='Five-Quote Comparison'!N21-'Five-Quote Comparison'!J21 -> -118.14
A22: Δ Q1 → Q5 (%) — Q5 vs the original AI quote | B22: =('Five-Quote Comparison'!N21-'Five-Quote Comparison'!J21)/'Five-Quote Comparison'!J21 -> -0.0042931556
A23: Q5 landed total — Tier 1 as quoted (qty 2/part, incl. 7.5% tax + DAP freight) | B23: ='Quote 5 Detail'!G13 -> 26772.511
A24: Q5 landed total — Tier 2 as quoted (qty 30/part) | B24: ='Quote 5 Detail'!G14 -> 182193.19
A25: Q5 blended landed cost per piece — Tier 1 | B25: ='Quote 5 Detail'!G53 -> 892.41703
A26: Q5 blended landed cost per piece — Tier 2 | B26: ='Quote 5 Detail'!K53 -> 404.87376
A28: Reference — Xometry benchmark (@ Q2 qty, parts only)
A29: Xometry total | B29: ='Five-Quote Comparison'!T21 -> 8915.44
A30: Q4 premium over Xometry ($) | B30: ='Five-Quote Comparison'!M21-'Five-Quote Comparison'!T21 -> 1478.56
A31: Q4 premium over Xometry (%) | B31: =('Five-Quote Comparison'!M21-'Five-Quote Comparison'!T21)/'Five-Quote Comparison'!T21 -> 0.16584263
A32: Q5 premium over Xometry ($) | B32: ='Five-Quote Comparison'!N21-'Five-Quote Comparison'!T21 -> 18484.64
A33: Q5 premium over Xometry (%) | B33: =('Five-Quote Comparison'!N21-'Five-Quote Comparison'!T21)/'Five-Quote Comparison'!T21 -> 2.073329
A35: MP value-add decomposition (Q2 → Q4)
A36: Category | B36: # Parts | C36: Q2 Ext ($) | D36: Q4 Ext ($)
A37: Parts rolled back to Q2 price (no MP value) | B37: =COUNTIF('Five-Quote Comparison'!Q6:Q20,"=0") -> 12 | C37: =SUMIF('Five-Quote Comparison'!Q6:Q20,"=0",'Five-Quote Comparison'!K6:K20) -> 8137.4 | D37: =SUMIF('Five-Quote Comparison'!Q6:Q20,"=0",'Five-Quote Comparison'!M6:M20) -> 8137.4
A38: Parts kept at MP discount (genuine MP value) ★ | B38: =COUNTIF('Five-Quote Comparison'!Q6:Q20,"<0") -> 3 | C38: =SUMIF('Five-Quote Comparison'!Q6:Q20,"<0",'Five-Quote Comparison'!K6:K20) -> 2963.8 | D38: =SUMIF('Five-Quote Comparison'!Q6:Q20,"<0",'Five-Quote Comparison'!M6:M20) -> 2256.6
A40: Quote 5 audit findings (detail and formulas on the "Quote 5 Detail" tab)
A41: Volume-tier discount, Tier 1 → Tier 2 (applied uniformly to all 15 parts) | B41: ='Quote 5 Detail'!D60 -> 0.55000122
A42: Spread in that tier ratio across the 15 parts | B42: ='Quote 5 Detail'!D59 -> 5.7678973e-05
A43: Parts whose Tier-1 price back-solves to a round-dollar base at 85% | B43: ='Quote 5 Detail'!D61 -> 13
A44: Implied gross margin at that back-solved base | B44: ='Quote 5 Detail'!D62 -> 0.15
A45: DAP freight as % of parts subtotal — Tier 1 | B45: ='Quote 5 Detail'!D65 -> 0.043808725
A46: DAP freight as % of parts subtotal — Tier 2 | B46: ='Quote 5 Detail'!D66 -> 0.052966378
A48: Key observations
A49: 1. CONFIRMED (V3, unchanged): the +10.34% systematic markup flagged in V2 was a quoting-team mistake. Q4 surgically rolls back 12 of 15 parts to Q2 prices while preserving the 3 MP-discount parts at Q3 prices.
A50: 2. The MP's TRUE value-add (Q2→Q4) is $707.20 (-6.4%), entirely concentrated in three parts: 670832 Rim Right (-$333.90), 670833 Rim Left (-$333.20), and 670845 Hanging Plate (-$40.10). Sum = exactly $707.20.
A51: 3. The two big-ticket discounts (670832/670833) are mirrored parts with identical Q2→Q4 savings to four sig figs. Strongly suggests these parts nest or process together more efficiently than the AI quoter modeled.
A52: 4. Q4 Head Cap (670836) is still quoted at qty 4 in the PDF — confirmed as intentional (not a quoting bug), so the per-unit story is clean even though the as-issued totals differ.
A53: 5. Q4 sits ~17% above the Xometry benchmark at like-for-like quantities (down from ~26% in Q3). Meaningful narrowing of the gap, but still a material premium worth thinking about as a sourcing question.
A54: 6. The original V1/V2 hypothesis is vindicated — pushing back on the +10.34% pattern was the right call. When MP holistic re-quotes show suspiciously uniform price moves on most parts but big concessions on a few, default to suspecting a multiplier error.
A55: 7. NEW — Q5 lands almost exactly back at Q1. At like-for-like quantities Q5 totals ~$27.4k against Q1's $27.5k, within ~0.4%. Sixteen months of re-quoting and one acknowledged correction have, at prototype volume, returned to the original AI quote's level. That is the headline to take into the next conversation.
A56: 8. NEW — the Q5 volume discount is a flat multiplier, not part economics. Every one of the 15 Tier-2 prices is exactly 45.00% of its Tier-1 price; the spread across all 15 parts is effectively zero. A genuine volume curve would differ part by part, because nesting efficiency, part height and post-processing labour do not scale identically. This is a pricing policy applied on top, which means it is negotiable — and it is worth asking for a mid-tier (qty 5–10) rather than being pushed from 2 straight to 30.
A57: 9. NEW — 13 of 15 Tier-1 prices back-solve to a round-dollar base at an 85% divisor ($200, $260, $280, $300, $375, $1,000, $1,100, $1,150, $1,480, $1,850 and so on), implying a round internal cost with a 15% margin on top. The two that break the pattern are 670832 and 670833 — the same mirrored rim pair that carried the real MP discounts in Q3/Q4. Those two appear to have been priced by hand while the other 13 came off a rate card.
A58: 10. NEW — freight gives no leverage. DAP freight runs ~4.4% of parts subtotal at Tier 1 and ~5.3% at Tier 2, so it scales with value rather than flattening out. Ordering more does not amortise shipping; the case for Tier 2 has to be made on the 55% part discount alone.
A59: 11. OPEN — process parity is unverified. Q5 is explicitly MJF / Nylon 12 / Black / Vapor Smoothed. The workbook never recorded the process for Q1–Q4, and vapor smoothing is a real cost adder. Confirm Q1–Q4 were quoted to the same finish spec before treating Δ Q4→Q5 as a like-for-like price move — if they were not, most of the Q4→Q5 jump may be scope, not inflation.
A60: 12. OPEN — the vendor on the Q5 pages is not named. The pages supplied show no vendor identity, and the quote is China production while the Fictiv history is not documented as such. Confirm the issuer before this row is cited internally as a Fictiv quote.
