Workbook

Sheet README
B2: Prompt Template Configurator
B3: v1.1 · August 2026 · owner Oscar Penny · generated from prompt-library/taxonomy/ (the source of truth — edit there, rebuild with src/build_configurator_xlsx.py)
B5: How to use
B6: START ON THE Tasks SHEET: pick one of the five course tasks, mark the requirements you need Yes, edit the yellow wording, and copy the assembled prompt (or the course prompt directly). The sheets below are the advanced, element-level builder.
B7: 1. Advanced: open Builder_Gen (chat prompts) or Builder_Agent (agent mission briefs).
B8: 2. Fill the YELLOW cells only: pick options from the dropdowns; add or override with custom text. Attributes marked "choice 1/2/3" accept several picks.
B9: 3. The prompt assembles itself on Prompt_Gen / Prompt_Agent — copy cell A4 into your AI tool.
B10: 4. Search the assembled prompt for {{ before you run — placeholders left unfilled mean you are not done.
B12: Legend
B13: YELLOW fill = cells you edit (dropdown choice, custom text). Everything else is generated — leave it.
B14: ★ next to an element name = keep this element; it is what makes the prompt reliable.
B15: The Options sheet is the full menu with guidance (core + extended); Taxonomy defines every element.
... B20: Companion tools: Prompt_Template_Creator.html (the interactive builder — same taxonomy, richer experience) · Prompt_Element_Taxonomy_Reference.pdf (the printed ontology).

Sheet Tasks
A1: THE FIVE COURSE TASKS — mark Include? = Yes, edit the yellow wording, copy the ASSEMBLED PROMPT (column E). A simple task needs only a few rows.
A3: ANALYZE SPREADSHEET DATA
B4: The course prompt (copy-ready): | C4: Use Course_Workbook.xlsx, Data tab, detail rows only — exclude the TOTAL row (144 rows; one Inspection_Hours cell is "n/a": treat it as missing, not zero, and disclose it). One row = one month × site × supplier; period 2025-09 to 2026-08 inclusive. Question: which supplier has the highest RETURN RATE, defined as total Units_Returned ÷ total Units_Shipped per supplier over the full period — computed from sums, never by averaging monthly percentages. Keep Defects_Found separate from returns; do not add them together. Rank the three suppliers showing numerator and denominator, reconcile total shipped and returned against the TOTAL row, and state one limitation of the comparison. Then stop.
B5: Your task line (edit): | C5: Help [reader] decide [decision] using [file / sheet], period [range], detail rows only.
A6: Include? | B6: Requirement type | C6: Your instruction (edit) | D6: How to check it
A7: No | B7: Row grain | C7: State that each detail row is a month–site–supplier observation. | D7: Confirm grouping keys before aggregation. | F7: =IF(AND($A7="Yes",$C7<>""),"- "&$C7,"") | G7: =IF($A7="Yes","- "&$D7,"")
A8: No | B8: Reporting period | C8: Use an explicit inclusive month range from Month. | D8: Check the first and last included months. | F8: =IF(AND($A8="Yes",$C8<>""),"- "&$C8,"") | G8: =IF($A8="Yes","- "&$D8,"")
A9: No | B9: Field types and units | C9: Treat Month as a month; identify counts, percentages, hours, and currency. | D9: Check parsing and unit labels. | F9: =IF(AND($A9="Yes",$C9<>""),"- "&$C9,"") | G9: =IF($A9="Yes","- "&$D9,"")
A10: No | B10: Duplicates and summary rows | C10: Exclude the existing TOTAL row and investigate duplicate keys. | D10: Compare row counts and a duplicate-key report. | F10: =IF(AND($A10="Yes",$C10<>""),"- "&$C10,"") | G10: =IF($A10="Yes","- "&$D10,"")
A11: No | B11: Metric definition | C11: Define return rate as sum of Units_Returned divided by sum of Units_Shipped. | D11: Recompute the numerator, denominator, and displayed rate. | F11: =IF(AND($A11="Yes",$C11<>""),"- "&$C11,"") | G11: =IF($A11="Yes","- "&$D11,"")
A12: No | B12: Weighting and denominators | C12: Do not infer overall on-time delivery from monthly percentages without delivery counts. | D12: Flag the missing denominator instead of claiming an overall rate. | F12: =IF(AND($A12="Yes",$C12<>""),"- "&$C12,"") | G12: =IF($A12="Yes","- "&$D12,"")
A13: No | B13: Missing and invalid values | C13: Retain the missing Inspection_Hours value; disclose any exclusion. | D13: Inspect missing-value counts and affected calculations. | F13: =IF(AND($A13="Yes",$C13<>""),"- "&$C13,"") | G13: =IF($A13="Yes","- "&$D13,"")
A14: No | B14: Segmentation and comparison | C14: Compare suppliers on the same selected period and sites. | D14: Confirm equal filter scope for each comparison. | F14: =IF(AND($A14="Yes",$C14<>""),"- "&$C14,"") | G14: =IF($A14="Yes","- "&$D14,"")
A15: No | B15: Rounding and number formats | C15: Display return rates to three decimal places while retaining calculation precision. | D15: Check displayed 0.348% against the underlying ratio. | F15: =IF(AND($A15="Yes",$C15<>""),"- "&$C15,"") | G15: =IF($A15="Yes","- "&$D15,"")
A16: No | B16: Formula traceability | C16: Use inspectable formulas or an included calculation log. | D16: Trace one output to its input rows. | F16: =IF(AND($A16="Yes",$C16<>""),"- "&$C16,"") | G16: =IF($A16="Yes","- "&$D16,"")
A17: No | B17: Structure and usability | C17: Provide a scorecard tab and a definitions tab with meaningful headers. | D17: Open both tabs and identify the measure without outside explanation. | F17: =IF(AND($A17="Yes",$C17<>""),"- "&$C17,"") | G17: =IF($A17="Yes","- "&$D17,"")
A18: No | B18: Verification and limitations | C18: Reconcile counts and sums; distinguish association from a causal explanation. | D18: Compare totals and challenge unsupported explanations. | F18: =IF(AND($A18="Yes",$C18<>""),"- "&$C18,"") | G18: =IF($A18="Yes","- "&$D18,"")
A19: No | B19: Delivery and portability | C19: Deliver an editable Excel workbook (.xlsx) with no broken external references. | D19: Open the file in the intended spreadsheet application. | F19: =IF(AND($A19="Yes",$C19<>""),"- "&$C19,"") | G19: =IF($A19="Yes","- "&$D19,"")
B20: Free-form additions (optional):
B21: ASSEMBLED PROMPT → | E21: =_xlfn.TEXTJOIN(CHAR(10)&CHAR(10),TRUE(),C5,IF(_xlfn.TEXTJOIN(CHAR(10),TRUE(),F7:F19)="","","Requirements:"&CHAR(10)&_xlfn.TEXTJOIN(CHAR(10),TRUE(),F7:F19)),IF(C20="","","Also:"&CHAR(10)&C20),IF(_xlfn.TEXTJOIN(CHAR(10),TRUE(),G7:G19)="","","How I will check the result:"&CHAR(10)&_xlfn.TEXTJOIN(CHAR(10),TRUE(),G7:G19))) -> Help [reader] decide [decision] using [file / sheet], period [range], detail rows only.
A23: BUILD AN INTERACTIVE DASHBOARD
B24: The course prompt (copy-ready): | C24: From the attached data file, build ONE self-contained HTML file that works offline from disk. Views: summary tiles, one chart, and a sortable table of the records — data embedded, every number computed from the embedded records, metric definitions and the snapshot date in the footer. Controls, wired so one selection re-scopes every view: a month-range selector with inclusive endpoints · category multi-select filters · a comparison switch · a monthly/quarterly granularity switch · a metric selector · drill-down from a chart segment to its underlying records · ranking on the selected measure · Reset. Show active selections; an empty selection says "no matching records"; missing values stay blank; a zero denominator shows "—". Label the file a static data snapshot with its date.
B25: Your task line (edit): | C25: A self-contained offline dashboard for [audience] to explore [data] and answer [question].
A26: Include? | B26: Requirement type | C26: Your instruction (edit) | D26: How to check it
A27: No | B27: Input contract | C27: Embed the checked supplier detail data and identify the snapshot date. | D27: Compare record count and source identifiers. | F27: =IF(AND($A27="Yes",$C27<>""),"- "&$C27,"") | G27: =IF($A27="Yes","- "&$D27,"")
A28: No | B28: Date range | C28: Use month selectors matching the source granularity; include both endpoints. | D28: Test a single month and the full range. | F28: =IF(AND($A28="Yes",$C28<>""),"- "&$C28,"") | G28: =IF($A28="Yes","- "&$D28,"")
A29: No | B29: Category controls | C29: Offer Supplier and Site multi-select controls; Type or Class requires a real source field. | D29: Compare each option with actual distinct values. | F29: =IF(AND($A29="Yes",$C29<>""),"- "&$C29,"") | G29: =IF($A29="Yes","- "&$D29,"")
A30: No | B30: Grouping and granularity | C30: Allow grouping by supplier, site, or month when relevant to the decision. | D30: Check counts and totals after changing the grouping. | F30: =IF(AND($A30="Yes",$C30<>""),"- "&$C30,"") | G30: =IF($A30="Yes","- "&$D30,"")
A31: No | B31: Metric selection | C31: Offer named measures with definitions and units. | D31: Verify that labels, scales, and calculations all change together. | F31: =IF(AND($A31="Yes",$C31<>""),"- "&$C31,"") | G31: =IF($A31="Yes","- "&$D31,"")
A32: No | B32: Filter combination | C32: Apply selected filters consistently, with an explicit AND/OR rule. | D32: Use a known intersection and compare included records. | F32: =IF(AND($A32="Yes",$C32<>""),"- "&$C32,"") | G32: =IF($A32="Yes","- "&$D32,"")
A33: No | B33: Coordinated views | C33: Charts, totals, and tables must represent the same selected records. | D33: Reconcile a chart total with its underlying table. | F33: =IF(AND($A33="Yes",$C33<>""),"- "&$C33,"") | G33: =IF($A33="Yes","- "&$D33,"")
A34: No | B34: Sorting and drill-down | C34: Sort numerically and allow inspection of supporting rows. | D34: Compare sorted order and inspect a selected group. | F34: =IF(AND($A34="Yes",$C34<>""),"- "&$C34,"") | G34: =IF($A34="Yes","- "&$D34,"")
A35: No | B35: Empty, missing, and zero states | C35: Distinguish no matching records from a valid zero; avoid division by zero. | D35: Exercise all three cases. | F35: =IF(AND($A35="Yes",$C35<>""),"- "&$C35,"") | G35: =IF($A35="Yes","- "&$D35,"")
A36: No | B36: Reset and visible state | C36: Show active selections and restore the default state with Reset. | D36: Change multiple controls, reset, and compare the initial view. | F36: =IF(AND($A36="Yes",$C36<>""),"- "&$C36,"") | G36: =IF($A36="Yes","- "&$D36,"")
A37: No | B37: Accessibility and layout | C37: Use labeled controls, visible focus, readable contrast, and a usable narrow layout. | D37: Navigate by keyboard and test a smaller window. | F37: =IF(AND($A37="Yes",$C37<>""),"- "&$C37,"") | G37: =IF($A37="Yes","- "&$D37,"")
A38: No | B38: Portability and dependencies | C38: Deliver one self-contained HyperText Markup Language (.html) file with embedded data and no required network calls. | D38: Open offline and inspect for missing assets. | F38: =IF(AND($A38="Yes",$C38<>""),"- "&$C38,"") | G38: =IF($A38="Yes","- "&$D38,"")
... A40: No | B40: Export and reconciliation | C40: If export is needed, export the filtered data and retain the chosen scope. | D40: Compare exported rows with the displayed selection. | F40: =IF(AND($A40="Yes",$C40<>""),"- "&$C40,"") | G40: =IF($A40="Yes","- "&$D40,"")
B41: Free-form additions (optional):
B42: ASSEMBLED PROMPT → | E42: =_xlfn.TEXTJOIN(CHAR(10)&CHAR(10),TRUE(),C25,IF(_xlfn.TEXTJOIN(CHAR(10),TRUE(),F27:F40)="","","Requirements:"&CHAR(10)&_xlfn.TEXTJOIN(CHAR(10),TRUE(),F27:F40)),IF(C41="","","Also:"&CHAR(10)&C41),IF(_xlfn.TEXTJOIN(CHAR(10),TRUE(),G27:G40)="","","How I will check the result:"&CHAR(10)&_xlfn.TEXTJOIN(CHAR(10),TRUE(),G27:G40))) -> A self-contained offline dashboard for [audience] to explore [data] and answer [question].
A44: PREPARE A PRESENTATION
B45: The course prompt (copy-ready): | C45: Create an editable five-slide management presentation using only the verified analysis. The audience must decide what follow-up is warranted. Cover: the business question and scope · the comparison · one useful time or segment view · a proposed follow-up · limitations with next steps. Give each slide one main message, readable evidence, accurate units and reporting period, and brief speaker notes. Preserve uncertainty and missing-data limits. Do not invent causes or unsupported benefits. Check every number against the analysis and inspect the exported slides for clipping and readability.
B46: Your task line (edit): | C46: A [n]-slide deck for [audience] to decide [decision], using only [verified source].
A47: Include? | B47: Requirement type | C47: Your instruction (edit) | D47: How to check it
A48: No | B48: Purpose and audience | C48: Name the decision, audience knowledge, and intended action. | D48: A reviewer can identify the decision and next step. | F48: =IF(AND($A48="Yes",$C48<>""),"- "&$C48,"") | G48: =IF($A48="Yes","- "&$D48,"")
A49: No | B49: Scope and slide count | C49: For the mock presentation, request five slides with a defined coverage list. | D49: Count slides and map each required topic. | F49: =IF(AND($A49="Yes",$C49<>""),"- "&$C49,"") | G49: =IF($A49="Yes","- "&$D49,"")
A50: No | B50: Story structure | C50: Move from business question to evidence, implications, and next action. | D50: Read only the titles and check the narrative. | F50: =IF(AND($A50="Yes",$C50<>""),"- "&$C50,"") | G50: =IF($A50="Yes","- "&$D50,"")
A51: No | B51: Message hierarchy | C51: Use one main message per slide; make evidence support that message. | D51: Ask a reader what to remember first. | F51: =IF(AND($A51="Yes",$C51<>""),"- "&$C51,"") | G51: =IF($A51="Yes","- "&$D51,"")
A52: No | B52: Data fidelity | C52: Use only checked findings and preserve period, units, and limitations. | D52: Reconcile displayed values with the workbook. | F52: =IF(AND($A52="Yes",$C52<>""),"- "&$C52,"") | G52: =IF($A52="Yes","- "&$D52,"")
A53: No | B53: Chart semantics | C53: Choose an appropriate chart, truthful axes, and clearly labeled categories. | D53: Check that the encoding supports the claimed comparison. | F53: =IF(AND($A53="Yes",$C53<>""),"- "&$C53,"") | G53: =IF($A53="Yes","- "&$D53,"")
A54: No | B54: Typography and readability | C54: Set readable projected text and avoid dense paragraphs on teaching slides. | D54: Inspect at presentation size and the expected viewing distance. | F54: =IF(AND($A54="Yes",$C54<>""),"- "&$C54,"") | G54: =IF($A54="Yes","- "&$D54,"")
A55: No | B55: Visual consistency | C55: Use a restrained palette, aligned margins, and consistent emphasis. | D55: Compare consecutive slides as a set. | F55: =IF(AND($A55="Yes",$C55<>""),"- "&$C55,"") | G55: =IF($A55="Yes","- "&$D55,"")
A56: No | B56: Speaker notes | C56: Provide purpose, talking points, transitions, and exercise instructions. | D56: Inspect notes on every relevant slide. | F56: =IF(AND($A56="Yes",$C56<>""),"- "&$C56,"") | G56: =IF($A56="Yes","- "&$D56,"")
A57: No | B57: Timing and mode | C57: Classify TEACH, DO, REFERENCE, and DIVIDER; protect 30 practice minutes. | D57: Sum notes and rehearse the live path. | F57: =IF(AND($A57="Yes",$C57<>""),"- "&$C57,"") | G57: =IF($A57="Yes","- "&$D57,"")
A58: No | B58: Reference completeness | C58: Make self-study slides understandable without the facilitator. | D58: Have a reader explain the example from the slide and notes. | F58: =IF(AND($A58="Yes",$C58<>""),"- "&$C58,"") | G58: =IF($A58="Yes","- "&$D58,"")
A59: No | B59: Accessibility | C59: Use readable contrast and descriptive alternatives for meaningful visuals. | D59: Review with the target presentation application’s accessibility tools. | F59: =IF(AND($A59="Yes",$C59<>""),"- "&$C59,"") | G59: =IF($A59="Yes","- "&$D59,"")
A60: No | B60: Delivery and editability | C60: Deliver an editable PowerPoint (.pptx), retaining notes and usable charts. | D60: Open, edit, and present the exported file. | F60: =IF(AND($A60="Yes",$C60<>""),"- "&$C60,"") | G60: =IF($A60="Yes","- "&$D60,"")
B61: Free-form additions (optional):
B62: ASSEMBLED PROMPT → | E62: =_xlfn.TEXTJOIN(CHAR(10)&CHAR(10),TRUE(),C46,IF(_xlfn.TEXTJOIN(CHAR(10),TRUE(),F48:F60)="","","Requirements:"&CHAR(10)&_xlfn.TEXTJOIN(CHAR(10),TRUE(),F48:F60)),IF(C61="","","Also:"&CHAR(10)&C61),IF(_xlfn.TEXTJOIN(CHAR(10),TRUE(),G48:G60)="","","How I will check the result:"&CHAR(10)&_xlfn.TEXTJOIN(CHAR(10),TRUE(),G48:G60))) -> A [n]-slide deck for [audience] to decide [decision], using only [verified source].
A64: SUMMARIZE AN EMAIL CONVERSATION
B65: The course prompt (copy-ready): | C65: Review the selected conversation about [topic] using only the messages and attachments you can access. Create a brief of the current situation, followed by tables of decisions and actions. For each decision: status, conditions, supporting message. For each action: task, explicitly stated owner, due date, status, supporting message. Distinguish current dates from superseded dates. List unanswered questions, conflicts, missing information, and referenced attachments you cannot access. Preserve approval conditions. Write "Not stated" for missing details. Separate source facts from your interpretation. End with the next clarification needed. If requested, draft a reply for review; do not send it.
B66: Your task line (edit): | C66: Brief the conversation about [topic] so [reader] knows the current state and what they owe.
A67: Include? | B67: Requirement type | C67: Your instruction (edit) | D67: How to check it
A68: No | B68: Source scope | C68: Name the selected thread, relevant date range, and available attachments. | D68: List the messages and attachments actually used. | F68: =IF(AND($A68="Yes",$C68<>""),"- "&$C68,"") | G68: =IF($A68="Yes","- "&$D68,"")
A69: No | B69: Current state | C69: Separate the latest position from earlier proposals. | D69: Trace each changed date to the message that superseded it. | F69: =IF(AND($A69="Yes",$C69<>""),"- "&$C69,"") | G69: =IF($A69="Yes","- "&$D69,"")
A70: No | B70: Decision extraction | C70: Distinguish approved, proposed, rejected, and unresolved items. | D70: Compare decision status with the source wording. | F70: =IF(AND($A70="Yes",$C70<>""),"- "&$C70,"") | G70: =IF($A70="Yes","- "&$D70,"")
A71: No | B71: Conditional approval | C71: Keep the cost cap and quality sign-off attached to the approval. | D71: Reject a summary that says simply approved. | F71: =IF(AND($A71="Yes",$C71<>""),"- "&$C71,"") | G71: =IF($A71="Yes","- "&$D71,"")
A72: No | B72: Actions and ownership | C72: Extract action, explicit owner, due date, and status. | D72: Check each field; use Not stated for missing details. | F72: =IF(AND($A72="Yes",$C72<>""),"- "&$C72,"") | G72: =IF($A72="Yes","- "&$D72,"")
A73: No | B73: Date meaning | C73: Distinguish a trial date, change date, and action due date. | D73: Check that September 25 and October 2 are not conflated. | F73: =IF(AND($A73="Yes",$C73<>""),"- "&$C73,"") | G73: =IF($A73="Yes","- "&$D73,"")
A74: No | B74: Open questions and conflicts | C74: List unresolved freight responsibility and contradictory statements. | D74: Locate the source question and any subsequent resolution. | F74: =IF(AND($A74="Yes",$C74<>""),"- "&$C74,"") | G74: =IF($A74="Yes","- "&$D74,"")
A75: No | B75: Evidence traceability | C75: Use message dates, senders, and supporting excerpts or available links. | D75: Open the referenced message and verify the claim. | F75: =IF(AND($A75="Yes",$C75<>""),"- "&$C75,"") | G75: =IF($A75="Yes","- "&$D75,"")
A76: No | B76: Attachments and missing input | C76: Flag a mentioned drawing that is not available to the assistant. | D76: Do not summarize content of an unavailable attachment. | F76: =IF(AND($A76="Yes",$C76<>""),"- "&$C76,"") | G76: =IF($A76="Yes","- "&$D76,"")
A77: No | B77: Format and tone | C77: Provide a neutral current-state brief and a separate action table. | D77: Check that opinions are labeled and actions are easy to scan. | F77: =IF(AND($A77="Yes",$C77<>""),"- "&$C77,"") | G77: =IF($A77="Yes","- "&$D77,"")
A78: No | B78: Access and tool availability | C78: Use only mail and attachments available in the actual Copilot and Outlook setup. | D78: Confirm retrieval scope; use the supplied-text exercise when needed. | F78: =IF(AND($A78="Yes",$C78<>""),"- "&$C78,"") | G78: =IF($A78="Yes","- "&$D78,"")
A79: No | B79: Authority and delivery | C79: Prepare any reply as a draft for human review; do not send automatically. | D79: Inspect the draft and action record. | F79: =IF(AND($A79="Yes",$C79<>""),"- "&$C79,"") | G79: =IF($A79="Yes","- "&$D79,"")
B80: Free-form additions (optional):
B81: ASSEMBLED PROMPT → | E81: =_xlfn.TEXTJOIN(CHAR(10)&CHAR(10),TRUE(),C66,IF(_xlfn.TEXTJOIN(CHAR(10),TRUE(),F68:F79)="","","Requirements:"&CHAR(10)&_xlfn.TEXTJOIN(CHAR(10),TRUE(),F68:F79)),IF(C80="","","Also:"&CHAR(10)&C80),IF(_xlfn.TEXTJOIN(CHAR(10),TRUE(),G68:G79)="","","How I will check the result:"&CHAR(10)&_xlfn.TEXTJOIN(CHAR(10),TRUE(),G68:G79))) -> Brief the conversation about [topic] so [reader] knows the current state and what they owe.
A83: EXPLAIN A TOPIC CLEARLY
B84: The course prompt (copy-ready): | C84: Using [source], explain [topic] so a reader at a fifth-grade reading level can understand it. State the main idea first. Use familiar words, short sentences, meaningful headings, and one concrete example. Define necessary technical terms when first used. Use an analogy only if it is accurate, and explain where it stops being useful. Preserve important conditions and uncertainty. Do not invent facts or use a childish tone. End with three comprehension questions and a short answer key. Check the explanation against the source and identify any simplification that changes the meaning.
B85: Your task line (edit): | C85: Explain [topic] from [source] for a reader at [reading level] who needs to [do / understand].
A86: Include? | B86: Requirement type | C86: Your instruction (edit) | D86: How to check it
A87: No | B87: Reader and purpose | C87: Write for a reader at a fifth-grade reading level who needs to understand or do a named task. | D87: A representative reader can state the purpose. | F87: =IF(AND($A87="Yes",$C87<>""),"- "&$C87,"") | G87: =IF($A87="Yes","- "&$D87,"")
A88: No | B88: Source and factual scope | C88: Use the supplied source and identify unsupported or missing information. | D88: Trace factual claims to the source. | F88: =IF(AND($A88="Yes",$C88<>""),"- "&$C88,"") | G88: =IF($A88="Yes","- "&$D88,"")
A89: No | B89: Concept coverage | C89: List the ideas the reader must understand before drafting. | D89: Compare the document with the coverage list. | F89: =IF(AND($A89="Yes",$C89<>""),"- "&$C89,"") | G89: =IF($A89="Yes","- "&$D89,"")
A90: No | B90: Vocabulary | C90: Prefer familiar words and define necessary technical terms at first use. | D90: Review unfamiliar terms and their definitions. | F90: =IF(AND($A90="Yes",$C90<>""),"- "&$C90,"") | G90: =IF($A90="Yes","- "&$D90,"")
A91: No | B91: Sentence and paragraph structure | C91: Use short direct sentences and one main idea per paragraph. | D91: Read aloud and inspect complex sentences. | F91: =IF(AND($A91="Yes",$C91<>""),"- "&$C91,"") | G91: =IF($A91="Yes","- "&$D91,"")
A92: No | B92: Organization | C92: Use meaningful headings and ordered steps when order matters. | D92: Ask a reader to locate the first action and a key explanation. | F92: =IF(AND($A92="Yes",$C92<>""),"- "&$C92,"") | G92: =IF($A92="Yes","- "&$D92,"")
A93: No | B93: Examples and analogies | C93: Include a concrete everyday example and state the limit of any analogy. | D93: Check that the analogy does not change the underlying idea. | F93: =IF(AND($A93="Yes",$C93<>""),"- "&$C93,"") | G93: =IF($A93="Yes","- "&$D93,"")
A94: No | B94: Tone and respect | C94: Use a clear adult tone without condescension or childish phrasing. | D94: Review wording with the intended audience. | F94: =IF(AND($A94="Yes",$C94<>""),"- "&$C94,"") | G94: =IF($A94="Yes","- "&$D94,"")
A95: No | B95: Accuracy and caveats | C95: Preserve important conditions, uncertainty, exceptions, and warnings from the source. | D95: Compare the simplified version with the original meaning. | F95: =IF(AND($A95="Yes",$C95<>""),"- "&$C95,"") | G95: =IF($A95="Yes","- "&$D95,"")
A96: No | B96: Readability evidence | C96: Use reading-level estimates as one signal, plus human comprehension checks. | D96: Do not claim exact grade-level comprehension from a score alone. | F96: =IF(AND($A96="Yes",$C96<>""),"- "&$C96,"") | G96: =IF($A96="Yes","- "&$D96,"")
A97: No | B97: Visual support and accessibility | C97: Use a labeled diagram or example only when it improves understanding. | D97: Ask what the visual helps the reader explain. | F97: =IF(AND($A97="Yes",$C97<>""),"- "&$C97,"") | G97: =IF($A97="Yes","- "&$D97,"")
A98: No | B98: Comprehension check | C98: Provide three questions and a short answer key grounded in the document. | D98: Confirm the answers can be found or inferred from the text. | F98: =IF(AND($A98="Yes",$C98<>""),"- "&$C98,"") | G98: =IF($A98="Yes","- "&$D98,"")
A99: No | B99: Delivery and reuse | C99: Specify an editable document, useful headings, and reusable topic placeholders. | D99: Open the output and adapt one topic without losing the structure. | F99: =IF(AND($A99="Yes",$C99<>""),"- "&$C99,"") | G99: =IF($A99="Yes","- "&$D99,"")
B100: Free-form additions (optional):
B101: ASSEMBLED PROMPT → | E101: =_xlfn.TEXTJOIN(CHAR(10)&CHAR(10),TRUE(),C85,IF(_xlfn.TEXTJOIN(CHAR(10),TRUE(),F87:F99)="","","Requirements:"&CHAR(10)&_xlfn.TEXTJOIN(CHAR(10),TRUE(),F87:F99)),IF(C100="","","Also:"&CHAR(10)&C100),IF(_xlfn.TEXTJOIN(CHAR(10),TRUE(),G87:G99)="","","How I will check the result:"&CHAR(10)&_xlfn.TEXTJOIN(CHAR(10),TRUE(),G87:G99))) -> Explain [topic] from [source] for a reader at [reading level] who needs to [do / understand].

Sheet Options
A1: Mode | B1: Element | C1: Attribute | D1: Option | E1: Pick when | F1: Emits into the prompt | G1: Tier
A2: generative | B2: Role | C2: Identity / posture | D2: Careful analyst | E2: numbers, data, trends | F2: You are a careful analyst. | G2: core
A3: generative | B3: Role | C3: Identity / posture | D3: Precise editor | E3: improving text you supply | F3: You are a precise editor. | G3: core
A4: generative | B4: Role | C4: Identity / posture | D4: Demanding reviewer | E4: grading, evaluating, comparing | F4: You are a demanding but fair reviewer. | G4: core
A5: generative | B5: Role | C5: Identity / posture | D5: Executive presentation writer | E5: decks, summaries for leadership | F5: You are a presentation writer for executives. | G5: core
A6: generative | B6: Role | C6: Identity / posture | D6: Patient explainer | E6: teaching, onboarding material | F6: You are a patient explainer who never condescends. | G6: core
A7: generative | B7: Role | C7: Identity / posture | D7: Devil's advocate | E7: stress-testing a plan or decision | F7: You are a devil's advocate. | G7: core
A8: generative | B8: Role | C8: Identity / posture | D8: Meticulous document processor | E8: extraction, comparison, forms | F8: You are a meticulous document processor. | G8: core
A9: generative | B9: Role | C9: Identity / posture | D9: Cited researcher | E9: web/document research | F9: You are a researcher who cites every claim. | G9: core
A10: generative | B10: Role | C10: Identity / posture | D10: Business writer | E10: emails, memos, announcements | F10: You are an experienced business writer. | G10: extended
A11: generative | B11: Role | C11: Identity / posture | D11: Technical writer | E11: procedures, specs, documentation | F11: You are a technical writer who values precision over polish. | G11: extended
A12: generative | B12: Role | C12: Identity / posture | D12: Facilitator | E12: synthesizing group input, agendas | F12: You are a neutral facilitator. | G12: extended
... A288: agentic | B288: Reporting | C288: Report discipline | D288: Evidence required | E288: always | F288: Claims of success carry evidence: the command run and its output, or the re-opened file. | G288: core

Sheet Builder_Gen
A1: Element | B1: Attribute | C1: Guidance | D1: Your choice (dropdown) | E1: Custom text (overrides/adds) | F1: Emitted text (auto)
A2: Role | B2: Who is answering: identity, expertise posture, and checkable behavioral commitments.
B3: Identity / posture | C3: Pick the professional posture. It sets vocabulary, caution level, and what gets foregrounded — not IQ. WHY IT MATTERS: Sets the register the answer is written in — vocabulary, caution level, what gets foregrounded. Expert personas measurably improve domain description tasks, but a 162-persona study found no accuracy gain on factual questions: identity buys voice and focus, not IQ. (Salewski et al. 2023; Zheng et al. 2024) | D3: Careful analyst | F3: =IF($E3<>"",$E3,IF($D3="","",IFERROR(INDEX(Options!$F$2:$F$20,MATCH($D3,Options!$D$2:$D$20,0)),""))) -> You are a careful analyst.
B4: Domain expertise | C4: Name the field so the right vocabulary and priorities surface. This foregrounds knowledge — it does not create it. WHY IT MATTERS: Naming the field surfaces its vocabulary, defaults, and priorities — the answer starts from the right corner of the model's training instead of the generic middle. It foregrounds knowledge the model already has; it cannot create knowledge it lacks. (Salewski et al. 2023; vendor role guidance) | F4: =$E4 -> 0
B5: Behavioral commitments · choice 1 | C5: The checkable rules — the part of Role that actually changes output. Pick from the three families below. WHY IT MATTERS: The part of Role that measurably changes output: a behavioral rule is checkable line-by-line in the result, where a title is a vibe. Grounding-style rules are the documented lever for drastically reducing invented content. (Anthropic reduce-hallucinations guidance) | F5: =$E5 -> 0
B6: Behavioral commitments · choice 2 | F6: =$E6 -> 0
B7: Accuracy behaviors · choice 1 | C7: For anything with facts and numbers. WHY IT MATTERS: Training rewards a confident guess over an honest blank, so guessing is the default; accuracy rules re-open the abstain option. Compute-via-code exists because model arithmetic degrades sharply as numbers grow. (OpenAI 2025, why LMs hallucinate; Faith & Fate, NeurIPS 2023) | D7: Never invent | F7: =IF($E7<>"",$E7,IF($D7="","",IFERROR(INDEX(Options!$F$21:$F$25,MATCH($D7,Options!$D$21:$D$25,0)),""))) -> You never invent facts or numbers — missing is missing.
B8: Accuracy behaviors · choice 2 | F8: =IF($E8<>"",$E8,IF($D8="","",IFERROR(INDEX(Options!$F$21:$F$25,MATCH($D8,Options!$D$21:$D$25,0)),"")))
B9: Accuracy behaviors · choice 3 | F9: =IF($E9<>"",$E9,IF($D9="","",IFERROR(INDEX(Options!$F$21:$F$25,MATCH($D9,Options!$D$21:$D$25,0)),"")))
B10: Transparency behaviors · choice 1 | C10: Make the work auditable. WHY IT MATTERS: Stated assumptions and shown work convert an answer you must trust into one you can audit — errors surface at review, not downstream. Self-checking works only against concrete criteria like these; a bare 'are you sure?' can make answers worse. (Anthropic self-check guidance; Huang et al. 2024) | F10: =IF($E10<>"",$E10,IF($D10="","",IFERROR(INDEX(Options!$F$26:$F$30,MATCH($D10,Options!$D$26:$D$30,0)),"")))
B11: Transparency behaviors · choice 2 | F11: =IF($E11<>"",$E11,IF($D11="","",IFERROR(INDEX(Options!$F$26:$F$30,MATCH($D11,Options!$D$26:$D$30,0)),"")))
B12: Transparency behaviors · choice 3 | F12: =IF($E12<>"",$E12,IF($D12="","",IFERROR(INDEX(Options!$F$26:$F$30,MATCH($D12,Options!$D$26:$D$30,0)),"")))
B13: Style behaviors · choice 1 | C13: How it writes, stated as rules. WHY IT MATTERS: Style stated as rules survives; style stated as adjectives drifts. 'One idea per sentence' is enforceable and checkable in the output — 'write clearly' is re-interpreted on every run. (vendor format guidance; prompt-sensitivity research) | F13: =IF($E13<>"",$E13,IF($D13="","",IFERROR(INDEX(Options!$F$31:$F$34,MATCH($D13,Options!$D$31:$D$34,0)),"")))
B14: Style behaviors · choice 2 | F14: =IF($E14<>"",$E14,IF($D14="","",IFERROR(INDEX(Options!$F$31:$F$34,MATCH($D14,Options!$D$31:$D$34,0)),"")))
B15: Style behaviors · choice 3 | F15: =IF($E15<>"",$E15,IF($D15="","",IFERROR(INDEX(Options!$F$31:$F$34,MATCH($D15,Options!$D$31:$D$34,0)),"")))
B16: Stance | C16: The critical posture. Blind the model to your preference — it mirrors any side you reveal. WHY IT MATTERS: Models affirm users ~49% more than humans do and mirror whichever side you reveal — a single flattering exchange measurably raises the user's conviction. Declaring a neutral or adversarial stance up front pre-empts the mirror before it engages. (Cheng et al., Science 2026; Sharma et al. 2023) | F16: =IF($E16<>"",$E16,IF($D16="","",IFERROR(INDEX(Options!$F$35:$F$39,MATCH($D16,Options!$D$35:$D$39,0)),"")))
A17: Task ★ | B17: The single clear ask: verb + object + audience + success criterion.
B18: Action starter | C18: Each verb is a mini-template — pick one and fill its {{slots}}, or write your own statement below. WHY IT MATTERS: The verb is the operation: it selects what transformation runs on your material and what 'done' looks like. Google's guidance calls the task verb 'the most important component of a prompt' — vague verbs produce exploration instead of answers. (Google Workspace prompting guide) | D18: Analyze | F18: =IF($E18<>"",$E18,IF($D18="","",IFERROR(INDEX(Options!$F$40:$F$55,MATCH($D18,Options!$D$40:$D$55,0)),""))) -> Answer: {{the question, with metric and period — e.g., "what is X by group for Q2 vs the target"}}?
B19: Task statement | C19: Or write the ask yourself — one task, one sentence if you can manage it. WHY IT MATTERS: One task in one sentence is the highest-leverage clarity move: current reasoning models pay a real cost for ambiguity — they burn thinking tokens trying to reconcile vague or conflicting instructions instead of answering. (OpenAI GPT-5 guide; Anthropic 'be clear and direct') | E19: Example (replace): what is the return rate by site for Q2 vs the 2.0% target? | F19: =$E19 -> Example (replace): what is the return rate by site for Q2 vs the 2.0% target?
B20: Audience | C20: Who receives this and what they already know. It sets altitude and vocabulary. WHY IT MATTERS: Audience re-ranks and re-words the same content: what leads, what gets cut, which terms need expansion. Without one, the model writes for nobody in particular — the mid-distribution reader who doesn't exist in your building. (vendor Persona/Context frameworks) | F20: =IF($E20<>"",$E20,IF($D20="","",IFERROR(INDEX(Options!$F$56:$F$61,MATCH($D20,Options!$D$56:$D$61,0)),"")))
B21: Reader's time budget | C21: How long they'll actually give it — the honest constraint. WHY IT MATTERS: The honest constraint that forces compression: a 30-second reader gets the number and the ask; a 10-minute reader gets the reasoning. Left uncapped, models default to thorough — which the reader experiences as long. (practitioner consensus; length is a vendor API dial for this reason) | F21: =IF($E21<>"",$E21,IF($D21="","",IFERROR(INDEX(Options!$F$62:$F$64,MATCH($D21,Options!$D$62:$D$64,0)),"")))
B22: Reading level | C22: The Canvas-style slider, as options. Plain-language guidance targets 6th–8th grade for general audiences. WHY IT MATTERS: Vocabulary altitude is a dial the model follows reliably — and its default sits well above general-audience reading. Plain-language practice targets 6th–8th grade for mixed audiences; say the level and it lands there. (plain-language standards; style-prompting research) | F22: =IF($E22<>"",$E22,IF($D22="","",IFERROR(INDEX(Options!$F$65:$F$69,MATCH($D22,Options!$D$65:$D$69,0)),"")))
B23: Success criterion | C23: The task's own completion test — what must be true of the output. WHY IT MATTERS: A stated completion test gives the model a target to optimize toward and gives you a check to run afterward — the same mechanism that makes self-verification work: concrete criteria catch errors reliably; vague quality asks don't. (Anthropic self-check guidance) | F23: =IF($E23<>"",$E23,IF($D23="","",IFERROR(INDEX(Options!$F$70:$F$73,MATCH($D23,Options!$D$70:$D$73,0)),"")))
B24: Purpose — why it matters | C24: The decision or event this feeds. Models generalize from reasons — and it filters what matters. WHY IT MATTERS: Models generalize from reasons: 'no ellipses — this will be read aloud by text-to-speech' outperforms the bare rule, because the model extends the spirit to cases you didn't list. Purpose also filters relevance — it now knows what matters to the decision. (Anthropic explain-why guidance) | F24: =$E24 -> 0
B25: Sense check | C25: Have the model confirm understanding before doing the work — cheapest error catch there is. WHY IT MATTERS: A restate-before-work step catches a misread task at the cheapest possible point — before any output exists. It is the generative version of the agentic Phase-0 intake gate: pennies to fix here, a full redo after a polished wrong answer. (plan-approval gate pattern) | F25: =IF($E25<>"",$E25,IF($D25="","",IFERROR(INDEX(Options!$F$74:$F$76,MATCH($D25,Options!$D$74:$D$76,0)),"")))
A26: Context | B26: Everything true in your world that isn't in the training data — material, definitions, quirks, constraints, and the reasons behind rules.
B27: Raw material | C27: The stuff to work from. Long documents go FIRST in the final prompt, instructions after — and delimit so material is never mistaken for instructions. WHY IT MATTERS: Placement measurably matters: long documents at the TOP with the question at the END improved answers by up to ~30% in vendor testing, and accuracy sags for content buried in the middle of a long context. (Anthropic long-context guidance; Liu et al. 2023, lost in the middle) | F27: =IF($E27<>"",$E27,IF($D27="","",IFERROR(INDEX(Options!$F$77:$F$79,MATCH($D27,Options!$D$77:$D$79,0)),"")))
B28: Glossary — controlled vocabulary · choice 1 | C28: Terms with local meaning. For metrics: numerator, denominator, grain, inclusions/exclusions — or the model will compute its own version. WHY IT MATTERS: The model resolves every undefined term to its most common global meaning — not your local one. A metric card (numerator, denominator, grain, exclusions) replaces the single biggest source of wrong analytical answers: a guessed denominator. (hallucination mechanics; data-analysis field practice) | F28: =IF($E28<>"",$E28,IF($D28="","",IFERROR(INDEX(Options!$F$80:$F$80,MATCH($D28,Options!$D$80:$D$80,0)),"")))
B29: Glossary — controlled vocabulary · choice 2 | F29: =IF($E29<>"",$E29,IF($D29="","",IFERROR(INDEX(Options!$F$80:$F$80,MATCH($D29,Options!$D$80:$D$80,0)),"")))
B30: Known quirks → rules · choice 1 | C30: Every quirk you don't write down becomes a silent 'fix' the model invents. Pair each with its rule. WHY IT MATTERS: Every quirk you don't write down becomes a silent 'fix' the model invents — plausibility fills the gap, fluently. A quirk paired with its rule converts a hidden landmine into a followed instruction. (OpenAI 2025, why LMs hallucinate) | F30: =IF($E30<>"",$E30,IF($D30="","",IFERROR(INDEX(Options!$F$81:$F$87,MATCH($D30,Options!$D$81:$D$87,0)),"")))
B31: Known quirks → rules · choice 2 | F31: =IF($E31<>"",$E31,IF($D31="","",IFERROR(INDEX(Options!$F$81:$F$87,MATCH($D31,Options!$D$81:$D$87,0)),"")))
B32: Known quirks → rules · choice 3 | F32: =IF($E32<>"",$E32,IF($D32="","",IFERROR(INDEX(Options!$F$81:$F$87,MATCH($D32,Options!$D$81:$D$87,0)),"")))
B33: Constraints & sensitivities · choice 1 | C33: What must not happen — stated positively where possible, with the reason where it isn't obvious. WHY IT MATTERS: Positively-phrased constraints are followed more reliably than prohibitions — earlier models showed inverse scaling on negated instructions, and current vendor guidance remains 'tell it what TO do.' When you must forbid, attach the reason. (Anthropic guidance; Jang et al. 2022) | F33: =IF($E33<>"",$E33,IF($D33="","",IFERROR(INDEX(Options!$F$88:$F$92,MATCH($D33,Options!$D$88:$D$92,0)),"")))
B34: Constraints & sensitivities · choice 2 | F34: =IF($E34<>"",$E34,IF($D34="","",IFERROR(INDEX(Options!$F$88:$F$92,MATCH($D34,Options!$D$88:$D$92,0)),"")))
B35: Constraints & sensitivities · choice 3 | F35: =IF($E35<>"",$E35,IF($D35="","",IFERROR(INDEX(Options!$F$88:$F$92,MATCH($D35,Options!$D$88:$D$92,0)),"")))
B36: The why behind the rules | C36: Explain any non-obvious rule — "this will be read aloud, so no ellipses" outperforms "no ellipses." Models generalize from reasons. WHY IT MATTERS: The reason behind a rule is itself an instruction: models apply explained rules in spirit, not just letter, extending them to cases you didn't enumerate — the vendor docs state this generalization effect verbatim. (Anthropic best practices) | F36: =$E36 -> 0
A37: Format | B37: The output contract: shape, length, tone, and what must be in or out.
B38: Output type | C38: The deliverable's shape. Name the columns for tables, the sections for documents. WHY IT MATTERS: Naming the deliverable's shape — a table with these columns, a memo with these sections — removes the largest degree of freedom the model would otherwise spend guessing, and makes output land ready to use instead of ready to reformat. (all four vendor frameworks: Format / Expectations) | F38: =IF($E38<>"",$E38,IF($D38="","",IFERROR(INDEX(Options!$F$93:$F$107,MATCH($D38,Options!$D$93:$D$107,0)),"")))
B39: Structure rules · choice 1 | C39: The internal skeleton — where the answer sits, what every section carries. WHY IT MATTERS: Trivial format differences swing measured accuracy by up to 76 points across phrasings — structure is not cosmetic. A fixed, tested skeleton removes that variance and puts the answer where the reader looks first. (Sclar et al., ICLR 2024) | F39: =IF($E39<>"",$E39,IF($D39="","",IFERROR(INDEX(Options!$F$108:$F$113,MATCH($D39,Options!$D$108:$D$113,0)),"")))
B40: Structure rules · choice 2 | F40: =IF($E40<>"",$E40,IF($D40="","",IFERROR(INDEX(Options!$F$108:$F$113,MATCH($D40,Options!$D$108:$D$113,0)),"")))
B41: Structure rules · choice 3 | F41: =IF($E41<>"",$E41,IF($D41="","",IFERROR(INDEX(Options!$F$108:$F$113,MATCH($D41,Options!$D$108:$D$113,0)),"")))
B42: Length cap | C42: Numeric, with a priority rule. Adjectives ("brief") are unenforceable; uncapped AI runs 2–3× long. WHY IT MATTERS: A numeric cap is enforceable; 'brief' is a mood. Uncapped, models run two to three times longer than the reader needs — length is so real a dial that vendors expose it as an API parameter. The famous $200-tip stunt produced ~11% longer answers, not better ones. (OpenAI verbosity; tip-experiment analyses) | F42: =IF($E42<>"",$E42,IF($D42="","",IFERROR(INDEX(Options!$F$114:$F$123,MATCH($D42,Options!$D$114:$D$123,0)),"")))
B43: Tone · choice 1 | C43: Compose from the three dials below — one pick per dial reads best. WHY IT MATTERS: Tone is where role prompting genuinely pays: models imitate a specified register reliably, and register changes how the human reader receives the work. Compose it from dials rather than adjectives — one pick per dial reads best. (vendor role-for-tone position; style-prompting research) | F43: =$E43 -> 0
B44: Tone · choice 2 | F44: =$E44 -> 0
B45: Formality | C45: WHY IT MATTERS: Formality sets the social distance of the prose — hallway versus boardroom. Models default to mid-formal; one explicit pick lands it where you need it. (style-prompting research) | F45: =IF($E45<>"",$E45,IF($D45="","",IFERROR(INDEX(Options!$F$124:$F$129,MATCH($D45,Options!$D$124:$D$129,0)),"")))
B46: Directness | C46: WHY IT MATTERS: Directness decides whether the ask or the courtesy leads. Models hedge by default — caution is trained in — so 'lead with the ask' has to be said to happen. (practitioner consensus; headline-first practice) | F46: =IF($E46<>"",$E46,IF($D46="","",IFERROR(INDEX(Options!$F$130:$F$134,MATCH($D46,Options!$D$130:$D$134,0)),"")))
B47: Warmth | C47: WHY IT MATTERS: Warmth calibrates the relationship signals in the text. Unmanaged, it drifts toward affirmation — the same preference-training pressure behind sycophancy — so the dial keeps warmth a choice rather than a bias. (Sharma et al. 2023, sycophancy origins) | F47: =IF($E47<>"",$E47,IF($D47="","",IFERROR(INDEX(Options!$F$135:$F$139,MATCH($D47,Options!$D$135:$D$139,0)),"")))
B48: Language level | C48: Vocabulary altitude and jargon policy. WHY IT MATTERS: Jargon policy decides who can act on the output without a translator. Models also mirror the prompt's own vocabulary — write at the altitude you want back. (Anthropic: match your prompt's style to the desired output) | F48: =IF($E48<>"",$E48,IF($D48="","",IFERROR(INDEX(Options!$F$140:$F$143,MATCH($D48,Options!$D$140:$D$143,0)),"")))
B49: Must include / must not · choice 1 | C49: The inclusion contract. WHY IT MATTERS: An explicit include/exclude list turns review into a checklist — presence and absence verified in seconds instead of re-reading for feel. It is the format-level version of checkable behavioral rules. (self-check-against-criteria guidance) | F49: =IF($E49<>"",$E49,IF($D49="","",IFERROR(INDEX(Options!$F$144:$F$149,MATCH($D49,Options!$D$144:$D$149,0)),"")))
B50: Must include / must not · choice 2 | F50: =IF($E50<>"",$E50,IF($D50="","",IFERROR(INDEX(Options!$F$144:$F$149,MATCH($D50,Options!$D$144:$D$149,0)),"")))
B51: Must include / must not · choice 3 | F51: =IF($E51<>"",$E51,IF($D51="","",IFERROR(INDEX(Options!$F$144:$F$149,MATCH($D51,Options!$D$144:$D$149,0)),"")))
B52: Variations | C52: Ask for alternatives to choose from — divergence as a dial. You become the selector, not the author. WHY IT MATTERS: Asking for N alternatives converts sampling variance from a bug into a menu — the insight behind self-consistency, where several sampled answers beat any single one. You become the selector, which is where your judgment belongs. (Wang et al. 2023, self-consistency) | F52: =IF($E52<>"",$E52,IF($D52="","",IFERROR(INDEX(Options!$F$150:$F$153,MATCH($D52,Options!$D$150:$D$153,0)),"")))
A53: Examples | B53: 3–5 realistic demonstrations of the task done right — the strongest steering signal there is.
B54: How many | C54: Zero-shot first on thinking models; add examples when format drifts. More helps most on formatting/labeling tasks. WHY IT MATTERS: Few-shot examples were the original prompt-engineering discovery: task performance from demonstrations alone, no retraining. 3–5 diverse examples steer format and tone most reliably — but start zero-shot on thinking models; few-shot measurably degrades some of them. (Brown et al. 2020; Anthropic guidance; DeepSeek-R1 paper) | F54: =IF($E54<>"",$E54,IF($D54="","",IFERROR(INDEX(Options!$F$154:$F$156,MATCH($D54,Options!$D$154:$D$156,0)),"")))
B55: Coverage · choice 1 | C55: Which cases your examples span — the model's boundary behavior copies theirs. WHY IT MATTERS: The model copies your examples' boundary behavior, not just their shape: exemplar choice and order alone can swing accuracy from near-chance to over 90%. All-happy-path examples teach it to treat every case as happy — one typical + one edge + one reject teaches the standard. (Lu et al. 2021; Prompt Report design decisions) | F55: =IF($E55<>"",$E55,IF($D55="","",IFERROR(INDEX(Options!$F$157:$F$159,MATCH($D55,Options!$D$157:$D$159,0)),"")))
B56: Coverage · choice 2 | F56: =IF($E56<>"",$E56,IF($D56="","",IFERROR(INDEX(Options!$F$157:$F$159,MATCH($D56,Options!$D$157:$D$159,0)),"")))
B57: Packaging | C57: Fence examples so they can't be mistaken for live input. WHY IT MATTERS: Fencing examples in tags keeps them from being read as live input or instructions — unambiguous parsing is the documented reason vendors recommend tag structure, and unfenced examples are the classic source of example text leaking into output. (Anthropic XML-tags guidance) | F57: =IF($E57<>"",$E57,IF($D57="","",IFERROR(INDEX(Options!$F$160:$F$161,MATCH($D57,Options!$D$160:$D$161,0)),"")))
B58: The examples | C58: Paste them. Real (redacted) beats invented; lightly-genericized real beats both. WHY IT MATTERS: Models imitate surface detail as much as structure — a real (redacted) example carries your house style's actual distribution; an invented one carries what the model guesses your style is. Exemplar quality and similarity are measured few-shot design decisions. (Prompt Report §2.2) | F58: =$E58 -> 0
A59: The Out | B59: The escape route for missing information: name the condition, the honest move, and how gaps surface — so the model never has to choose between obeying you and being honest.
B60: When it applies · choice 1 | C60: The situations where not-knowing must surface instead of being papered over. WHY IT MATTERS: Standard training rewards a confident guess over 'I don't know' — benchmarks score the guess, so guessing is the default. Naming the exact situations where not-knowing must surface re-opens the abstain option precisely where it matters. (OpenAI 2025, why LMs hallucinate) | F60: =IF($E60<>"",$E60,IF($D60="","",IFERROR(INDEX(Options!$F$162:$F$167,MATCH($D60,Options!$D$162:$D$167,0)),"")))
B61: When it applies · choice 2 | F61: =IF($E61<>"",$E61,IF($D61="","",IFERROR(INDEX(Options!$F$162:$F$167,MATCH($D61,Options!$D$162:$D$167,0)),"")))
B62: When it applies · choice 3 | F62: =IF($E62<>"",$E62,IF($D62="","",IFERROR(INDEX(Options!$F$162:$F$167,MATCH($D62,Options!$D$162:$D$167,0)),"")))
B63: What to do instead | C63: The escape hatch's shape. WHY IT MATTERS: Explicitly permitting 'I don't know' 'can drastically reduce false information' — the vendor's own wording. Prefer a CHECKABLE shape: UNKNOWN plus a gap list can be verified in the output; a bare 'say so' names no form. Giving the escape hatch a shape converts invisible guesses into visible, handleable items. (Anthropic reduce-hallucinations, verbatim) | F63: =IF($E63<>"",$E63,IF($D63="","",IFERROR(INDEX(Options!$F$168:$F$171,MATCH($D63,Options!$D$168:$D$171,0)),"")))
A64: The Stop | B64: The scope boundary — converts open-ended capability into bounded work.
B65: Scope | C65: Numbered, in priority order — the model works down the list. WHY IT MATTERS: A numbered scope list is an execution order: the model works down it instead of wandering sideways. Explicit scope and stop criteria are how vendors now control model 'eagerness' — the same dial, applied to text work. (OpenAI GPT-5 guidance) | F65: =$E65 -> 0
B66: Stop rule | C66: Where work ends — or pauses for you. WHY IT MATTERS: An explicit end condition prevents both default failures: stopping early with a partial answer, and padding on past the answer. For anything loop-like, stopping conditions are a control requirement, not a nicety. (Anthropic building-effective-agents) | F66: =IF($E66<>"",$E66,IF($D66="","",IFERROR(INDEX(Options!$F$172:$F$175,MATCH($D66,Options!$D$172:$D$175,0)),"")))
B67: Explicitly out of scope | C67: Name the adjacent things NOT to touch. WHY IT MATTERS: Models err toward helpful overreach — adjacent questions get answered because they can be. Naming the not-asked keeps output on the question you actually have: the manual version of a relevance guardrail. (OpenAI guardrail categories) | F67: =$E67 -> 0

Sheet Builder_Agent
A1: Element | B1: Attribute | C1: Guidance | D1: Your choice (dropdown) | E1: Custom text (overrides/adds) | F1: Emitted text (auto)
A2: Role | B2: The standing behavioral contract — biases hundreds of unsupervised decisions, not one answer.
B3: Working posture | C3: The job-shaped identity. Compound postures (engineer + analyst + writer) prevent single-lens blind spots. WHY IT MATTERS: An agent's posture persists across hundreds of unsupervised decisions, so it must be job-shaped, not title-shaped. Compound postures (engineer + analyst + writer) prevent the single-lens failure where every problem gets one discipline's answer. (agent-design practice; Anthropic agent guidance) | F3: =IF($E3<>"",$E3,IF($D3="","",IFERROR(INDEX(Options!$F$176:$F$180,MATCH($D3,Options!$D$176:$D$180,0)),"")))
B4: Standing behaviors · choice 1 | C4: The rules that must survive hour three of a long run. WHY IT MATTERS: Long runs outlive their own context — what was said in minute one has faded by hour three. Standing behaviors are the conduct that must hold when nothing recent reinforces it, which is why harness guidance bakes rules into re-read files rather than conversation. (Anthropic long-running-agents harness) | F4: =IF($E4<>"",$E4,IF($D4="","",IFERROR(INDEX(Options!$F$181:$F$186,MATCH($D4,Options!$D$181:$D$186,0)),"")))
B5: Standing behaviors · choice 2 | F5: =IF($E5<>"",$E5,IF($D5="","",IFERROR(INDEX(Options!$F$181:$F$186,MATCH($D5,Options!$D$181:$D$186,0)),"")))
B6: Standing behaviors · choice 3 | F6: =IF($E6<>"",$E6,IF($D6="","",IFERROR(INDEX(Options!$F$181:$F$186,MATCH($D6,Options!$D$181:$D$186,0)),"")))
B7: Standing behaviors · choice 4 | F7: =IF($E7<>"",$E7,IF($D7="","",IFERROR(INDEX(Options!$F$181:$F$186,MATCH($D7,Options!$D$181:$D$186,0)),"")))
A8: Mission ★ | B8: The goal and the definition of done — the loop's exit condition.
B9: Goal | C9: One sentence: the question to answer or the thing to produce. WHY IT MATTERS: One goal sentence is the loop's objective function: gather → act → verify → repeat runs 'until the goal is met.' Two goals in one brief make every prioritization a coin-flip you never see. (Anthropic agent-loop framing) | F9: =$E9 -> 0
B10: Decision it supports | C10: What someone will do differently depending on the answer — filters everything downstream. WHY IT MATTERS: Naming the decision the work supports filters everything downstream — which findings matter, what precision suffices, what is noise. It is the brief-level relevance guardrail: scope drift dies here. (OpenAI relevance-guardrail concept; mission-brief practice) | F10: =$E10 -> 0
B11: Audience & deadline | C11: Who sees it, how long they'll give it, and when it's due. WHY IT MATTERS: Audience and deadline set the depth-versus-speed tradeoffs the agent will otherwise make for you, silently. A 30-second executive read and a hard due date change method choices all the way down the pipeline. (practitioner consensus) | F11: =$E11 -> 0
B12: Cadence | C12: One-off or recurring changes the economics: recurring jobs get standing briefs. WHY IT MATTERS: One-off versus recurring changes the economics of the whole brief: recurring jobs justify standing briefs, delta reporting, and versioned definitions — where agentic prompting pays compound interest. (reuse-by-diff pattern; AGENTS.md practice) | F12: =IF($E12<>"",$E12,IF($D12="","",IFERROR(INDEX(Options!$F$187:$F$188,MATCH($D12,Options!$D$187:$D$188,0)),"")))
B13: Done looks like | C13: The deliverables in one line — exact and countable. WHY IT MATTERS: The loop needs an exit condition it can evaluate. 'Done looks like: three files, named thus' is countable; without it agents stop early or run forever — the documented failure that structured task lists with pass flags exist to prevent. (Anthropic harness: feature-list pattern) | F13: =$E13 -> 0
B14: Verifiable by · choice 1 | C14: The check the agent can actually run to know it's done — the single highest-leverage line in an agentic prompt. WHY IT MATTERS: The single highest-leverage line in a brief. The vendor's own rule for long-running agents: mark work complete 'only after end-to-end verification confirms it works, not when the code is written.' A done-check the agent can run converts 'I finished' into 'it passed.' (Anthropic memory-tool guidance, verbatim) | F14: =IF($E14<>"",$E14,IF($D14="","",IFERROR(INDEX(Options!$F$189:$F$193,MATCH($D14,Options!$D$189:$D$193,0)),"")))
B15: Verifiable by · choice 2 | F15: =IF($E15<>"",$E15,IF($D15="","",IFERROR(INDEX(Options!$F$189:$F$193,MATCH($D15,Options!$D$189:$D$193,0)),"")))
B16: Verifiable by · choice 3 | F16: =IF($E16<>"",$E16,IF($D16="","",IFERROR(INDEX(Options!$F$189:$F$193,MATCH($D16,Options!$D$189:$D$193,0)),"")))
A17: Context | B17: Tribal knowledge, written down — the agent steps on every unstated quirk.
B18: Domain in three sentences | C18: The process, the actors, what 'good' means. WHY IT MATTERS: Three sentences of process, actors, and what 'good' means give every downstream judgment a frame. Without them the agent optimizes for generic best practice — generically right, specifically wrong for your operation. (context-element mechanics) | F18: =$E18 -> 0
B19: Glossary (controlled vocabulary) · choice 1 | C19: Every metric as a card: numerator, denominator, grain, inclusions, exclusions. The agent will otherwise compute three subtly different versions. WHY IT MATTERS: An agent touches every source repeatedly: a guessed denominator doesn't make one wrong sentence — it propagates through every transformation, chart, and slide of the run. Metric cards make definitions load-bearing once and correct everywhere. (source-register discipline; pipeline field practice) | F19: =IF($E19<>"",$E19,IF($D19="","",IFERROR(INDEX(Options!$F$194:$F$194,MATCH($D19,Options!$D$194:$D$194,0)),"")))
B20: Glossary (controlled vocabulary) · choice 2 | F20: =IF($E20<>"",$E20,IF($D20="","",IFERROR(INDEX(Options!$F$194:$F$194,MATCH($D20,Options!$D$194:$D$194,0)),"")))
B21: Entities & identifiers | C21: Part numbers, site names, aliases, vendor codes — spelled the way the audience spells them. WHY IT MATTERS: Exact identifiers, spelled the way the audience spells them, prevent silent fuzzy matching — the join on 'almost the same part number' that poisons a dataset without raising an error. Enumerated entities turn matching into lookup. (data-pipeline practice) | F21: =$E21 -> 0
B22: Known quirks → rules · choice 1 | C22: Things that have bitten before, each with the rule that disarms it. WHY IT MATTERS: Each known quirk with its disarming rule converts institutional scar tissue into instructions. Undocumented, the same quirk gets 'fixed' differently every run — plausibly, silently, and sometimes destructively. (hallucination mechanics applied to data) | F22: =IF($E22<>"",$E22,IF($D22="","",IFERROR(INDEX(Options!$F$195:$F$198,MATCH($D22,Options!$D$195:$D$198,0)),"")))
B23: Known quirks → rules · choice 2 | F23: =IF($E23<>"",$E23,IF($D23="","",IFERROR(INDEX(Options!$F$195:$F$198,MATCH($D23,Options!$D$195:$D$198,0)),"")))
B24: Targets & prior work | C24: Thresholds that matter, and files or decisions the output must stay consistent with. WHY IT MATTERS: Thresholds and previously-published numbers are the run's consistency constraints: they anchor new output to figures the organization already trusts and make drift a detectable event instead of a surprise in a meeting. (reconciliation-anchor family) | F24: =$E24 -> 0
A25: Environment ★ | B25: The workspace contract: where the agent may read, where it must write, what is forbidden.
B26: Workspace | C26: Repo/folder and branch. One initiative, one folder. WHY IT MATTERS: One initiative, one folder is blast-radius design: everything the run touches is enumerable, backupable, revertable. It also makes sessions reproducible — harness practice starts every session by re-reading the same workspace. (Anthropic harness: per-session ritual) | F26: =$E26 -> 0
B27: Read/write boundaries · choice 1 | C27: The three-zone layout: immutable inputs, versioned outputs, regenerable scratch. WHY IT MATTERS: The three-zone layout engineers reversibility in before any action runs: immutable inputs can't be corrupted, versioned outputs can't be silently overwritten, scratch is disposable by contract. Vendor tooling enforces the same idea as protected paths and blocked destructive commands. (Claude Code permission modes; git-revert harness practice) | F27: =IF($E27<>"",$E27,IF($D27="","",IFERROR(INDEX(Options!$F$199:$F$201,MATCH($D27,Options!$D$199:$D$201,0)),"")))
B28: Read/write boundaries · choice 2 | F28: =IF($E28<>"",$E28,IF($D28="","",IFERROR(INDEX(Options!$F$199:$F$201,MATCH($D28,Options!$D$199:$D$201,0)),"")))
B29: Tools allowed · choice 1 | C29: Name what exists. Anything unnamed is a guess. WHY IT MATTERS: Least privilege starts with naming what exists — anything unnamed is a guess the agent may make for you. Published guidance risk-rates every tool (low/medium/high) by write access, reversibility, and impact; the allowed list is where that rating lives. (OpenAI practical guide, tool safeguards) | F29: =IF($E29<>"",$E29,IF($D29="","",IFERROR(INDEX(Options!$F$202:$F$206,MATCH($D29,Options!$D$202:$D$206,0)),"")))
B30: Tools allowed · choice 2 | F30: =IF($E30<>"",$E30,IF($D30="","",IFERROR(INDEX(Options!$F$202:$F$206,MATCH($D30,Options!$D$202:$D$206,0)),"")))
B31: Tools allowed · choice 3 | F31: =IF($E31<>"",$E31,IF($D31="","",IFERROR(INDEX(Options!$F$202:$F$206,MATCH($D31,Options!$D$202:$D$206,0)),"")))
B32: Forbidden actions · choice 1 | C32: The explicit denylist — name what would be assumed available otherwise. WHY IT MATTERS: An explicit denylist beats an implied one because evaluation order is deny-first: what is forbidden stays forbidden regardless of what else allows it. Name what would otherwise be assumed available — email, deletion, posting. (permission-rule precedence: deny > ask > allow) | F32: =IF($E32<>"",$E32,IF($D32="","",IFERROR(INDEX(Options!$F$207:$F$212,MATCH($D32,Options!$D$207:$D$212,0)),"")))
B33: Forbidden actions · choice 2 | F33: =IF($E33<>"",$E33,IF($D33="","",IFERROR(INDEX(Options!$F$207:$F$212,MATCH($D33,Options!$D$207:$D$212,0)),"")))
B34: Forbidden actions · choice 3 | F34: =IF($E34<>"",$E34,IF($D34="","",IFERROR(INDEX(Options!$F$207:$F$212,MATCH($D34,Options!$D$207:$D$212,0)),"")))
B35: Confidentiality · choice 1 | C35: What may leave the workspace, and in what form. WHY IT MATTERS: The documented exfiltration pattern needs three legs at once: private data, untrusted content, and an outbound channel. The confidentiality clause removes or narrows the outbound leg — say what may leave the workspace, and in what form. (lethal-trifecta analysis; PII-filter guardrails) | F35: =IF($E35<>"",$E35,IF($D35="","",IFERROR(INDEX(Options!$F$213:$F$215,MATCH($D35,Options!$D$213:$D$215,0)),"")))
B36: Confidentiality · choice 2 | F36: =IF($E36<>"",$E36,IF($D36="","",IFERROR(INDEX(Options!$F$213:$F$215,MATCH($D36,Options!$D$213:$D$215,0)),"")))
B37: Action risk policy · choice 1 | C37: How actions are triaged by consequence — the published patterns. WHY IT MATTERS: Triaging actions by consequence is the published pattern on both major stacks: reversible proceeds, irreversible asks — operationalized as low/medium/high tool ratings and never/maybe/always-irreversible action classes. (OpenAI practical guide; Magentic-UI action guards) | F37: =IF($E37<>"",$E37,IF($D37="","",IFERROR(INDEX(Options!$F$216:$F$218,MATCH($D37,Options!$D$216:$D$218,0)),"")))
B38: Action risk policy · choice 2 | F38: =IF($E38<>"",$E38,IF($D38="","",IFERROR(INDEX(Options!$F$216:$F$218,MATCH($D38,Options!$D$216:$D$218,0)),"")))
A39: Inputs | B39: The source register: each source's location, format, grain, trust level, and known issues.
B40: Source register | C40: One block per source. The skeleton below is the discipline — fill every line or write UNKNOWN. WHY IT MATTERS: A source register makes every input's location, format, grain, and meaning explicit before anything is computed — profiling before processing. Skipped, the first wrong assumption about what one row means propagates through the entire run. (ETL discipline) | F40: =$E40 -> 0
B41: Trust levels · choice 1 | C41: Declare per source — trust level dictates validation depth. WHY IT MATTERS: Trust level dictates validation depth — the data-side version of tool risk ratings: a system export and a hand-typed tracker must not get the same scrutiny. Declaring it routes checking effort to where errors actually live. (risk-rating pattern applied to sources) | F41: =IF($E41<>"",$E41,IF($D41="","",IFERROR(INDEX(Options!$F$219:$F$221,MATCH($D41,Options!$D$219:$D$221,0)),"")))
B42: Trust levels · choice 2 | F42: =IF($E42<>"",$E42,IF($D42="","",IFERROR(INDEX(Options!$F$219:$F$221,MATCH($D42,Options!$D$219:$D$221,0)),"")))
B43: The UNKNOWN rule | C43: The register's cardinal rule. WHY IT MATTERS: 'Write UNKNOWN, never guess' turns the model's strongest failure mode — plausible gap-filling — into a logged, owned item. An UNKNOWN is a work item; a guess is a landmine with a delay. (abstention research applied to pipelines) | F43: =IF($E43<>"",$E43,IF($D43="","",IFERROR(INDEX(Options!$F$222:$F$222,MATCH($D43,Options!$D$222:$D$222,0)),"")))
A44: Plan | B44: Bounded method: the steps in order, methods allowed, methods requiring permission.
B45: Steps | C45: Each step: what it consumes, what it produces. WHY IT MATTERS: Steps with named inputs and outputs make intermediates inspectable — the documented reason explicit pipelines still matter: 'useful when you need to inspect intermediate outputs or enforce a specific pipeline structure.' Audit trails are built here. (Anthropic chaining guidance) | F45: =$E45 -> 0
B46: Methods allowed · choice 1 | C46: Boring and reproducible. The default analytical toolkit. WHY IT MATTERS: Boring, reproducible methods are a feature: descriptive stats and run charts re-run identically and survive challenge; clever one-offs don't. Compute-via-code is non-negotiable — model arithmetic degrades sharply as the numbers grow. (Faith & Fate, NeurIPS 2023) | F46: =IF($E46<>"",$E46,IF($D46="","",IFERROR(INDEX(Options!$F$223:$F$227,MATCH($D46,Options!$D$223:$D$227,0)),"")))
B47: Methods allowed · choice 2 | F47: =IF($E47<>"",$E47,IF($D47="","",IFERROR(INDEX(Options!$F$223:$F$227,MATCH($D47,Options!$D$223:$D$227,0)),"")))
B48: Methods allowed · choice 3 | F48: =IF($E48<>"",$E48,IF($D48="","",IFERROR(INDEX(Options!$F$223:$F$227,MATCH($D48,Options!$D$223:$D$227,0)),"")))
B49: Not without asking · choice 1 | C49: Propose at a gate; never just use. WHY IT MATTERS: 'Propose at a gate, never just use' routes method escalation through a human — the high-risk and failure-threshold triggers vendors place on agent actions, applied to analysis choices that would change what the numbers mean. (OpenAI escalation guidance) | F49: =IF($E49<>"",$E49,IF($D49="","",IFERROR(INDEX(Options!$F$228:$F$231,MATCH($D49,Options!$D$228:$D$231,0)),"")))
B50: Not without asking · choice 2 | F50: =IF($E50<>"",$E50,IF($D50="","",IFERROR(INDEX(Options!$F$228:$F$231,MATCH($D50,Options!$D$228:$D$231,0)),"")))
B51: Not without asking · choice 3 | F51: =IF($E51<>"",$E51,IF($D51="","",IFERROR(INDEX(Options!$F$228:$F$231,MATCH($D51,Options!$D$228:$D$231,0)),"")))
A52: Checks ★ | B52: Machine-evaluable verification: HARD stops the run, SOFT flags and continues.
B53: Reconciliation anchor | C53: One number from OUTSIDE the run that the results must tie to. The most important single check. WHY IT MATTERS: One number from outside the run that the results must tie to catches whole-pipeline errors — wrong filters, dropped rows, doubled joins — with a single comparison. Recalculate, scan for errors, tie out: the pattern vendor tooling mandates before delivery. (reconciliation/recalc practice) | F53: =$E53 -> 0
B54: HARD checks (stop the run) · choice 1 | C54: Failure means stop, show the offending rows, and wait. WHY IT MATTERS: Rules-based feedback is 'the best form of feedback' an agent gets — clear rules, plus which rule failed and why. HARD checks make the run fail loudly at the failure point instead of finishing wrong politely; showing the offending rows makes the failure debuggable. (Anthropic Agent SDK verify-work) | F54: =IF($E54<>"",$E54,IF($D54="","",IFERROR(INDEX(Options!$F$232:$F$241,MATCH($D54,Options!$D$232:$D$241,0)),"")))
B55: HARD checks (stop the run) · choice 2 | F55: =IF($E55<>"",$E55,IF($D55="","",IFERROR(INDEX(Options!$F$232:$F$241,MATCH($D55,Options!$D$232:$D$241,0)),"")))
B56: HARD checks (stop the run) · choice 3 | F56: =IF($E56<>"",$E56,IF($D56="","",IFERROR(INDEX(Options!$F$232:$F$241,MATCH($D56,Options!$D$232:$D$241,0)),"")))
B57: HARD checks (stop the run) · choice 4 | F57: =IF($E57<>"",$E57,IF($D57="","",IFERROR(INDEX(Options!$F$232:$F$241,MATCH($D57,Options!$D$232:$D$241,0)),"")))
B58: SOFT checks (flag and continue) · choice 1 | C58: Suspicion, not failure — logged to open items. WHY IT MATTERS: SOFT separates suspicion from failure so the run neither ignores anomalies nor cries wolf: flagged items land in open items with evidence attached, and a human triages them at review instead of mid-run. (check-type taxonomy; open-items discipline) | F58: =IF($E58<>"",$E58,IF($D58="","",IFERROR(INDEX(Options!$F$242:$F$245,MATCH($D58,Options!$D$242:$D$245,0)),"")))
B59: SOFT checks (flag and continue) · choice 2 | F59: =IF($E59<>"",$E59,IF($D59="","",IFERROR(INDEX(Options!$F$242:$F$245,MATCH($D59,Options!$D$242:$D$245,0)),"")))
B60: SOFT checks (flag and continue) · choice 3 | F60: =IF($E60<>"",$E60,IF($D60="","",IFERROR(INDEX(Options!$F$242:$F$245,MATCH($D60,Options!$D$242:$D$245,0)),"")))
A61: Outputs | B61: The deliverable contract and the audit trail — exact names, exact locations, three logs.
B62: Deliverables | C62: Numbered, with the _MMDDYY convention and what each contains. WHY IT MATTERS: Numbered deliverables with exact names make 'done' countable — the reason harness guidance tracks work as a structured list with pass flags rather than prose: it prevents premature completion and orphaned extras alike. (Anthropic harness: feature-list pattern) | F62: =$E62 -> 0
B63: Logs · choice 1 | C63: The three files that make a run auditable. WHY IT MATTERS: CHANGES, FINDINGS, and OPEN_ITEMS make a run auditable after the fact — the 'structured updates' long-running-agent guidance requires every session to leave. Without logs there is no way to distinguish what the agent did from what it says it did. (Anthropic harness guidance) | F63: =IF($E63<>"",$E63,IF($D63="","",IFERROR(INDEX(Options!$F$246:$F$248,MATCH($D63,Options!$D$246:$D$248,0)),"")))
B64: Logs · choice 2 | F64: =IF($E64<>"",$E64,IF($D64="","",IFERROR(INDEX(Options!$F$246:$F$248,MATCH($D64,Options!$D$246:$D$248,0)),"")))
B65: Reproducibility · choice 1 | C65: The regeneration guarantee. WHY IT MATTERS: The regeneration guarantee — same inputs, same command, same outputs — turns a deliverable into evidence. It is why outputs carry formulas rather than pasted values and why environments get an init script: reproducibility is engineered, not hoped for. (harness init-script pattern; workbook discipline) | F65: =IF($E65<>"",$E65,IF($D65="","",IFERROR(INDEX(Options!$F$249:$F$251,MATCH($D65,Options!$D$249:$D$251,0)),"")))
B66: Reproducibility · choice 2 | F66: =IF($E66<>"",$E66,IF($D66="","",IFERROR(INDEX(Options!$F$249:$F$251,MATCH($D66,Options!$D$249:$D$251,0)),"")))
A67: Process & Gates ★ | B67: Phases with human checkpoints at the cheap-error points — and the autonomy rules between them.
B68: Phases | C68: Phase 0 is always intake: the agent restates the mission and its assumptions in its own words. WHY IT MATTERS: Phase 0 — the agent restates the mission and its assumptions in its own words — is the cheapest error catch in the run: a misread brief costs pennies here and a full rerun later. Plan-then-approve is the documented pattern across vendor tooling. (Claude Code plan mode; Magentic-UI co-planning) | F68: =$E68 -> 0
B69: Gates · choice 1 | C69: Human checkpoints, in ascending cost of the error they catch. WHY IT MATTERS: Gates put human judgment where published guidance puts it: before edits (plan approval), before irreversible or high-stakes actions, at failure thresholds, and at final review — each gate catching its error class at its cheapest point. (OpenAI practical guide; gate-placement survey) | F69: =IF($E69<>"",$E69,IF($D69="","",IFERROR(INDEX(Options!$F$252:$F$256,MATCH($D69,Options!$D$252:$D$256,0)),"")))
B70: Gates · choice 2 | F70: =IF($E70<>"",$E70,IF($D70="","",IFERROR(INDEX(Options!$F$252:$F$256,MATCH($D70,Options!$D$252:$D$256,0)),"")))
B71: Gates · choice 3 | F71: =IF($E71<>"",$E71,IF($D71="","",IFERROR(INDEX(Options!$F$252:$F$256,MATCH($D71,Options!$D$252:$D$256,0)),"")))
B72: Autonomy rules · choice 1 | C72: Both halves matter: without 'proceed' you built a slow chatbot; without 'stop' you built a liability. WHY IT MATTERS: Both halves are load-bearing: without proceed rules you built a slow chatbot that asks about everything; without stop rules you built a liability that asks about nothing. The published stop triggers are high-risk actions and exceeded failure thresholds. (OpenAI human-intervention guidance) | F72: =IF($E72<>"",$E72,IF($D72="","",IFERROR(INDEX(Options!$F$257:$F$263,MATCH($D72,Options!$D$257:$D$263,0)),"")))
B73: Autonomy rules · choice 2 | F73: =IF($E73<>"",$E73,IF($D73="","",IFERROR(INDEX(Options!$F$257:$F$263,MATCH($D73,Options!$D$257:$D$263,0)),"")))
B74: Autonomy rules · choice 3 | F74: =IF($E74<>"",$E74,IF($D74="","",IFERROR(INDEX(Options!$F$257:$F$263,MATCH($D74,Options!$D$257:$D$263,0)),"")))
B75: Autonomy rules · choice 4 | F75: =IF($E75<>"",$E75,IF($D75="","",IFERROR(INDEX(Options!$F$257:$F$263,MATCH($D75,Options!$D$257:$D$263,0)),"")))
B76: Autonomy level | C76: A deliberate design choice, separate from capability. Named by the role you keep — pick the lowest level that still gets the job done. WHY IT MATTERS: Autonomy is 'a deliberate design decision, separate from capability' — the published levels are named by the role the human keeps: operator, collaborator, consultant, approver, observer. Pick the lowest level that gets the job done; capability never obliges autonomy. (Feng et al. 2025) | F76: =IF($E76<>"",$E76,IF($D76="","",IFERROR(INDEX(Options!$F$264:$F$268,MATCH($D76,Options!$D$264:$D$268,0)),"")))
A77: Rules | B77: The non-negotiables — short, absolute, few — that must survive a long context.
B78: Invariants · choice 1 | C78: The standard set — prune to what this job actually needs. WHY IT MATTERS: Invariants are the deterministic guardrail class — rules enforced as rules, not judgment calls: never invent data, never overwrite inputs, version everything. Deterministic protections are their own category in vendor guardrail taxonomies precisely because they don't degrade under pressure. (OpenAI rules-based protections) | F78: =IF($E78<>"",$E78,IF($D78="","",IFERROR(INDEX(Options!$F$269:$F$274,MATCH($D78,Options!$D$269:$D$274,0)),"")))
B79: Invariants · choice 2 | F79: =IF($E79<>"",$E79,IF($D79="","",IFERROR(INDEX(Options!$F$269:$F$274,MATCH($D79,Options!$D$269:$D$274,0)),"")))
B80: Invariants · choice 3 | F80: =IF($E80<>"",$E80,IF($D80="","",IFERROR(INDEX(Options!$F$269:$F$274,MATCH($D80,Options!$D$269:$D$274,0)),"")))
B81: Invariants · choice 4 | F81: =IF($E81<>"",$E81,IF($D81="","",IFERROR(INDEX(Options!$F$269:$F$274,MATCH($D81,Options!$D$269:$D$274,0)),"")))
A82: Quality Bar | B82: The definition of done as a checklist the agent must satisfy — and you can audit in sixty seconds.
B83: Definition of done · choice 1 | C83: Tick-able, evidence-able items. WHY IT MATTERS: A definition of done as tick-able, evidence-able items is the anti-premature-completion device: 'passes' flips only on verification, and the checks themselves are out of bounds to edit — 'it is unacceptable to remove or edit tests.' (Anthropic harness, verbatim) | F83: =IF($E83<>"",$E83,IF($D83="","",IFERROR(INDEX(Options!$F$275:$F$280,MATCH($D83,Options!$D$275:$D$280,0)),"")))
B84: Definition of done · choice 2 | F84: =IF($E84<>"",$E84,IF($D84="","",IFERROR(INDEX(Options!$F$275:$F$280,MATCH($D84,Options!$D$275:$D$280,0)),"")))
B85: Definition of done · choice 3 | F85: =IF($E85<>"",$E85,IF($D85="","",IFERROR(INDEX(Options!$F$275:$F$280,MATCH($D85,Options!$D$275:$D$280,0)),"")))
A86: Reporting | B86: The fixed shape of the final message: status, headline, evidence, open items — under 25 lines.
B87: Report shape · choice 1 | C87: The standard six lines — deselect only what genuinely doesn't apply. WHY IT MATTERS: A fixed report shape is why status reads in 30 seconds: the same lines in the same order every run, skimmable by humans and parseable by tools. Every agent SDK ships fixed result-status enums for the same reason — variable-shape reports hide failures. (SDK result/status enums) | F87: =IF($E87<>"",$E87,IF($D87="","",IFERROR(INDEX(Options!$F$281:$F$286,MATCH($D87,Options!$D$281:$D$286,0)),"")))
B88: Report shape · choice 2 | F88: =IF($E88<>"",$E88,IF($D88="","",IFERROR(INDEX(Options!$F$281:$F$286,MATCH($D88,Options!$D$281:$D$286,0)),"")))
B89: Report shape · choice 3 | F89: =IF($E89<>"",$E89,IF($D89="","",IFERROR(INDEX(Options!$F$281:$F$286,MATCH($D89,Options!$D$281:$D$286,0)),"")))
B90: Report shape · choice 4 | F90: =IF($E90<>"",$E90,IF($D90="","",IFERROR(INDEX(Options!$F$281:$F$286,MATCH($D90,Options!$D$281:$D$286,0)),"")))
B91: Report discipline · choice 1 | C91: The rules that keep reports readable and honest. WHY IT MATTERS: Evidence over assertion: 'done' means the check it ran, the output it got, and the file re-opened and verified — not the claim. Reports that cite their evidence convert trust from personality to track record, which is what agent oversight is supposed to run on. (harness verification guidance; NCSC oversight principle) | F91: =IF($E91<>"",$E91,IF($D91="","",IFERROR(INDEX(Options!$F$287:$F$288,MATCH($D91,Options!$D$287:$D$288,0)),"")))
B92: Report discipline · choice 2 | F92: =IF($E92<>"",$E92,IF($D92="","",IFERROR(INDEX(Options!$F$287:$F$288,MATCH($D92,Options!$D$287:$D$288,0)),"")))

Sheet Prompt_Gen
A1: ASSEMBLED GENERATIVE PROMPT — copy cell A4 (it recalculates from Builder_Gen)
A2: Fill the yellow cells on the builder sheet; blank rows are skipped automatically. Search the result for {{ — unfilled placeholders mean you are not done.
A4: =_xlfn.TEXTJOIN(CHAR(10)&CHAR(10),TRUE(),$C$4,$C$5,$C$6,$C$7,$C$8,$C$9,$C$10) -> <role> You are a careful analyst. You never invent facts or numbers — missing is missing. </role> <task> Answer: {{the question, with metric and period — e.g., "what is X by group for Q2 vs the target"}}? Example (replace): what is the return rate by site for Q2 vs the 2.0% target? </task> | C4: =IF(_xlfn.TEXTJOIN(CHAR(10),TRUE(),Builder_Gen!$F$2:$F$16)="","","<role>"&CHAR(10)&_xlfn.TEXTJOIN(CHAR(10),TRUE(),Builder_Gen!$F$2:$F$16)&CHAR(10)&"</role>") -> <role> You are a careful analyst. You never invent facts or numbers — missing is missing. </role>
C5: =IF(_xlfn.TEXTJOIN(CHAR(10),TRUE(),Builder_Gen!$F$17:$F$25)="","","<task>"&CHAR(10)&_xlfn.TEXTJOIN(CHAR(10),TRUE(),Builder_Gen!$F$17:$F$25)&CHAR(10)&"</task>") -> <task> Answer: {{the question, with metric and period — e.g., "what is X by group for Q2 vs the target"}}? Example (replace): what is the return rate by site for Q2 vs the 2.0% target? </task>
C6: =IF(_xlfn.TEXTJOIN(CHAR(10),TRUE(),Builder_Gen!$F$26:$F$36)="","","<context>"&CHAR(10)&_xlfn.TEXTJOIN(CHAR(10),TRUE(),Builder_Gen!$F$26:$F$36)&CHAR(10)&"</context>")
C7: =IF(_xlfn.TEXTJOIN(CHAR(10),TRUE(),Builder_Gen!$F$37:$F$52)="","","<format>"&CHAR(10)&_xlfn.TEXTJOIN(CHAR(10),TRUE(),Builder_Gen!$F$37:$F$52)&CHAR(10)&"</format>")
C8: =IF(_xlfn.TEXTJOIN(CHAR(10),TRUE(),Builder_Gen!$F$53:$F$58)="","","<examples>"&CHAR(10)&_xlfn.TEXTJOIN(CHAR(10),TRUE(),Builder_Gen!$F$53:$F$58)&CHAR(10)&"</examples>")
C9: =IF(_xlfn.TEXTJOIN(CHAR(10),TRUE(),Builder_Gen!$F$59:$F$63)="","","<uncertainty_rules>"&CHAR(10)&_xlfn.TEXTJOIN(CHAR(10),TRUE(),Builder_Gen!$F$59:$F$63)&CHAR(10)&"</uncertainty_rules>")
C10: =IF(_xlfn.TEXTJOIN(CHAR(10),TRUE(),Builder_Gen!$F$64:$F$67)="","","<scope>"&CHAR(10)&_xlfn.TEXTJOIN(CHAR(10),TRUE(),Builder_Gen!$F$64:$F$67)&CHAR(10)&"</scope>")

Sheet Prompt_Agent
A1: ASSEMBLED AGENTIC PROMPT — copy cell A4 (it recalculates from Builder_Agent)
A2: Fill the yellow cells on the builder sheet; blank rows are skipped automatically. Search the result for {{ — unfilled placeholders mean you are not done.
A4: =_xlfn.TEXTJOIN(CHAR(10)&CHAR(10),TRUE(),$C$4,$C$5,$C$6,$C$7,$C$8,$C$9,$C$10,$C$11,$C$12,$C$13,$C$14,$C$15) | C4: =IF(_xlfn.TEXTJOIN(CHAR(10),TRUE(),Builder_Agent!$F$2:$F$7)="","","<role>"&CHAR(10)&_xlfn.TEXTJOIN(CHAR(10),TRUE(),Builder_Agent!$F$2:$F$7)&CHAR(10)&"</role>")
C5: =IF(_xlfn.TEXTJOIN(CHAR(10),TRUE(),Builder_Agent!$F$8:$F$16)="","","<mission>"&CHAR(10)&_xlfn.TEXTJOIN(CHAR(10),TRUE(),Builder_Agent!$F$8:$F$16)&CHAR(10)&"</mission>")
C6: =IF(_xlfn.TEXTJOIN(CHAR(10),TRUE(),Builder_Agent!$F$17:$F$24)="","","<context>"&CHAR(10)&_xlfn.TEXTJOIN(CHAR(10),TRUE(),Builder_Agent!$F$17:$F$24)&CHAR(10)&"</context>")
C7: =IF(_xlfn.TEXTJOIN(CHAR(10),TRUE(),Builder_Agent!$F$25:$F$38)="","","<environment>"&CHAR(10)&_xlfn.TEXTJOIN(CHAR(10),TRUE(),Builder_Agent!$F$25:$F$38)&CHAR(10)&"</environment>")
C8: =IF(_xlfn.TEXTJOIN(CHAR(10),TRUE(),Builder_Agent!$F$39:$F$43)="","","<inputs>"&CHAR(10)&_xlfn.TEXTJOIN(CHAR(10),TRUE(),Builder_Agent!$F$39:$F$43)&CHAR(10)&"</inputs>")
C9: =IF(_xlfn.TEXTJOIN(CHAR(10),TRUE(),Builder_Agent!$F$44:$F$51)="","","<plan>"&CHAR(10)&_xlfn.TEXTJOIN(CHAR(10),TRUE(),Builder_Agent!$F$44:$F$51)&CHAR(10)&"</plan>")
C10: =IF(_xlfn.TEXTJOIN(CHAR(10),TRUE(),Builder_Agent!$F$52:$F$60)="","","<checks>"&CHAR(10)&_xlfn.TEXTJOIN(CHAR(10),TRUE(),Builder_Agent!$F$52:$F$60)&CHAR(10)&"</checks>")
C11: =IF(_xlfn.TEXTJOIN(CHAR(10),TRUE(),Builder_Agent!$F$61:$F$66)="","","<outputs>"&CHAR(10)&_xlfn.TEXTJOIN(CHAR(10),TRUE(),Builder_Agent!$F$61:$F$66)&CHAR(10)&"</outputs>")
C12: =IF(_xlfn.TEXTJOIN(CHAR(10),TRUE(),Builder_Agent!$F$67:$F$76)="","","<process>"&CHAR(10)&_xlfn.TEXTJOIN(CHAR(10),TRUE(),Builder_Agent!$F$67:$F$76)&CHAR(10)&"</process>")
C13: =IF(_xlfn.TEXTJOIN(CHAR(10),TRUE(),Builder_Agent!$F$77:$F$81)="","","<rules>"&CHAR(10)&_xlfn.TEXTJOIN(CHAR(10),TRUE(),Builder_Agent!$F$77:$F$81)&CHAR(10)&"</rules>")
C14: =IF(_xlfn.TEXTJOIN(CHAR(10),TRUE(),Builder_Agent!$F$82:$F$85)="","","<quality_bar>"&CHAR(10)&_xlfn.TEXTJOIN(CHAR(10),TRUE(),Builder_Agent!$F$82:$F$85)&CHAR(10)&"</quality_bar>")
C15: =IF(_xlfn.TEXTJOIN(CHAR(10),TRUE(),Builder_Agent!$F$86:$F$92)="","","<reporting>"&CHAR(10)&_xlfn.TEXTJOIN(CHAR(10),TRUE(),Builder_Agent!$F$86:$F$92)&CHAR(10)&"</reporting>")

Sheet Taxonomy
A1: Mode | B1: Element | C1: OOP | D1: Definition | E1: Prevents
A2: generative | B2: Role | C2: class Role extends PromptElement | D2: Who is answering: identity, expertise posture, and checkable behavioral commitments. | E2: the generic-assistant voice; mid-distribution, hedge-everything output.
A3: generative | B3: Task | C3: class Task extends PromptElement | D3: The single clear ask: verb + object + audience + success criterion. | E3: wandering output — ten observations and no answer.
A4: generative | B4: Context | C4: class Context extends PromptElement | D4: Everything true in your world that isn't in the training data — material, definitions, quirks, constraints, and the reasons behind rules. | E4: generically-right, specifically-wrong output — the plausible number with your company's name on it.
A5: generative | B5: Format | C5: class Format extends PromptElement | D5: The output contract: shape, length, tone, and what must be in or out. | E5: the 3×-too-long draft; the buried answer; output you must re-shape by hand.
A6: generative | B6: Examples | C6: class Examples extends PromptElement | D6: 3–5 realistic demonstrations of the task done right — the strongest steering signal there is. | E6: the model guessing your standard from the internet's average; format drift across runs.
A7: generative | B7: The Out | C7: class TheOut extends SafetyValve | D7: The escape route for missing information: name the condition, the honest move, and how gaps surface — so the model never has to choose between obeying you and being honest. | E7: confident invention — the signature failure of factual work.
A8: generative | B8: The Stop | C8: class TheStop extends SafetyValve | D8: The scope boundary — converts open-ended capability into bounded work. | E8: scope sprawl; work continuing past the point of usefulness.
A9: agentic | B9: Role | C9: class AgentRole extends Role | D9: The standing behavioral contract — biases hundreds of unsupervised decisions, not one answer. | E9: an agent that improvises its professional standards mid-run.
A10: agentic | B10: Mission | C10: class Mission extends Task // + definitionOfDone | D10: The goal and the definition of done — the loop's exit condition. | E10: the agent deciding for itself what finished means — plausible activity, indefinitely.
A11: agentic | B11: Context | C11: class AgentContext extends Context // coverage pressure | D11: Tribal knowledge, written down — the agent steps on every unstated quirk. | E11: silent invented fixes — the most expensive agent error, because they look like diligence.
A12: agentic | B12: Environment | C12: class Environment extends PromptElement // NEW IN KIND | D12: The workspace contract: where the agent may read, where it must write, what is forbidden. | E12: the agent 'helpfully' editing your master file or wandering outside its folder.
... A20: agentic | B20: Reporting | C20: class Reporting extends Format // the interface back to you | D20: The fixed shape of the final message: status, headline, evidence, open items — under 25 lines. | E20: a narrative essay where a status should be.
