Workbook

Sheet README
B2: Prompt Template Configurator
B3: v1.0 · August 2026 · owner Oscar Penny · generated from prompt-library/taxonomy/ (the source of truth — edit there, rebuild with src/build_configurator_xlsx.py)
B5: How to use
B6: 1. Open Builder_Gen (chat prompts) or Builder_Agent (agent mission briefs).
B7: 2. Fill the YELLOW cells only: pick options from the dropdowns; add or override with custom text. Attributes marked "choice 1/2/3" accept several picks.
B8: 3. The prompt assembles itself on Prompt_Gen / Prompt_Agent — copy cell A4 into your AI tool.
B9: 4. Search the assembled prompt for {{ before you run — placeholders left unfilled mean you are not done.
B11: Legend
B12: YELLOW fill = cells you edit (dropdown choice, custom text). Everything else is generated — leave it.
B13: ★ next to an element name = keep this element; it is what makes the prompt reliable.
B14: The Options sheet is the full menu with guidance (core + extended); Taxonomy defines every element.
B16: Example
... B19: Companion tools: Prompt_Template_Creator.html (the interactive builder — same taxonomy, richer experience) · Prompt_Element_Taxonomy_Reference.pdf (the printed ontology).

Sheet Options
A1: Mode | B1: Element | C1: Attribute | D1: Option | E1: Pick when | F1: Emits into the prompt | G1: Tier
A2: generative | B2: Role | C2: Identity / posture | D2: Careful analyst | E2: numbers, data, trends | F2: You are a careful analyst. | G2: core
A3: generative | B3: Role | C3: Identity / posture | D3: Precise editor | E3: improving text you supply | F3: You are a precise editor. | G3: core
A4: generative | B4: Role | C4: Identity / posture | D4: Demanding reviewer | E4: grading, evaluating, comparing | F4: You are a demanding but fair reviewer. | G4: core
A5: generative | B5: Role | C5: Identity / posture | D5: Executive presentation writer | E5: decks, summaries for leadership | F5: You are a presentation writer for executives. | G5: core
A6: generative | B6: Role | C6: Identity / posture | D6: Patient explainer | E6: teaching, onboarding material | F6: You are a patient explainer who never condescends. | G6: core
A7: generative | B7: Role | C7: Identity / posture | D7: Devil's advocate | E7: stress-testing a plan or decision | F7: You are a devil's advocate. | G7: core
A8: generative | B8: Role | C8: Identity / posture | D8: Meticulous document processor | E8: extraction, comparison, forms | F8: You are a meticulous document processor. | G8: core
A9: generative | B9: Role | C9: Identity / posture | D9: Cited researcher | E9: web/document research | F9: You are a researcher who cites every claim. | G9: core
A10: generative | B10: Role | C10: Identity / posture | D10: Business writer | E10: emails, memos, announcements | F10: You are an experienced business writer. | G10: extended
A11: generative | B11: Role | C11: Identity / posture | D11: Technical writer | E11: procedures, specs, documentation | F11: You are a technical writer who values precision over polish. | G11: extended
A12: generative | B12: Role | C12: Identity / posture | D12: Facilitator | E12: synthesizing group input, agendas | F12: You are a neutral facilitator. | G12: extended
... A287: agentic | B287: Reporting | C287: Report discipline | D287: Evidence required | E287: always | F287: Claims of success carry evidence: the command run and its output, or the re-opened file. | G287: core

Sheet Builder_Gen
A1: Element | B1: Attribute | C1: Guidance | D1: Your choice (dropdown) | E1: Custom text (overrides/adds) | F1: Emitted text (auto)
A2: Role | B2: Who is answering: identity, expertise posture, and checkable behavioral commitments.
B3: Identity / posture | C3: Pick the professional posture. It sets vocabulary, caution level, and what gets foregrounded — not IQ. | D3: Careful analyst | F3: =IF($E3<>"",$E3,IF($D3="","",IFERROR(INDEX(Options!$F$2:$F$20,MATCH($D3,Options!$D$2:$D$20,0)),""))) -> You are a careful analyst.
B4: Domain expertise | C4: Name the field so the right vocabulary and priorities surface. This foregrounds knowledge — it does not create it. | F4: =$E4 -> 0
B5: Behavioral commitments · choice 1 | C5: The checkable rules — the part of Role that actually changes output. Pick from the three families below. | F5: =$E5 -> 0
B6: Behavioral commitments · choice 2 | F6: =$E6 -> 0
B7: Accuracy behaviors · choice 1 | C7: For anything with facts and numbers. | D7: Never invent | F7: =IF($E7<>"",$E7,IF($D7="","",IFERROR(INDEX(Options!$F$21:$F$25,MATCH($D7,Options!$D$21:$D$25,0)),""))) -> You never invent facts or numbers — missing is missing.
B8: Accuracy behaviors · choice 2 | F8: =IF($E8<>"",$E8,IF($D8="","",IFERROR(INDEX(Options!$F$21:$F$25,MATCH($D8,Options!$D$21:$D$25,0)),"")))
B9: Accuracy behaviors · choice 3 | F9: =IF($E9<>"",$E9,IF($D9="","",IFERROR(INDEX(Options!$F$21:$F$25,MATCH($D9,Options!$D$21:$D$25,0)),"")))
B10: Transparency behaviors · choice 1 | C10: Make the work auditable. | F10: =IF($E10<>"",$E10,IF($D10="","",IFERROR(INDEX(Options!$F$26:$F$30,MATCH($D10,Options!$D$26:$D$30,0)),"")))
B11: Transparency behaviors · choice 2 | F11: =IF($E11<>"",$E11,IF($D11="","",IFERROR(INDEX(Options!$F$26:$F$30,MATCH($D11,Options!$D$26:$D$30,0)),"")))
B12: Transparency behaviors · choice 3 | F12: =IF($E12<>"",$E12,IF($D12="","",IFERROR(INDEX(Options!$F$26:$F$30,MATCH($D12,Options!$D$26:$D$30,0)),"")))
B13: Style behaviors · choice 1 | C13: How it writes, stated as rules. | F13: =IF($E13<>"",$E13,IF($D13="","",IFERROR(INDEX(Options!$F$31:$F$34,MATCH($D13,Options!$D$31:$D$34,0)),"")))
B14: Style behaviors · choice 2 | F14: =IF($E14<>"",$E14,IF($D14="","",IFERROR(INDEX(Options!$F$31:$F$34,MATCH($D14,Options!$D$31:$D$34,0)),"")))
B15: Style behaviors · choice 3 | F15: =IF($E15<>"",$E15,IF($D15="","",IFERROR(INDEX(Options!$F$31:$F$34,MATCH($D15,Options!$D$31:$D$34,0)),"")))
B16: Stance | C16: The critical posture. Blind the model to your preference — it mirrors any side you reveal. | F16: =IF($E16<>"",$E16,IF($D16="","",IFERROR(INDEX(Options!$F$35:$F$39,MATCH($D16,Options!$D$35:$D$39,0)),"")))
A17: Task ★ | B17: The single clear ask: verb + object + audience + success criterion.
B18: Action starter | C18: Each verb is a mini-template — pick one and fill its {{slots}}, or write your own statement below. | D18: Analyze | F18: =IF($E18<>"",$E18,IF($D18="","",IFERROR(INDEX(Options!$F$40:$F$55,MATCH($D18,Options!$D$40:$D$55,0)),""))) -> Answer: {{the question, with metric and period — e.g., "what is X by group for Q2 vs the target"}}?
B19: Task statement | C19: Or write the ask yourself — one task, one sentence if you can manage it. | E19: Example (replace): what is the return rate by site for Q2 vs the 2.0% target? | F19: =$E19 -> Example (replace): what is the return rate by site for Q2 vs the 2.0% target?
B20: Audience | C20: Who receives this and what they already know. It sets altitude and vocabulary. | F20: =IF($E20<>"",$E20,IF($D20="","",IFERROR(INDEX(Options!$F$56:$F$61,MATCH($D20,Options!$D$56:$D$61,0)),"")))
B21: Reader's time budget | C21: How long they'll actually give it — the honest constraint. | F21: =IF($E21<>"",$E21,IF($D21="","",IFERROR(INDEX(Options!$F$62:$F$64,MATCH($D21,Options!$D$62:$D$64,0)),"")))
B22: Reading level | C22: The Canvas-style slider, as options. Plain-language guidance targets 6th–8th grade for general audiences. | F22: =IF($E22<>"",$E22,IF($D22="","",IFERROR(INDEX(Options!$F$65:$F$69,MATCH($D22,Options!$D$65:$D$69,0)),"")))
B23: Success criterion | C23: The task's own completion test — what must be true of the output. | F23: =IF($E23<>"",$E23,IF($D23="","",IFERROR(INDEX(Options!$F$70:$F$73,MATCH($D23,Options!$D$70:$D$73,0)),"")))
B24: Purpose — why it matters | C24: The decision or event this feeds. Models generalize from reasons — and it filters what matters. | F24: =$E24 -> 0
B25: Sense check | C25: Have the model confirm understanding before doing the work — cheapest error catch there is. | F25: =IF($E25<>"",$E25,IF($D25="","",IFERROR(INDEX(Options!$F$74:$F$76,MATCH($D25,Options!$D$74:$D$76,0)),"")))
A26: Context | B26: Everything true in your world that isn't in the training data — material, definitions, quirks, constraints, and the reasons behind rules.
B27: Raw material | C27: The stuff to work from. Long documents go FIRST in the final prompt, instructions after — and delimit so material is never mistaken for instructions. | F27: =IF($E27<>"",$E27,IF($D27="","",IFERROR(INDEX(Options!$F$77:$F$79,MATCH($D27,Options!$D$77:$D$79,0)),"")))
B28: Glossary — controlled vocabulary · choice 1 | C28: Terms with local meaning. For metrics: numerator, denominator, grain, inclusions/exclusions — or the model will compute its own version. | F28: =IF($E28<>"",$E28,IF($D28="","",IFERROR(INDEX(Options!$F$80:$F$80,MATCH($D28,Options!$D$80:$D$80,0)),"")))
B29: Glossary — controlled vocabulary · choice 2 | F29: =IF($E29<>"",$E29,IF($D29="","",IFERROR(INDEX(Options!$F$80:$F$80,MATCH($D29,Options!$D$80:$D$80,0)),"")))
B30: Known quirks → rules · choice 1 | C30: Every quirk you don't write down becomes a silent 'fix' the model invents. Pair each with its rule. | F30: =IF($E30<>"",$E30,IF($D30="","",IFERROR(INDEX(Options!$F$81:$F$87,MATCH($D30,Options!$D$81:$D$87,0)),"")))
B31: Known quirks → rules · choice 2 | F31: =IF($E31<>"",$E31,IF($D31="","",IFERROR(INDEX(Options!$F$81:$F$87,MATCH($D31,Options!$D$81:$D$87,0)),"")))
B32: Known quirks → rules · choice 3 | F32: =IF($E32<>"",$E32,IF($D32="","",IFERROR(INDEX(Options!$F$81:$F$87,MATCH($D32,Options!$D$81:$D$87,0)),"")))
B33: Constraints & sensitivities · choice 1 | C33: What must not happen — stated positively where possible, with the reason where it isn't obvious. | F33: =IF($E33<>"",$E33,IF($D33="","",IFERROR(INDEX(Options!$F$88:$F$92,MATCH($D33,Options!$D$88:$D$92,0)),"")))
B34: Constraints & sensitivities · choice 2 | F34: =IF($E34<>"",$E34,IF($D34="","",IFERROR(INDEX(Options!$F$88:$F$92,MATCH($D34,Options!$D$88:$D$92,0)),"")))
B35: Constraints & sensitivities · choice 3 | F35: =IF($E35<>"",$E35,IF($D35="","",IFERROR(INDEX(Options!$F$88:$F$92,MATCH($D35,Options!$D$88:$D$92,0)),"")))
B36: The why behind the rules | C36: Explain any non-obvious rule — "this will be read aloud, so no ellipses" outperforms "no ellipses." Models generalize from reasons. | F36: =$E36 -> 0
A37: Format | B37: The output contract: shape, length, tone, and what must be in or out.
B38: Output type | C38: The deliverable's shape. Name the columns for tables, the sections for documents. | F38: =IF($E38<>"",$E38,IF($D38="","",IFERROR(INDEX(Options!$F$93:$F$107,MATCH($D38,Options!$D$93:$D$107,0)),"")))
B39: Structure rules · choice 1 | C39: The internal skeleton — where the answer sits, what every section carries. | F39: =IF($E39<>"",$E39,IF($D39="","",IFERROR(INDEX(Options!$F$108:$F$113,MATCH($D39,Options!$D$108:$D$113,0)),"")))
B40: Structure rules · choice 2 | F40: =IF($E40<>"",$E40,IF($D40="","",IFERROR(INDEX(Options!$F$108:$F$113,MATCH($D40,Options!$D$108:$D$113,0)),"")))
B41: Structure rules · choice 3 | F41: =IF($E41<>"",$E41,IF($D41="","",IFERROR(INDEX(Options!$F$108:$F$113,MATCH($D41,Options!$D$108:$D$113,0)),"")))
B42: Length cap | C42: Numeric, with a priority rule. Adjectives ("brief") are unenforceable; uncapped AI runs 2–3× long. | F42: =IF($E42<>"",$E42,IF($D42="","",IFERROR(INDEX(Options!$F$114:$F$123,MATCH($D42,Options!$D$114:$D$123,0)),"")))
B43: Tone · choice 1 | C43: Compose from the three dials below — one pick per dial reads best. | F43: =$E43 -> 0
B44: Tone · choice 2 | F44: =$E44 -> 0
B45: Formality | F45: =IF($E45<>"",$E45,IF($D45="","",IFERROR(INDEX(Options!$F$124:$F$129,MATCH($D45,Options!$D$124:$D$129,0)),"")))
B46: Directness | F46: =IF($E46<>"",$E46,IF($D46="","",IFERROR(INDEX(Options!$F$130:$F$134,MATCH($D46,Options!$D$130:$D$134,0)),"")))
B47: Warmth | F47: =IF($E47<>"",$E47,IF($D47="","",IFERROR(INDEX(Options!$F$135:$F$139,MATCH($D47,Options!$D$135:$D$139,0)),"")))
B48: Language level | C48: Vocabulary altitude and jargon policy. | F48: =IF($E48<>"",$E48,IF($D48="","",IFERROR(INDEX(Options!$F$140:$F$143,MATCH($D48,Options!$D$140:$D$143,0)),"")))
B49: Must include / must not · choice 1 | C49: The inclusion contract. | F49: =IF($E49<>"",$E49,IF($D49="","",IFERROR(INDEX(Options!$F$144:$F$149,MATCH($D49,Options!$D$144:$D$149,0)),"")))
B50: Must include / must not · choice 2 | F50: =IF($E50<>"",$E50,IF($D50="","",IFERROR(INDEX(Options!$F$144:$F$149,MATCH($D50,Options!$D$144:$D$149,0)),"")))
B51: Must include / must not · choice 3 | F51: =IF($E51<>"",$E51,IF($D51="","",IFERROR(INDEX(Options!$F$144:$F$149,MATCH($D51,Options!$D$144:$D$149,0)),"")))
B52: Variations | C52: Ask for alternatives to choose from — divergence as a dial. You become the selector, not the author. | F52: =IF($E52<>"",$E52,IF($D52="","",IFERROR(INDEX(Options!$F$150:$F$153,MATCH($D52,Options!$D$150:$D$153,0)),"")))
A53: Examples | B53: 3–5 realistic demonstrations of the task done right — the strongest steering signal there is.
B54: How many | C54: Zero-shot first on thinking models; add examples when format drifts. More helps most on formatting/labeling tasks. | F54: =IF($E54<>"",$E54,IF($D54="","",IFERROR(INDEX(Options!$F$154:$F$156,MATCH($D54,Options!$D$154:$D$156,0)),"")))
B55: Coverage · choice 1 | C55: Which cases your examples span — the model's boundary behavior copies theirs. | F55: =IF($E55<>"",$E55,IF($D55="","",IFERROR(INDEX(Options!$F$157:$F$159,MATCH($D55,Options!$D$157:$D$159,0)),"")))
B56: Coverage · choice 2 | F56: =IF($E56<>"",$E56,IF($D56="","",IFERROR(INDEX(Options!$F$157:$F$159,MATCH($D56,Options!$D$157:$D$159,0)),"")))
B57: Packaging | C57: Fence examples so they can't be mistaken for live input. | F57: =IF($E57<>"",$E57,IF($D57="","",IFERROR(INDEX(Options!$F$160:$F$161,MATCH($D57,Options!$D$160:$D$161,0)),"")))
B58: The examples | C58: Paste them. Real (redacted) beats invented; lightly-genericized real beats both. | F58: =$E58 -> 0
A59: The Out | B59: Permission to not know — re-opens the abstain option that benchmark training closed.
B60: When it applies · choice 1 | C60: The situations where not-knowing must surface instead of being papered over. | F60: =IF($E60<>"",$E60,IF($D60="","",IFERROR(INDEX(Options!$F$162:$F$167,MATCH($D60,Options!$D$162:$D$167,0)),"")))
B61: When it applies · choice 2 | F61: =IF($E61<>"",$E61,IF($D61="","",IFERROR(INDEX(Options!$F$162:$F$167,MATCH($D61,Options!$D$162:$D$167,0)),"")))
B62: When it applies · choice 3 | F62: =IF($E62<>"",$E62,IF($D62="","",IFERROR(INDEX(Options!$F$162:$F$167,MATCH($D62,Options!$D$162:$D$167,0)),"")))
B63: What to do instead | C63: The escape hatch's shape. | F63: =IF($E63<>"",$E63,IF($D63="","",IFERROR(INDEX(Options!$F$168:$F$170,MATCH($D63,Options!$D$168:$D$170,0)),"")))
A64: The Stop | B64: The scope boundary — converts open-ended capability into bounded work.
B65: Scope | C65: Numbered, in priority order — the model works down the list. | F65: =$E65 -> 0
B66: Stop rule | C66: Where work ends — or pauses for you. | F66: =IF($E66<>"",$E66,IF($D66="","",IFERROR(INDEX(Options!$F$171:$F$174,MATCH($D66,Options!$D$171:$D$174,0)),"")))
B67: Explicitly out of scope | C67: Name the adjacent things NOT to touch. | F67: =$E67 -> 0

Sheet Builder_Agent
A1: Element | B1: Attribute | C1: Guidance | D1: Your choice (dropdown) | E1: Custom text (overrides/adds) | F1: Emitted text (auto)
A2: Role | B2: The standing behavioral contract — biases hundreds of unsupervised decisions, not one answer.
B3: Working posture | C3: The job-shaped identity. Compound postures (engineer + analyst + writer) prevent single-lens blind spots. | F3: =IF($E3<>"",$E3,IF($D3="","",IFERROR(INDEX(Options!$F$175:$F$179,MATCH($D3,Options!$D$175:$D$179,0)),"")))
B4: Standing behaviors · choice 1 | C4: The rules that must survive hour three of a long run. | F4: =IF($E4<>"",$E4,IF($D4="","",IFERROR(INDEX(Options!$F$180:$F$185,MATCH($D4,Options!$D$180:$D$185,0)),"")))
B5: Standing behaviors · choice 2 | F5: =IF($E5<>"",$E5,IF($D5="","",IFERROR(INDEX(Options!$F$180:$F$185,MATCH($D5,Options!$D$180:$D$185,0)),"")))
B6: Standing behaviors · choice 3 | F6: =IF($E6<>"",$E6,IF($D6="","",IFERROR(INDEX(Options!$F$180:$F$185,MATCH($D6,Options!$D$180:$D$185,0)),"")))
B7: Standing behaviors · choice 4 | F7: =IF($E7<>"",$E7,IF($D7="","",IFERROR(INDEX(Options!$F$180:$F$185,MATCH($D7,Options!$D$180:$D$185,0)),"")))
A8: Mission ★ | B8: The goal and the definition of done — the loop's exit condition.
B9: Goal | C9: One sentence: the question to answer or the thing to produce. | F9: =$E9 -> 0
B10: Decision it supports | C10: What someone will do differently depending on the answer — filters everything downstream. | F10: =$E10 -> 0
B11: Audience & deadline | C11: Who sees it, how long they'll give it, and when it's due. | F11: =$E11 -> 0
B12: Cadence | C12: One-off or recurring changes the economics: recurring jobs get standing briefs. | F12: =IF($E12<>"",$E12,IF($D12="","",IFERROR(INDEX(Options!$F$186:$F$187,MATCH($D12,Options!$D$186:$D$187,0)),"")))
B13: Done looks like | C13: The deliverables in one line — exact and countable. | F13: =$E13 -> 0
B14: Verifiable by · choice 1 | C14: The check the agent can actually run to know it's done — the single highest-leverage line in an agentic prompt. | F14: =IF($E14<>"",$E14,IF($D14="","",IFERROR(INDEX(Options!$F$188:$F$192,MATCH($D14,Options!$D$188:$D$192,0)),"")))
B15: Verifiable by · choice 2 | F15: =IF($E15<>"",$E15,IF($D15="","",IFERROR(INDEX(Options!$F$188:$F$192,MATCH($D15,Options!$D$188:$D$192,0)),"")))
B16: Verifiable by · choice 3 | F16: =IF($E16<>"",$E16,IF($D16="","",IFERROR(INDEX(Options!$F$188:$F$192,MATCH($D16,Options!$D$188:$D$192,0)),"")))
A17: Context | B17: Tribal knowledge, written down — the agent steps on every unstated quirk.
B18: Domain in three sentences | C18: The process, the actors, what 'good' means. | F18: =$E18 -> 0
B19: Glossary (controlled vocabulary) · choice 1 | C19: Every metric as a card: numerator, denominator, grain, inclusions, exclusions. The agent will otherwise compute three subtly different versions. | F19: =IF($E19<>"",$E19,IF($D19="","",IFERROR(INDEX(Options!$F$193:$F$193,MATCH($D19,Options!$D$193:$D$193,0)),"")))
B20: Glossary (controlled vocabulary) · choice 2 | F20: =IF($E20<>"",$E20,IF($D20="","",IFERROR(INDEX(Options!$F$193:$F$193,MATCH($D20,Options!$D$193:$D$193,0)),"")))
B21: Entities & identifiers | C21: Part numbers, site names, aliases, vendor codes — spelled the way the audience spells them. | F21: =$E21 -> 0
B22: Known quirks → rules · choice 1 | C22: Things that have bitten before, each with the rule that disarms it. | F22: =IF($E22<>"",$E22,IF($D22="","",IFERROR(INDEX(Options!$F$194:$F$197,MATCH($D22,Options!$D$194:$D$197,0)),"")))
B23: Known quirks → rules · choice 2 | F23: =IF($E23<>"",$E23,IF($D23="","",IFERROR(INDEX(Options!$F$194:$F$197,MATCH($D23,Options!$D$194:$D$197,0)),"")))
B24: Targets & prior work | C24: Thresholds that matter, and files or decisions the output must stay consistent with. | F24: =$E24 -> 0
A25: Environment ★ | B25: The workspace contract: where the agent may read, where it must write, what is forbidden.
B26: Workspace | C26: Repo/folder and branch. One initiative, one folder. | F26: =$E26 -> 0
B27: Read/write boundaries · choice 1 | C27: The three-zone layout: immutable inputs, versioned outputs, regenerable scratch. | F27: =IF($E27<>"",$E27,IF($D27="","",IFERROR(INDEX(Options!$F$198:$F$200,MATCH($D27,Options!$D$198:$D$200,0)),"")))
B28: Read/write boundaries · choice 2 | F28: =IF($E28<>"",$E28,IF($D28="","",IFERROR(INDEX(Options!$F$198:$F$200,MATCH($D28,Options!$D$198:$D$200,0)),"")))
B29: Tools allowed · choice 1 | C29: Name what exists. Anything unnamed is a guess. | F29: =IF($E29<>"",$E29,IF($D29="","",IFERROR(INDEX(Options!$F$201:$F$205,MATCH($D29,Options!$D$201:$D$205,0)),"")))
B30: Tools allowed · choice 2 | F30: =IF($E30<>"",$E30,IF($D30="","",IFERROR(INDEX(Options!$F$201:$F$205,MATCH($D30,Options!$D$201:$D$205,0)),"")))
B31: Tools allowed · choice 3 | F31: =IF($E31<>"",$E31,IF($D31="","",IFERROR(INDEX(Options!$F$201:$F$205,MATCH($D31,Options!$D$201:$D$205,0)),"")))
B32: Forbidden actions · choice 1 | C32: The explicit denylist — name what would be assumed available otherwise. | F32: =IF($E32<>"",$E32,IF($D32="","",IFERROR(INDEX(Options!$F$206:$F$211,MATCH($D32,Options!$D$206:$D$211,0)),"")))
B33: Forbidden actions · choice 2 | F33: =IF($E33<>"",$E33,IF($D33="","",IFERROR(INDEX(Options!$F$206:$F$211,MATCH($D33,Options!$D$206:$D$211,0)),"")))
B34: Forbidden actions · choice 3 | F34: =IF($E34<>"",$E34,IF($D34="","",IFERROR(INDEX(Options!$F$206:$F$211,MATCH($D34,Options!$D$206:$D$211,0)),"")))
B35: Confidentiality · choice 1 | C35: What may leave the workspace, and in what form. | F35: =IF($E35<>"",$E35,IF($D35="","",IFERROR(INDEX(Options!$F$212:$F$214,MATCH($D35,Options!$D$212:$D$214,0)),"")))
B36: Confidentiality · choice 2 | F36: =IF($E36<>"",$E36,IF($D36="","",IFERROR(INDEX(Options!$F$212:$F$214,MATCH($D36,Options!$D$212:$D$214,0)),"")))
B37: Action risk policy · choice 1 | C37: How actions are triaged by consequence — the published patterns. | F37: =IF($E37<>"",$E37,IF($D37="","",IFERROR(INDEX(Options!$F$215:$F$217,MATCH($D37,Options!$D$215:$D$217,0)),"")))
B38: Action risk policy · choice 2 | F38: =IF($E38<>"",$E38,IF($D38="","",IFERROR(INDEX(Options!$F$215:$F$217,MATCH($D38,Options!$D$215:$D$217,0)),"")))
A39: Inputs | B39: The source register: each source's location, format, grain, trust level, and known issues.
B40: Source register | C40: One block per source. The skeleton below is the discipline — fill every line or write UNKNOWN. | F40: =$E40 -> 0
B41: Trust levels · choice 1 | C41: Declare per source — trust level dictates validation depth. | F41: =IF($E41<>"",$E41,IF($D41="","",IFERROR(INDEX(Options!$F$218:$F$220,MATCH($D41,Options!$D$218:$D$220,0)),"")))
B42: Trust levels · choice 2 | F42: =IF($E42<>"",$E42,IF($D42="","",IFERROR(INDEX(Options!$F$218:$F$220,MATCH($D42,Options!$D$218:$D$220,0)),"")))
B43: The UNKNOWN rule | C43: The register's cardinal rule. | F43: =IF($E43<>"",$E43,IF($D43="","",IFERROR(INDEX(Options!$F$221:$F$221,MATCH($D43,Options!$D$221:$D$221,0)),"")))
A44: Plan | B44: Bounded method: the steps in order, methods allowed, methods requiring permission.
B45: Steps | C45: Each step: what it consumes, what it produces. | F45: =$E45 -> 0
B46: Methods allowed · choice 1 | C46: Boring and reproducible. The default analytical toolkit. | F46: =IF($E46<>"",$E46,IF($D46="","",IFERROR(INDEX(Options!$F$222:$F$226,MATCH($D46,Options!$D$222:$D$226,0)),"")))
B47: Methods allowed · choice 2 | F47: =IF($E47<>"",$E47,IF($D47="","",IFERROR(INDEX(Options!$F$222:$F$226,MATCH($D47,Options!$D$222:$D$226,0)),"")))
B48: Methods allowed · choice 3 | F48: =IF($E48<>"",$E48,IF($D48="","",IFERROR(INDEX(Options!$F$222:$F$226,MATCH($D48,Options!$D$222:$D$226,0)),"")))
B49: Not without asking · choice 1 | C49: Propose at a gate; never just use. | F49: =IF($E49<>"",$E49,IF($D49="","",IFERROR(INDEX(Options!$F$227:$F$230,MATCH($D49,Options!$D$227:$D$230,0)),"")))
B50: Not without asking · choice 2 | F50: =IF($E50<>"",$E50,IF($D50="","",IFERROR(INDEX(Options!$F$227:$F$230,MATCH($D50,Options!$D$227:$D$230,0)),"")))
B51: Not without asking · choice 3 | F51: =IF($E51<>"",$E51,IF($D51="","",IFERROR(INDEX(Options!$F$227:$F$230,MATCH($D51,Options!$D$227:$D$230,0)),"")))
A52: Checks ★ | B52: Machine-evaluable verification: HARD stops the run, SOFT flags and continues.
B53: Reconciliation anchor | C53: One number from OUTSIDE the run that the results must tie to. The most important single check. | F53: =$E53 -> 0
B54: HARD checks (stop the run) · choice 1 | C54: Failure means stop, show the offending rows, and wait. | F54: =IF($E54<>"",$E54,IF($D54="","",IFERROR(INDEX(Options!$F$231:$F$240,MATCH($D54,Options!$D$231:$D$240,0)),"")))
B55: HARD checks (stop the run) · choice 2 | F55: =IF($E55<>"",$E55,IF($D55="","",IFERROR(INDEX(Options!$F$231:$F$240,MATCH($D55,Options!$D$231:$D$240,0)),"")))
B56: HARD checks (stop the run) · choice 3 | F56: =IF($E56<>"",$E56,IF($D56="","",IFERROR(INDEX(Options!$F$231:$F$240,MATCH($D56,Options!$D$231:$D$240,0)),"")))
B57: HARD checks (stop the run) · choice 4 | F57: =IF($E57<>"",$E57,IF($D57="","",IFERROR(INDEX(Options!$F$231:$F$240,MATCH($D57,Options!$D$231:$D$240,0)),"")))
B58: SOFT checks (flag and continue) · choice 1 | C58: Suspicion, not failure — logged to open items. | F58: =IF($E58<>"",$E58,IF($D58="","",IFERROR(INDEX(Options!$F$241:$F$244,MATCH($D58,Options!$D$241:$D$244,0)),"")))
B59: SOFT checks (flag and continue) · choice 2 | F59: =IF($E59<>"",$E59,IF($D59="","",IFERROR(INDEX(Options!$F$241:$F$244,MATCH($D59,Options!$D$241:$D$244,0)),"")))
B60: SOFT checks (flag and continue) · choice 3 | F60: =IF($E60<>"",$E60,IF($D60="","",IFERROR(INDEX(Options!$F$241:$F$244,MATCH($D60,Options!$D$241:$D$244,0)),"")))
A61: Outputs | B61: The deliverable contract and the audit trail — exact names, exact locations, three logs.
B62: Deliverables | C62: Numbered, with the _MMDDYY convention and what each contains. | F62: =$E62 -> 0
B63: Logs · choice 1 | C63: The three files that make a run auditable. | F63: =IF($E63<>"",$E63,IF($D63="","",IFERROR(INDEX(Options!$F$245:$F$247,MATCH($D63,Options!$D$245:$D$247,0)),"")))
B64: Logs · choice 2 | F64: =IF($E64<>"",$E64,IF($D64="","",IFERROR(INDEX(Options!$F$245:$F$247,MATCH($D64,Options!$D$245:$D$247,0)),"")))
B65: Reproducibility · choice 1 | C65: The regeneration guarantee. | F65: =IF($E65<>"",$E65,IF($D65="","",IFERROR(INDEX(Options!$F$248:$F$250,MATCH($D65,Options!$D$248:$D$250,0)),"")))
B66: Reproducibility · choice 2 | F66: =IF($E66<>"",$E66,IF($D66="","",IFERROR(INDEX(Options!$F$248:$F$250,MATCH($D66,Options!$D$248:$D$250,0)),"")))
A67: Process & Gates ★ | B67: Phases with human checkpoints at the cheap-error points — and the autonomy rules between them.
B68: Phases | C68: Phase 0 is always intake: the agent restates the mission and its assumptions in its own words. | F68: =$E68 -> 0
B69: Gates · choice 1 | C69: Human checkpoints, in ascending cost of the error they catch. | F69: =IF($E69<>"",$E69,IF($D69="","",IFERROR(INDEX(Options!$F$251:$F$255,MATCH($D69,Options!$D$251:$D$255,0)),"")))
B70: Gates · choice 2 | F70: =IF($E70<>"",$E70,IF($D70="","",IFERROR(INDEX(Options!$F$251:$F$255,MATCH($D70,Options!$D$251:$D$255,0)),"")))
B71: Gates · choice 3 | F71: =IF($E71<>"",$E71,IF($D71="","",IFERROR(INDEX(Options!$F$251:$F$255,MATCH($D71,Options!$D$251:$D$255,0)),"")))
B72: Autonomy rules · choice 1 | C72: Both halves matter: without 'proceed' you built a slow chatbot; without 'stop' you built a liability. | F72: =IF($E72<>"",$E72,IF($D72="","",IFERROR(INDEX(Options!$F$256:$F$262,MATCH($D72,Options!$D$256:$D$262,0)),"")))
B73: Autonomy rules · choice 2 | F73: =IF($E73<>"",$E73,IF($D73="","",IFERROR(INDEX(Options!$F$256:$F$262,MATCH($D73,Options!$D$256:$D$262,0)),"")))
B74: Autonomy rules · choice 3 | F74: =IF($E74<>"",$E74,IF($D74="","",IFERROR(INDEX(Options!$F$256:$F$262,MATCH($D74,Options!$D$256:$D$262,0)),"")))
B75: Autonomy rules · choice 4 | F75: =IF($E75<>"",$E75,IF($D75="","",IFERROR(INDEX(Options!$F$256:$F$262,MATCH($D75,Options!$D$256:$D$262,0)),"")))
B76: Autonomy level | C76: A deliberate design choice, separate from capability. Named by the role you keep — pick the lowest level that still gets the job done. | F76: =IF($E76<>"",$E76,IF($D76="","",IFERROR(INDEX(Options!$F$263:$F$267,MATCH($D76,Options!$D$263:$D$267,0)),"")))
A77: Rules | B77: The non-negotiables — short, absolute, few — that must survive a long context.
B78: Invariants · choice 1 | C78: The standard set — prune to what this job actually needs. | F78: =IF($E78<>"",$E78,IF($D78="","",IFERROR(INDEX(Options!$F$268:$F$273,MATCH($D78,Options!$D$268:$D$273,0)),"")))
B79: Invariants · choice 2 | F79: =IF($E79<>"",$E79,IF($D79="","",IFERROR(INDEX(Options!$F$268:$F$273,MATCH($D79,Options!$D$268:$D$273,0)),"")))
B80: Invariants · choice 3 | F80: =IF($E80<>"",$E80,IF($D80="","",IFERROR(INDEX(Options!$F$268:$F$273,MATCH($D80,Options!$D$268:$D$273,0)),"")))
B81: Invariants · choice 4 | F81: =IF($E81<>"",$E81,IF($D81="","",IFERROR(INDEX(Options!$F$268:$F$273,MATCH($D81,Options!$D$268:$D$273,0)),"")))
A82: Quality Bar | B82: The definition of done as a checklist the agent must satisfy — and you can audit in sixty seconds.
B83: Definition of done · choice 1 | C83: Tick-able, evidence-able items. | F83: =IF($E83<>"",$E83,IF($D83="","",IFERROR(INDEX(Options!$F$274:$F$279,MATCH($D83,Options!$D$274:$D$279,0)),"")))
B84: Definition of done · choice 2 | F84: =IF($E84<>"",$E84,IF($D84="","",IFERROR(INDEX(Options!$F$274:$F$279,MATCH($D84,Options!$D$274:$D$279,0)),"")))
B85: Definition of done · choice 3 | F85: =IF($E85<>"",$E85,IF($D85="","",IFERROR(INDEX(Options!$F$274:$F$279,MATCH($D85,Options!$D$274:$D$279,0)),"")))
A86: Reporting | B86: The fixed shape of the final message: status, headline, evidence, open items — under 25 lines.
B87: Report shape · choice 1 | C87: The standard six lines — deselect only what genuinely doesn't apply. | F87: =IF($E87<>"",$E87,IF($D87="","",IFERROR(INDEX(Options!$F$280:$F$285,MATCH($D87,Options!$D$280:$D$285,0)),"")))
B88: Report shape · choice 2 | F88: =IF($E88<>"",$E88,IF($D88="","",IFERROR(INDEX(Options!$F$280:$F$285,MATCH($D88,Options!$D$280:$D$285,0)),"")))
B89: Report shape · choice 3 | F89: =IF($E89<>"",$E89,IF($D89="","",IFERROR(INDEX(Options!$F$280:$F$285,MATCH($D89,Options!$D$280:$D$285,0)),"")))
B90: Report shape · choice 4 | F90: =IF($E90<>"",$E90,IF($D90="","",IFERROR(INDEX(Options!$F$280:$F$285,MATCH($D90,Options!$D$280:$D$285,0)),"")))
B91: Report discipline · choice 1 | C91: The rules that keep reports readable and honest. | F91: =IF($E91<>"",$E91,IF($D91="","",IFERROR(INDEX(Options!$F$286:$F$287,MATCH($D91,Options!$D$286:$D$287,0)),"")))
B92: Report discipline · choice 2 | F92: =IF($E92<>"",$E92,IF($D92="","",IFERROR(INDEX(Options!$F$286:$F$287,MATCH($D92,Options!$D$286:$D$287,0)),"")))

Sheet Prompt_Gen
A1: ASSEMBLED GENERATIVE PROMPT — copy cell A4 (it recalculates from Builder_Gen)
A2: Fill the yellow cells on the builder sheet; blank rows are skipped automatically. Search the result for {{ — unfilled placeholders mean you are not done.
A4: =_xlfn.TEXTJOIN(CHAR(10)&CHAR(10),TRUE(),$C$4,$C$5,$C$6,$C$7,$C$8,$C$9,$C$10) -> <role> You are a careful analyst. You never invent facts or numbers — missing is missing. </role> <task> Answer: {{the question, with metric and period — e.g., "what is X by group for Q2 vs the target"}}? Example (replace): what is the return rate by site for Q2 vs the 2.0% target? </task> | C4: =IF(_xlfn.TEXTJOIN(CHAR(10),TRUE(),Builder_Gen!$F$2:$F$16)="","","<role>"&CHAR(10)&_xlfn.TEXTJOIN(CHAR(10),TRUE(),Builder_Gen!$F$2:$F$16)&CHAR(10)&"</role>") -> <role> You are a careful analyst. You never invent facts or numbers — missing is missing. </role>
C5: =IF(_xlfn.TEXTJOIN(CHAR(10),TRUE(),Builder_Gen!$F$17:$F$25)="","","<task>"&CHAR(10)&_xlfn.TEXTJOIN(CHAR(10),TRUE(),Builder_Gen!$F$17:$F$25)&CHAR(10)&"</task>") -> <task> Answer: {{the question, with metric and period — e.g., "what is X by group for Q2 vs the target"}}? Example (replace): what is the return rate by site for Q2 vs the 2.0% target? </task>
C6: =IF(_xlfn.TEXTJOIN(CHAR(10),TRUE(),Builder_Gen!$F$26:$F$36)="","","<context>"&CHAR(10)&_xlfn.TEXTJOIN(CHAR(10),TRUE(),Builder_Gen!$F$26:$F$36)&CHAR(10)&"</context>")
C7: =IF(_xlfn.TEXTJOIN(CHAR(10),TRUE(),Builder_Gen!$F$37:$F$52)="","","<format>"&CHAR(10)&_xlfn.TEXTJOIN(CHAR(10),TRUE(),Builder_Gen!$F$37:$F$52)&CHAR(10)&"</format>")
C8: =IF(_xlfn.TEXTJOIN(CHAR(10),TRUE(),Builder_Gen!$F$53:$F$58)="","","<examples>"&CHAR(10)&_xlfn.TEXTJOIN(CHAR(10),TRUE(),Builder_Gen!$F$53:$F$58)&CHAR(10)&"</examples>")
C9: =IF(_xlfn.TEXTJOIN(CHAR(10),TRUE(),Builder_Gen!$F$59:$F$63)="","","<uncertainty_rules>"&CHAR(10)&_xlfn.TEXTJOIN(CHAR(10),TRUE(),Builder_Gen!$F$59:$F$63)&CHAR(10)&"</uncertainty_rules>")
C10: =IF(_xlfn.TEXTJOIN(CHAR(10),TRUE(),Builder_Gen!$F$64:$F$67)="","","<scope>"&CHAR(10)&_xlfn.TEXTJOIN(CHAR(10),TRUE(),Builder_Gen!$F$64:$F$67)&CHAR(10)&"</scope>")

Sheet Prompt_Agent
A1: ASSEMBLED AGENTIC PROMPT — copy cell A4 (it recalculates from Builder_Agent)
A2: Fill the yellow cells on the builder sheet; blank rows are skipped automatically. Search the result for {{ — unfilled placeholders mean you are not done.
A4: =_xlfn.TEXTJOIN(CHAR(10)&CHAR(10),TRUE(),$C$4,$C$5,$C$6,$C$7,$C$8,$C$9,$C$10,$C$11,$C$12,$C$13,$C$14,$C$15) | C4: =IF(_xlfn.TEXTJOIN(CHAR(10),TRUE(),Builder_Agent!$F$2:$F$7)="","","<role>"&CHAR(10)&_xlfn.TEXTJOIN(CHAR(10),TRUE(),Builder_Agent!$F$2:$F$7)&CHAR(10)&"</role>")
C5: =IF(_xlfn.TEXTJOIN(CHAR(10),TRUE(),Builder_Agent!$F$8:$F$16)="","","<mission>"&CHAR(10)&_xlfn.TEXTJOIN(CHAR(10),TRUE(),Builder_Agent!$F$8:$F$16)&CHAR(10)&"</mission>")
C6: =IF(_xlfn.TEXTJOIN(CHAR(10),TRUE(),Builder_Agent!$F$17:$F$24)="","","<context>"&CHAR(10)&_xlfn.TEXTJOIN(CHAR(10),TRUE(),Builder_Agent!$F$17:$F$24)&CHAR(10)&"</context>")
C7: =IF(_xlfn.TEXTJOIN(CHAR(10),TRUE(),Builder_Agent!$F$25:$F$38)="","","<environment>"&CHAR(10)&_xlfn.TEXTJOIN(CHAR(10),TRUE(),Builder_Agent!$F$25:$F$38)&CHAR(10)&"</environment>")
C8: =IF(_xlfn.TEXTJOIN(CHAR(10),TRUE(),Builder_Agent!$F$39:$F$43)="","","<inputs>"&CHAR(10)&_xlfn.TEXTJOIN(CHAR(10),TRUE(),Builder_Agent!$F$39:$F$43)&CHAR(10)&"</inputs>")
C9: =IF(_xlfn.TEXTJOIN(CHAR(10),TRUE(),Builder_Agent!$F$44:$F$51)="","","<plan>"&CHAR(10)&_xlfn.TEXTJOIN(CHAR(10),TRUE(),Builder_Agent!$F$44:$F$51)&CHAR(10)&"</plan>")
C10: =IF(_xlfn.TEXTJOIN(CHAR(10),TRUE(),Builder_Agent!$F$52:$F$60)="","","<checks>"&CHAR(10)&_xlfn.TEXTJOIN(CHAR(10),TRUE(),Builder_Agent!$F$52:$F$60)&CHAR(10)&"</checks>")
C11: =IF(_xlfn.TEXTJOIN(CHAR(10),TRUE(),Builder_Agent!$F$61:$F$66)="","","<outputs>"&CHAR(10)&_xlfn.TEXTJOIN(CHAR(10),TRUE(),Builder_Agent!$F$61:$F$66)&CHAR(10)&"</outputs>")
C12: =IF(_xlfn.TEXTJOIN(CHAR(10),TRUE(),Builder_Agent!$F$67:$F$76)="","","<process>"&CHAR(10)&_xlfn.TEXTJOIN(CHAR(10),TRUE(),Builder_Agent!$F$67:$F$76)&CHAR(10)&"</process>")
C13: =IF(_xlfn.TEXTJOIN(CHAR(10),TRUE(),Builder_Agent!$F$77:$F$81)="","","<rules>"&CHAR(10)&_xlfn.TEXTJOIN(CHAR(10),TRUE(),Builder_Agent!$F$77:$F$81)&CHAR(10)&"</rules>")
C14: =IF(_xlfn.TEXTJOIN(CHAR(10),TRUE(),Builder_Agent!$F$82:$F$85)="","","<quality_bar>"&CHAR(10)&_xlfn.TEXTJOIN(CHAR(10),TRUE(),Builder_Agent!$F$82:$F$85)&CHAR(10)&"</quality_bar>")
C15: =IF(_xlfn.TEXTJOIN(CHAR(10),TRUE(),Builder_Agent!$F$86:$F$92)="","","<reporting>"&CHAR(10)&_xlfn.TEXTJOIN(CHAR(10),TRUE(),Builder_Agent!$F$86:$F$92)&CHAR(10)&"</reporting>")

Sheet Taxonomy
A1: Mode | B1: Element | C1: OOP | D1: Definition | E1: Prevents
A2: generative | B2: Role | C2: class Role extends PromptElement | D2: Who is answering: identity, expertise posture, and checkable behavioral commitments. | E2: the generic-assistant voice; mid-distribution, hedge-everything output.
A3: generative | B3: Task | C3: class Task extends PromptElement | D3: The single clear ask: verb + object + audience + success criterion. | E3: wandering output — ten observations and no answer.
A4: generative | B4: Context | C4: class Context extends PromptElement | D4: Everything true in your world that isn't in the training data — material, definitions, quirks, constraints, and the reasons behind rules. | E4: generically-right, specifically-wrong output — the plausible number with your company's name on it.
A5: generative | B5: Format | C5: class Format extends PromptElement | D5: The output contract: shape, length, tone, and what must be in or out. | E5: the 3×-too-long draft; the buried answer; output you must re-shape by hand.
A6: generative | B6: Examples | C6: class Examples extends PromptElement | D6: 3–5 realistic demonstrations of the task done right — the strongest steering signal there is. | E6: the model guessing your standard from the internet's average; format drift across runs.
A7: generative | B7: The Out | C7: class TheOut extends SafetyValve | D7: Permission to not know — re-opens the abstain option that benchmark training closed. | E7: confident invention — the signature failure of factual work.
A8: generative | B8: The Stop | C8: class TheStop extends SafetyValve | D8: The scope boundary — converts open-ended capability into bounded work. | E8: scope sprawl; work continuing past the point of usefulness.
A9: agentic | B9: Role | C9: class AgentRole extends Role | D9: The standing behavioral contract — biases hundreds of unsupervised decisions, not one answer. | E9: an agent that improvises its professional standards mid-run.
A10: agentic | B10: Mission | C10: class Mission extends Task // + definitionOfDone | D10: The goal and the definition of done — the loop's exit condition. | E10: the agent deciding for itself what finished means — plausible activity, indefinitely.
A11: agentic | B11: Context | C11: class AgentContext extends Context // coverage pressure | D11: Tribal knowledge, written down — the agent steps on every unstated quirk. | E11: silent invented fixes — the most expensive agent error, because they look like diligence.
A12: agentic | B12: Environment | C12: class Environment extends PromptElement // NEW IN KIND | D12: The workspace contract: where the agent may read, where it must write, what is forbidden. | E12: the agent 'helpfully' editing your master file or wandering outside its folder.
... A20: agentic | B20: Reporting | C20: class Reporting extends Format // the interface back to you | D20: The fixed shape of the final message: status, headline, evidence, open items — under 25 lines. | E20: a narrative essay where a status should be.
